Blink_LEDS/Blink_LEDS.v
//Verilog
module Blink_LED
  #(parameter COUNT_10HZ = 1250000,
    parameter COUNT_5HZ = 2500000,
    parameter COUNT_2HZ = 6250000,
    parameter COUNT_1HZ = 12500000)
  (input CLK,
   output reg LED1 = 1'b0,
   output reg LED2 = 1'b0,
   output reg LED3 = 1'b0,
   output reg LED4 = 1'b0);
  
reg [31:0] r_Count_10Hz = 0;
  reg [31:0] r_Count_5Hz = 0;
  reg [31:0] r_Count_2Hz = 0;
  reg [31:0] r_Count_1Hz = 0;

always @(posedge CLK)
begin
  if(r_Count_10Hz == COUNT_10HZ)
  begin
    LED1 <= ~LED1;
    r_Count_10Hz <=0;
  end
  else
    r_Count_10Hz <= r_Count_10Hz + 1;
end
  
always @(posedge CLK)
begin
  if(r_Count_5Hz == COUNT_5HZ)
  begin
    LED2 <= ~LED2;
    r_Count_5Hz <= 0;
  end
  else
    r_Count_5Hz <= r_Count_5Hz + 1;
end
  
always @(posedge CLK)
begin
  if(r_Count_2Hz == COUNT_2HZ)
  begin
    LED3 <= ~LED3;
    r_Count_2Hz <=0;
  end
  else
    r_Count_2Hz <= r_Count_2Hz + 1;
end
  
always @(posedge CLK)
begin
  if(r_Count_1Hz == COUNT_1HZ)
  begin
    LED4 <= ~LED4;
    r_Count_1Hz <=0;
  end
  else
    r_Count_1Hz <= r_Count_1Hz + 1;
end
  
endmodule

FILES/TESTBENCHES/Blink_LED/testbench.sv
// Code testbench here
module Blink_LED_TB();
  
  reg r_Clock = 1'b0;
  
  always #1 r_Clock <= ~r_Clock;
  
  Blink_LED #(.COUNT_10HZ(5),
              .COUNT_5HZ(10),
              .COUNT_2HZ(25),
              .COUNT_1HZ(30)) UUT
  (.CLK(r_Clock),
   .LED1(),
   .LED2(),
   .LED3(),
   .LED4());
  
  initial
    begin
      $display("Starting Testbench...");
      #200;
      $finish();
    end
  
  initial
    begin
      $dumpfile("dump.vcd");
      $dumpvars(0);
    end
  
endmodule

FILES/TESTBENCHES/Blink_LED/dump.vcd
$date
	Wed Jun 26 16:27:52 2024
$end

$version
	Synopsys VCS version U-2023.03-SP2_Full64
$end

$timescale
	1ns
$end

$comment Csum: 1 9de2cf86c66153a8 $end


$scope module Blink_LED_TB $end
$var reg 1 ! r_Clock $end

$scope module UUT $end
$var wire 1 ! CLK $end
$var reg 1 " LED1 $end
$var reg 1 # LED2 $end
$var reg 1 $ LED3 $end
$var reg 1 % LED4 $end
$var reg 32 & r_Count_10Hz [31:0] $end
$var reg 32 ' r_Count_5Hz [31:0] $end
$var reg 32 ( r_Count_2Hz [31:0] $end
$var reg 32 ) r_Count_1Hz [31:0] $end
$upscope $end

$upscope $end

$enddefinitions $end

#0
$dumpvars
0"
0#
0$
0%
0!
b00000000000000000000000000000000 &
b00000000000000000000000000000000 )
b00000000000000000000000000000000 (
b00000000000000000000000000000000 '
$end
#1
1!
b00000000000000000000000000000001 &
b00000000000000000000000000000001 '
b00000000000000000000000000000001 (
b00000000000000000000000000000001 )
#2
0!
#3
1!
b00000000000000000000000000000010 &
b00000000000000000000000000000010 '
b00000000000000000000000000000010 (
b00000000000000000000000000000010 )
#4
0!
#5
1!
b00000000000000000000000000000011 &
b00000000000000000000000000000011 '
b00000000000000000000000000000011 (
b00000000000000000000000000000011 )
#6
0!
#7
1!
b00000000000000000000000000000100 &
b00000000000000000000000000000100 '
b00000000000000000000000000000100 (
b00000000000000000000000000000100 )
#8
0!
#9
1!
b00000000000000000000000000000101 &
b00000000000000000000000000000101 '
b00000000000000000000000000000101 (
b00000000000000000000000000000101 )
#10
0!
#11
1!
1"
b00000000000000000000000000000000 &
b00000000000000000000000000000110 '
b00000000000000000000000000000110 (
b00000000000000000000000000000110 )
#12
0!
#13
1!
b00000000000000000000000000000001 &
b00000000000000000000000000000111 '
b00000000000000000000000000000111 (
b00000000000000000000000000000111 )
#14
0!
#15
1!
b00000000000000000000000000000010 &
b00000000000000000000000000001000 '
b00000000000000000000000000001000 (
b00000000000000000000000000001000 )
#16
0!
#17
1!
b00000000000000000000000000000011 &
b00000000000000000000000000001001 '
b00000000000000000000000000001001 (
b00000000000000000000000000001001 )
#18
0!
#19
1!
b00000000000000000000000000000100 &
b00000000000000000000000000001010 '
b00000000000000000000000000001010 (
b00000000000000000000000000001010 )
#20
0!
#21
1!
b00000000000000000000000000000101 &
1#
b00000000000000000000000000000000 '
b00000000000000000000000000001011 (
b00000000000000000000000000001011 )
#22
0!
#23
1!
0"
b00000000000000000000000000000000 &
b00000000000000000000000000000001 '
b00000000000000000000000000001100 (
b00000000000000000000000000001100 )
#24
0!
#25
1!
b00000000000000000000000000000001 &
b00000000000000000000000000000010 '
b00000000000000000000000000001101 (
b00000000000000000000000000001101 )
#26
0!
#27
1!
b00000000000000000000000000000010 &
b00000000000000000000000000000011 '
b00000000000000000000000000001110 (
b00000000000000000000000000001110 )
#28
0!
#29
1!
b00000000000000000000000000000011 &
b00000000000000000000000000000100 '
b00000000000000000000000000001111 (
b00000000000000000000000000001111 )
#30
0!
#31
1!
b00000000000000000000000000000100 &
b00000000000000000000000000000101 '
b00000000000000000000000000010000 (
b00000000000000000000000000010000 )
#32
0!
#33
1!
b00000000000000000000000000000101 &
b00000000000000000000000000000110 '
b00000000000000000000000000010001 (
b00000000000000000000000000010001 )
#34
0!
#35
1!
1"
b00000000000000000000000000000000 &
b00000000000000000000000000000111 '
b00000000000000000000000000010010 (
b00000000000000000000000000010010 )
#36
0!
#37
1!
b00000000000000000000000000000001 &
b00000000000000000000000000001000 '
b00000000000000000000000000010011 (
b00000000000000000000000000010011 )
#38
0!
#39
1!
b00000000000000000000000000000010 &
b00000000000000000000000000001001 '
b00000000000000000000000000010100 (
b00000000000000000000000000010100 )
#40
0!
#41
1!
b00000000000000000000000000000011 &
b00000000000000000000000000001010 '
b00000000000000000000000000010101 (
b00000000000000000000000000010101 )
#42
0!
#43
1!
b00000000000000000000000000000100 &
0#
b00000000000000000000000000000000 '
b00000000000000000000000000010110 (
b00000000000000000000000000010110 )
#44
0!
#45
1!
b00000000000000000000000000000101 &
b00000000000000000000000000000001 '
b00000000000000000000000000010111 (
b00000000000000000000000000010111 )
#46
0!
#47
1!
0"
b00000000000000000000000000000000 &
b00000000000000000000000000000010 '
b00000000000000000000000000011000 (
b00000000000000000000000000011000 )
#48
0!
#49
1!
b00000000000000000000000000000001 &
b00000000000000000000000000000011 '
b00000000000000000000000000011001 (
b00000000000000000000000000011001 )
#50
0!
#51
1!
b00000000000000000000000000000010 &
b00000000000000000000000000000100 '
1$
b00000000000000000000000000000000 (
b00000000000000000000000000011010 )
#52
0!
#53
1!
b00000000000000000000000000000011 &
b00000000000000000000000000000101 '
b00000000000000000000000000000001 (
b00000000000000000000000000011011 )
#54
0!
#55
1!
b00000000000000000000000000000100 &
b00000000000000000000000000000110 '
b00000000000000000000000000000010 (
b00000000000000000000000000011100 )
#56
0!
#57
1!
b00000000000000000000000000000101 &
b00000000000000000000000000000111 '
b00000000000000000000000000000011 (
b00000000000000000000000000011101 )
#58
0!
#59
1!
1"
b00000000000000000000000000000000 &
b00000000000000000000000000001000 '
b00000000000000000000000000000100 (
b00000000000000000000000000011110 )
#60
0!
#61
1!
b00000000000000000000000000000001 &
b00000000000000000000000000001001 '
b00000000000000000000000000000101 (
1%
b00000000000000000000000000000000 )
#62
0!
#63
1!
b00000000000000000000000000000010 &
b00000000000000000000000000001010 '
b00000000000000000000000000000110 (
b00000000000000000000000000000001 )
#64
0!
#65
1!
b00000000000000000000000000000011 &
1#
b00000000000000000000000000000000 '
b00000000000000000000000000000111 (
b00000000000000000000000000000010 )
#66
0!
#67
1!
b00000000000000000000000000000100 &
b00000000000000000000000000000001 '
b00000000000000000000000000001000 (
b00000000000000000000000000000011 )
#68
0!
#69
1!
b00000000000000000000000000000101 &
b00000000000000000000000000000010 '
b00000000000000000000000000001001 (
b00000000000000000000000000000100 )
#70
0!
#71
1!
0"
b00000000000000000000000000000000 &
b00000000000000000000000000000011 '
b00000000000000000000000000001010 (
b00000000000000000000000000000101 )
#72
0!
#73
1!
b00000000000000000000000000000001 &
b00000000000000000000000000000100 '
b00000000000000000000000000001011 (
b00000000000000000000000000000110 )
#74
0!
#75
1!
b00000000000000000000000000000010 &
b00000000000000000000000000000101 '
b00000000000000000000000000001100 (
b00000000000000000000000000000111 )
#76
0!
#77
1!
b00000000000000000000000000000011 &
b00000000000000000000000000000110 '
b00000000000000000000000000001101 (
b00000000000000000000000000001000 )
#78
0!
#79
1!
b00000000000000000000000000000100 &
b00000000000000000000000000000111 '
b00000000000000000000000000001110 (
b00000000000000000000000000001001 )
#80
0!
#81
1!
b00000000000000000000000000000101 &
b00000000000000000000000000001000 '
b00000000000000000000000000001111 (
b00000000000000000000000000001010 )
#82
0!
#83
1!
1"
b00000000000000000000000000000000 &
b00000000000000000000000000001001 '
b00000000000000000000000000010000 (
b00000000000000000000000000001011 )
#84
0!
#85
1!
b00000000000000000000000000000001 &
b00000000000000000000000000001010 '
b00000000000000000000000000010001 (
b00000000000000000000000000001100 )
#86
0!
#87
1!
b00000000000000000000000000000010 &
0#
b00000000000000000000000000000000 '
b00000000000000000000000000010010 (
b00000000000000000000000000001101 )
#88
0!
#89
1!
b00000000000000000000000000000011 &
b00000000000000000000000000000001 '
b00000000000000000000000000010011 (
b00000000000000000000000000001110 )
#90
0!
#91
1!
b00000000000000000000000000000100 &
b00000000000000000000000000000010 '
b00000000000000000000000000010100 (
b00000000000000000000000000001111 )
#92
0!
#93
1!
b00000000000000000000000000000101 &
b00000000000000000000000000000011 '
b00000000000000000000000000010101 (
b00000000000000000000000000010000 )
#94
0!
#95
1!
0"
b00000000000000000000000000000000 &
b00000000000000000000000000000100 '
b00000000000000000000000000010110 (
b00000000000000000000000000010001 )
#96
0!
#97
1!
b00000000000000000000000000000001 &
b00000000000000000000000000000101 '
b00000000000000000000000000010111 (
b00000000000000000000000000010010 )
#98
0!
#99
1!
b00000000000000000000000000000010 &
b00000000000000000000000000000110 '
b00000000000000000000000000011000 (
b00000000000000000000000000010011 )
#100
0!
#101
1!
b00000000000000000000000000000011 &
b00000000000000000000000000000111 '
b00000000000000000000000000011001 (
b00000000000000000000000000010100 )
#102
0!
#103
1!
b00000000000000000000000000000100 &
b00000000000000000000000000001000 '
0$
b00000000000000000000000000000000 (
b00000000000000000000000000010101 )
#104
0!
#105
1!
b00000000000000000000000000000101 &
b00000000000000000000000000001001 '
b00000000000000000000000000000001 (
b00000000000000000000000000010110 )
#106
0!
#107
1!
1"
b00000000000000000000000000000000 &
b00000000000000000000000000001010 '
b00000000000000000000000000000010 (
b00000000000000000000000000010111 )
#108
0!
#109
1!
b00000000000000000000000000000001 &
1#
b00000000000000000000000000000000 '
b00000000000000000000000000000011 (
b00000000000000000000000000011000 )
#110
0!
#111
1!
b00000000000000000000000000000010 &
b00000000000000000000000000000001 '
b00000000000000000000000000000100 (
b00000000000000000000000000011001 )
#112
0!
#113
1!
b00000000000000000000000000000011 &
b00000000000000000000000000000010 '
b00000000000000000000000000000101 (
b00000000000000000000000000011010 )
#114
0!
#115
1!
b00000000000000000000000000000100 &
b00000000000000000000000000000011 '
b00000000000000000000000000000110 (
b00000000000000000000000000011011 )
#116
0!
#117
1!
b00000000000000000000000000000101 &
b00000000000000000000000000000100 '
b00000000000000000000000000000111 (
b00000000000000000000000000011100 )
#118
0!
#119
1!
0"
b00000000000000000000000000000000 &
b00000000000000000000000000000101 '
b00000000000000000000000000001000 (
b00000000000000000000000000011101 )
#120
0!
#121
1!
b00000000000000000000000000000001 &
b00000000000000000000000000000110 '
b00000000000000000000000000001001 (
b00000000000000000000000000011110 )
#122
0!
#123
1!
b00000000000000000000000000000010 &
b00000000000000000000000000000111 '
b00000000000000000000000000001010 (
0%
b00000000000000000000000000000000 )
#124
0!
#125
1!
b00000000000000000000000000000011 &
b00000000000000000000000000001000 '
b00000000000000000000000000001011 (
b00000000000000000000000000000001 )
#126
0!
#127
1!
b00000000000000000000000000000100 &
b00000000000000000000000000001001 '
b00000000000000000000000000001100 (
b00000000000000000000000000000010 )
#128
0!
#129
1!
b00000000000000000000000000000101 &
b00000000000000000000000000001010 '
b00000000000000000000000000001101 (
b00000000000000000000000000000011 )
#130
0!
#131
1!
1"
b00000000000000000000000000000000 &
0#
b00000000000000000000000000000000 '
b00000000000000000000000000001110 (
b00000000000000000000000000000100 )
#132
0!
#133
1!
b00000000000000000000000000000001 &
b00000000000000000000000000000001 '
b00000000000000000000000000001111 (
b00000000000000000000000000000101 )
#134
0!
#135
1!
b00000000000000000000000000000010 &
b00000000000000000000000000000010 '
b00000000000000000000000000010000 (
b00000000000000000000000000000110 )
#136
0!
#137
1!
b00000000000000000000000000000011 &
b00000000000000000000000000000011 '
b00000000000000000000000000010001 (
b00000000000000000000000000000111 )
#138
0!
#139
1!
b00000000000000000000000000000100 &
b00000000000000000000000000000100 '
b00000000000000000000000000010010 (
b00000000000000000000000000001000 )
#140
0!
#141
1!
b00000000000000000000000000000101 &
b00000000000000000000000000000101 '
b00000000000000000000000000010011 (
b00000000000000000000000000001001 )
#142
0!
#143
1!
0"
b00000000000000000000000000000000 &
b00000000000000000000000000000110 '
b00000000000000000000000000010100 (
b00000000000000000000000000001010 )
#144
0!
#145
1!
b00000000000000000000000000000001 &
b00000000000000000000000000000111 '
b00000000000000000000000000010101 (
b00000000000000000000000000001011 )
#146
0!
#147
1!
b00000000000000000000000000000010 &
b00000000000000000000000000001000 '
b00000000000000000000000000010110 (
b00000000000000000000000000001100 )
#148
0!
#149
1!
b00000000000000000000000000000011 &
b00000000000000000000000000001001 '
b00000000000000000000000000010111 (
b00000000000000000000000000001101 )
#150
0!
#151
1!
b00000000000000000000000000000100 &
b00000000000000000000000000001010 '
b00000000000000000000000000011000 (
b00000000000000000000000000001110 )
#152
0!
#153
1!
b00000000000000000000000000000101 &
1#
b00000000000000000000000000000000 '
b00000000000000000000000000011001 (
b00000000000000000000000000001111 )
#154
0!
#155
1!
1"
b00000000000000000000000000000000 &
b00000000000000000000000000000001 '
1$
b00000000000000000000000000000000 (
b00000000000000000000000000010000 )
#156
0!
#157
1!
b00000000000000000000000000000001 &
b00000000000000000000000000000010 '
b00000000000000000000000000000001 (
b00000000000000000000000000010001 )
#158
0!
#159
1!
b00000000000000000000000000000010 &
b00000000000000000000000000000011 '
b00000000000000000000000000000010 (
b00000000000000000000000000010010 )
#160
0!
#161
1!
b00000000000000000000000000000011 &
b00000000000000000000000000000100 '
b00000000000000000000000000000011 (
b00000000000000000000000000010011 )
#162
0!
#163
1!
b00000000000000000000000000000100 &
b00000000000000000000000000000101 '
b00000000000000000000000000000100 (
b00000000000000000000000000010100 )
#164
0!
#165
1!
b00000000000000000000000000000101 &
b00000000000000000000000000000110 '
b00000000000000000000000000000101 (
b00000000000000000000000000010101 )
#166
0!
#167
1!
0"
b00000000000000000000000000000000 &
b00000000000000000000000000000111 '
b00000000000000000000000000000110 (
b00000000000000000000000000010110 )
#168
0!
#169
1!
b00000000000000000000000000000001 &
b00000000000000000000000000001000 '
b00000000000000000000000000000111 (
b00000000000000000000000000010111 )
#170
0!
#171
1!
b00000000000000000000000000000010 &
b00000000000000000000000000001001 '
b00000000000000000000000000001000 (
b00000000000000000000000000011000 )
#172
0!
#173
1!
b00000000000000000000000000000011 &
b00000000000000000000000000001010 '
b00000000000000000000000000001001 (
b00000000000000000000000000011001 )
#174
0!
#175
1!
b00000000000000000000000000000100 &
0#
b00000000000000000000000000000000 '
b00000000000000000000000000001010 (
b00000000000000000000000000011010 )
#176
0!
#177
1!
b00000000000000000000000000000101 &
b00000000000000000000000000000001 '
b00000000000000000000000000001011 (
b00000000000000000000000000011011 )
#178
0!
#179
1!
1"
b00000000000000000000000000000000 &
b00000000000000000000000000000010 '
b00000000000000000000000000001100 (
b00000000000000000000000000011100 )
#180
0!
#181
1!
b00000000000000000000000000000001 &
b00000000000000000000000000000011 '
b00000000000000000000000000001101 (
b00000000000000000000000000011101 )
#182
0!
#183
1!
b00000000000000000000000000000010 &
b00000000000000000000000000000100 '
b00000000000000000000000000001110 (
b00000000000000000000000000011110 )
#184
0!
#185
1!
b00000000000000000000000000000011 &
b00000000000000000000000000000101 '
b00000000000000000000000000001111 (
1%
b00000000000000000000000000000000 )
#186
0!
#187
1!
b00000000000000000000000000000100 &
b00000000000000000000000000000110 '
b00000000000000000000000000010000 (
b00000000000000000000000000000001 )
#188
0!
#189
1!
b00000000000000000000000000000101 &
b00000000000000000000000000000111 '
b00000000000000000000000000010001 (
b00000000000000000000000000000010 )
#190
0!
#191
1!
0"
b00000000000000000000000000000000 &
b00000000000000000000000000001000 '
b00000000000000000000000000010010 (
b00000000000000000000000000000011 )
#192
0!
#193
1!
b00000000000000000000000000000001 &
b00000000000000000000000000001001 '
b00000000000000000000000000010011 (
b00000000000000000000000000000100 )
#194
0!
#195
1!
b00000000000000000000000000000010 &
b00000000000000000000000000001010 '
b00000000000000000000000000010100 (
b00000000000000000000000000000101 )
#196
0!
#197
1!
b00000000000000000000000000000011 &
1#
b00000000000000000000000000000000 '
b00000000000000000000000000010101 (
b00000000000000000000000000000110 )
#198
0!
#199
1!
b00000000000000000000000000000100 &
b00000000000000000000000000000001 '
b00000000000000000000000000010110 (
b00000000000000000000000000000111 )
