VGA/Sync_Pulse.v
module Sync_Pulse(
input CLK,
output H_pulse, V_pulse
);

// 800 Col by 525 Row
// 640 Col Active, 160 Col H-Sync
// 480 Row Active, 45 Row V-Sync

// 25Mhz Clock / (800 by 525) Area = 60Hz refresh rate (60 clock cycles per pixel per second)
// 25Mhz / 800 = 31250 Clock cycles per column
// 25Mhz / 525 = 47619.0476 Clock cycles per row

// H-Sync = High for 25000 Clock cycles
// V-Sync = High for 43537.4149 Clock cycles 

reg [14:0] r_CountCol = 0;
reg [15:0] r_CountRow = 0;
reg r_H_pulse = 1'b1;
reg r_V_pulse = 1'b1;

always @(posedge CLK)
begin
   if (r_CountCol < 38400)// maybe this should be 540
    r_H_pulse <= 1'b1;
  else if (r_CountCol < 48000)// maybe this should be 800
    r_H_pulse <= 1'b0;
  else
    r_CountCol <= 0;
  
  r_CountCol <= r_CountCol + 1;
  
  if (r_CountRow < 28800)
    r_V_pulse <= 1'b1;
  else if (r_CountRow < 31500)
    r_V_pulse <= 1'b0;
  else
    r_CountRow <= 0;
    
  r_CountRow <= r_CountRow + 1;
end

assign H_pulse = r_H_pulse;
assign V_pulse = r_V_pulse;

endmodule

VGA/Sync_Pulse_tb.v
`timescale 1ns/10ps
module Sync_Pulse_tb();
  
  reg r_Clock = 0;
  wire H_Pulse, V_Pulse;
  
  Sync_Pulse inst(
    .CLK(r_Clock),
    .H_pulse(H_Pulse),
    .V_pulse(V_Pulse));
  
  always #(20)
    r_Clock <= ~r_Clock;
  
  reg h_sync_triggered = 0;
  reg v_sync_triggered = 0;

  always @(posedge r_Clock)       begin
    if (H_Pulse == 1'b0 && !h_sync_triggered) begin
      h_sync_triggered <= 1'b1;
      $display("H_sync went to 1'b0 at time %0t", $time);
    end

    if (V_Pulse == 1'b0 && !v_sync_triggered) begin
      v_sync_triggered <= 1'b1;
      $display("V_sync went to 1'b0 at time %0t", $time);
    end

    // Stop simulation when both H_sync and V_sync have triggered
    //if (h_sync_triggered && v_sync_triggered)
      //$finish;
  end
  
  initial
  begin
    $dumpfile("dump.vcd");
    $dumpvars(0, inst);
    
    #2200000
    $finish;
  end
  
endmodule

VGA/dump.vcd
$date
	Mon Jul  8 12:26:24 2024
$end
$version
	Icarus Verilog
$end
$timescale
	10ps
$end
$scope module Sync_Pulse_tb $end
$scope module inst $end
$var wire 1 ! CLK $end
$var wire 1 " H_pulse $end
$var wire 1 # V_pulse $end
$var reg 15 $ r_CountCol [14:0] $end
$var reg 16 % r_CountRow [15:0] $end
$var reg 1 & r_H_pulse $end
$var reg 1 ' r_V_pulse $end
$upscope $end
$upscope $end
$enddefinitions $end
$comment Show the parameter values. $end
$dumpall
$end
#0
$dumpvars
1'
1&
b0 %
b0 $
1#
1"
0!
$end
#2000
b0 %
b1 $
1!
#4000
0!
#6000
b0 %
b10 $
1!
#8000
0!
#10000
b0 %
b11 $
1!
#12000
0!
#14000
b0 %
b100 $
1!
#16000
0!
#18000
b0 %
b101 $
1!
#20000
0!
#22000
b0 %
b110 $
1!
#24000
0!
#26000
b0 %
b111 $
1!
#28000
0!
#30000
b0 %
b1000 $
1!
#32000
0!
#34000
b0 %
b1001 $
1!
#36000
0!
#38000
b0 %
b1010 $
1!
#40000
0!
#42000
b0 %
b1011 $
1!
#44000
0!
#46000
b0 %
b1100 $
1!
#48000
0!
#50000
b0 %
b1101 $
1!
#52000
0!
#54000
b0 %
b1110 $
1!
#56000
0!
#58000
b0 %
b1111 $
1!
#60000
0!
#62000
b0 %
b10000 $
1!
#64000
0!
#66000
b0 %
b10001 $
1!
#68000
0!
#70000
b0 %
b10010 $
1!
#72000
0!
#74000
b0 %
b10011 $
1!
#76000
0!
#78000
b0 %
b10100 $
1!
#80000
0!
#82000
b0 %
b10101 $
1!
#84000
0!
#86000
b0 %
b10110 $
1!
#88000
0!
#90000
b0 %
b10111 $
1!
#92000
0!
#94000
b0 %
b11000 $
1!
#96000
0!
#98000
b0 %
b11001 $
1!
#100000
0!
#102000
b0 %
b11010 $
1!
#104000
0!
#106000
b0 %
b11011 $
1!
#108000
0!
#110000
b0 %
b11100 $
1!
#112000
0!
#114000
b0 %
b11101 $
1!
#116000
0!
#118000
b0 %
b11110 $
1!
#120000
0!
#122000
b0 %
b11111 $
1!
#124000
0!
#126000
b0 %
b100000 $
1!
#128000
0!
#130000
b0 %
b100001 $
1!
#132000
0!
#134000
b0 %
b100010 $
1!
#136000
0!
#138000
b0 %
b100011 $
1!
#140000
0!
#142000
b0 %
b100100 $
1!
#144000
0!
#146000
b0 %
b100101 $
1!
#148000
0!
#150000
b0 %
b100110 $
1!
#152000
0!
#154000
b0 %
b100111 $
1!
#156000
0!
#158000
b0 %
b101000 $
1!
#160000
0!
#162000
b0 %
b101001 $
1!
#164000
0!
#166000
b0 %
b101010 $
1!
#168000
0!
#170000
b0 %
b101011 $
1!
#172000
0!
#174000
b0 %
b101100 $
1!
#176000
0!
#178000
b0 %
b101101 $
1!
#180000
0!
#182000
b0 %
b101110 $
1!
#184000
0!
#186000
b0 %
b101111 $
1!
#188000
0!
#190000
b0 %
b110000 $
1!
#192000
0!
#194000
b0 %
b110001 $
1!
#196000
0!
#198000
b0 %
b110010 $
1!
#200000
0!
#202000
b0 %
b110011 $
1!
#204000
0!
#206000
b0 %
b110100 $
1!
#208000
0!
#210000
b0 %
b110101 $
1!
#212000
0!
#214000
b0 %
b110110 $
1!
#216000
0!
#218000
b0 %
b110111 $
1!
#220000
0!
#222000
b0 %
b111000 $
1!
#224000
0!
#226000
b0 %
b111001 $
1!
#228000
0!
#230000
b0 %
b111010 $
1!
#232000
0!
#234000
b0 %
b111011 $
1!
#236000
0!
#238000
b0 %
b111100 $
1!
#240000
0!
#242000
b0 %
b111101 $
1!
#244000
0!
#246000
b0 %
b111110 $
1!
#248000
0!
#250000
b0 %
b111111 $
1!
#252000
0!
#254000
b0 %
b1000000 $
1!
#256000
0!
#258000
b0 %
b1000001 $
1!
#260000
0!
#262000
b0 %
b1000010 $
1!
#264000
0!
#266000
b0 %
b1000011 $
1!
#268000
0!
#270000
b0 %
b1000100 $
1!
#272000
0!
#274000
b0 %
b1000101 $
1!
#276000
0!
#278000
b0 %
b1000110 $
1!
#280000
0!
#282000
b0 %
b1000111 $
1!
#284000
0!
#286000
b0 %
b1001000 $
1!
#288000
0!
#290000
b0 %
b1001001 $
1!
#292000
0!
#294000
b0 %
b1001010 $
1!
#296000
0!
#298000
b0 %
b1001011 $
1!
#300000
0!
#302000
b0 %
b1001100 $
1!
#304000
0!
#306000
b0 %
b1001101 $
1!
#308000
0!
#310000
b0 %
b1001110 $
1!
#312000
0!
#314000
b0 %
b1001111 $
1!
#316000
0!
#318000
b0 %
b1010000 $
1!
#320000
0!
#322000
b0 %
b1010001 $
1!
#324000
0!
#326000
b0 %
b1010010 $
1!
#328000
0!
#330000
b0 %
b1010011 $
1!
#332000
0!
#334000
b0 %
b1010100 $
1!
#336000
0!
#338000
b0 %
b1010101 $
1!
#340000
0!
#342000
b0 %
b1010110 $
1!
#344000
0!
#346000
b0 %
b1010111 $
1!
#348000
0!
#350000
b0 %
b1011000 $
1!
#352000
0!
#354000
b0 %
b1011001 $
1!
#356000
0!
#358000
b0 %
b1011010 $
1!
#360000
0!
#362000
b0 %
b1011011 $
1!
#364000
0!
#366000
b0 %
b1011100 $
1!
#368000
0!
#370000
b0 %
b1011101 $
1!
#372000
0!
#374000
b0 %
b1011110 $
1!
#376000
0!
#378000
b0 %
b1011111 $
1!
#380000
0!
#382000
b0 %
b1100000 $
1!
#384000
0!
#386000
b0 %
b1100001 $
1!
#388000
0!
#390000
b0 %
b1100010 $
1!
#392000
0!
#394000
b0 %
b1100011 $
1!
#396000
0!
#398000
b0 %
b1100100 $
1!
#400000
0!
#402000
b0 %
b1100101 $
1!
#404000
0!
#406000
b0 %
b1100110 $
1!
#408000
0!
#410000
b0 %
b1100111 $
1!
#412000
0!
#414000
b0 %
b1101000 $
1!
#416000
0!
#418000
b0 %
b1101001 $
1!
#420000
0!
#422000
b0 %
b1101010 $
1!
#424000
0!
#426000
b0 %
b1101011 $
1!
#428000
0!
#430000
b0 %
b1101100 $
1!
#432000
0!
#434000
b0 %
b1101101 $
1!
#436000
0!
#438000
b0 %
b1101110 $
1!
#440000
0!
#442000
b0 %
b1101111 $
1!
#444000
0!
#446000
b0 %
b1110000 $
1!
#448000
0!
#450000
b0 %
b1110001 $
1!
#452000
0!
#454000
b0 %
b1110010 $
1!
#456000
0!
#458000
b0 %
b1110011 $
1!
#460000
0!
#462000
b0 %
b1110100 $
1!
#464000
0!
#466000
b0 %
b1110101 $
1!
#468000
0!
#470000
b0 %
b1110110 $
1!
#472000
0!
#474000
b0 %
b1110111 $
1!
#476000
0!
#478000
b0 %
b1111000 $
1!
#480000
0!
#482000
b0 %
b1111001 $
1!
#484000
0!
#486000
b0 %
b1111010 $
1!
#488000
0!
#490000
b0 %
b1111011 $
1!
#492000
0!
#494000
b0 %
b1111100 $
1!
#496000
0!
#498000
b0 %
b1111101 $
1!
#500000
0!
#502000
b0 %
b1111110 $
1!
#504000
0!
#506000
b0 %
b1111111 $
1!
#508000
0!
#510000
b0 %
b10000000 $
1!
#512000
0!
#514000
b0 %
b10000001 $
1!
#516000
0!
#518000
b0 %
b10000010 $
1!
#520000
0!
#522000
b0 %
b10000011 $
1!
#524000
0!
#526000
b0 %
b10000100 $
1!
#528000
0!
#530000
b0 %
b10000101 $
1!
#532000
0!
#534000
b0 %
b10000110 $
1!
#536000
0!
#538000
b0 %
b10000111 $
1!
#540000
0!
#542000
b0 %
b10001000 $
1!
#544000
0!
#546000
b0 %
b10001001 $
1!
#548000
0!
#550000
b0 %
b10001010 $
1!
#552000
0!
#554000
b0 %
b10001011 $
1!
#556000
0!
#558000
b0 %
b10001100 $
1!
#560000
0!
#562000
b0 %
b10001101 $
1!
#564000
0!
#566000
b0 %
b10001110 $
1!
#568000
0!
#570000
b0 %
b10001111 $
1!
#572000
0!
#574000
b0 %
b10010000 $
1!
#576000
0!
#578000
b0 %
b10010001 $
1!
#580000
0!
#582000
b0 %
b10010010 $
1!
#584000
0!
#586000
b0 %
b10010011 $
1!
#588000
0!
#590000
b0 %
b10010100 $
1!
#592000
0!
#594000
b0 %
b10010101 $
1!
#596000
0!
#598000
b0 %
b10010110 $
1!
#600000
0!
#602000
b0 %
b10010111 $
1!
#604000
0!
#606000
b0 %
b10011000 $
1!
#608000
0!
#610000
b0 %
b10011001 $
1!
#612000
0!
#614000
b0 %
b10011010 $
1!
#616000
0!
#618000
b0 %
b10011011 $
1!
#620000
0!
#622000
b0 %
b10011100 $
1!
#624000
0!
#626000
b0 %
b10011101 $
1!
#628000
0!
#630000
b0 %
b10011110 $
1!
#632000
0!
#634000
b0 %
b10011111 $
1!
#636000
0!
#638000
b0 %
b10100000 $
1!
#640000
0!
#642000
b0 %
b10100001 $
1!
#644000
0!
#646000
b0 %
b10100010 $
1!
#648000
0!
#650000
b0 %
b10100011 $
1!
#652000
0!
#654000
b0 %
b10100100 $
1!
#656000
0!
#658000
b0 %
b10100101 $
1!
#660000
0!
#662000
b0 %
b10100110 $
1!
#664000
0!
#666000
b0 %
b10100111 $
1!
#668000
0!
#670000
b0 %
b10101000 $
1!
#672000
0!
#674000
b0 %
b10101001 $
1!
#676000
0!
#678000
b0 %
b10101010 $
1!
#680000
0!
#682000
b0 %
b10101011 $
1!
#684000
0!
#686000
b0 %
b10101100 $
1!
#688000
0!
#690000
b0 %
b10101101 $
1!
#692000
0!
#694000
b0 %
b10101110 $
1!
#696000
0!
#698000
b0 %
b10101111 $
1!
#700000
0!
#702000
b0 %
b10110000 $
1!
#704000
0!
#706000
b0 %
b10110001 $
1!
#708000
0!
#710000
b0 %
b10110010 $
1!
#712000
0!
#714000
b0 %
b10110011 $
1!
#716000
0!
#718000
b0 %
b10110100 $
1!
#720000
0!
#722000
b0 %
b10110101 $
1!
#724000
0!
#726000
b0 %
b10110110 $
1!
#728000
0!
#730000
b0 %
b10110111 $
1!
#732000
0!
#734000
b0 %
b10111000 $
1!
#736000
0!
#738000
b0 %
b10111001 $
1!
#740000
0!
#742000
b0 %
b10111010 $
1!
#744000
0!
#746000
b0 %
b10111011 $
1!
#748000
0!
#750000
b0 %
b10111100 $
1!
#752000
0!
#754000
b0 %
b10111101 $
1!
#756000
0!
#758000
b0 %
b10111110 $
1!
#760000
0!
#762000
b0 %
b10111111 $
1!
#764000
0!
#766000
b0 %
b11000000 $
1!
#768000
0!
#770000
b0 %
b11000001 $
1!
#772000
0!
#774000
b0 %
b11000010 $
1!
#776000
0!
#778000
b0 %
b11000011 $
1!
#780000
0!
#782000
b0 %
b11000100 $
1!
#784000
0!
#786000
b0 %
b11000101 $
1!
#788000
0!
#790000
b0 %
b11000110 $
1!
#792000
0!
#794000
b0 %
b11000111 $
1!
#796000
0!
#798000
b0 %
b11001000 $
1!
#800000
0!
#802000
b0 %
b11001001 $
1!
#804000
0!
#806000
b0 %
b11001010 $
1!
#808000
0!
#810000
b0 %
b11001011 $
1!
#812000
0!
#814000
b0 %
b11001100 $
1!
#816000
0!
#818000
b0 %
b11001101 $
1!
#820000
0!
#822000
b0 %
b11001110 $
1!
#824000
0!
#826000
b0 %
b11001111 $
1!
#828000
0!
#830000
b0 %
b11010000 $
1!
#832000
0!
#834000
b0 %
b11010001 $
1!
#836000
0!
#838000
b0 %
b11010010 $
1!
#840000
0!
#842000
b0 %
b11010011 $
1!
#844000
0!
#846000
b0 %
b11010100 $
1!
#848000
0!
#850000
b0 %
b11010101 $
1!
#852000
0!
#854000
b0 %
b11010110 $
1!
#856000
0!
#858000
b0 %
b11010111 $
1!
#860000
0!
#862000
b0 %
b11011000 $
1!
#864000
0!
#866000
b0 %
b11011001 $
1!
#868000
0!
#870000
b0 %
b11011010 $
1!
#872000
0!
#874000
b0 %
b11011011 $
1!
#876000
0!
#878000
b0 %
b11011100 $
1!
#880000
0!
#882000
b0 %
b11011101 $
1!
#884000
0!
#886000
b0 %
b11011110 $
1!
#888000
0!
#890000
b0 %
b11011111 $
1!
#892000
0!
#894000
b0 %
b11100000 $
1!
#896000
0!
#898000
b0 %
b11100001 $
1!
#900000
0!
#902000
b0 %
b11100010 $
1!
#904000
0!
#906000
b0 %
b11100011 $
1!
#908000
0!
#910000
b0 %
b11100100 $
1!
#912000
0!
#914000
b0 %
b11100101 $
1!
#916000
0!
#918000
b0 %
b11100110 $
1!
#920000
0!
#922000
b0 %
b11100111 $
1!
#924000
0!
#926000
b0 %
b11101000 $
1!
#928000
0!
#930000
b0 %
b11101001 $
1!
#932000
0!
#934000
b0 %
b11101010 $
1!
#936000
0!
#938000
b0 %
b11101011 $
1!
#940000
0!
#942000
b0 %
b11101100 $
1!
#944000
0!
#946000
b0 %
b11101101 $
1!
#948000
0!
#950000
b0 %
b11101110 $
1!
#952000
0!
#954000
b0 %
b11101111 $
1!
#956000
0!
#958000
b0 %
b11110000 $
1!
#960000
0!
#962000
b0 %
b11110001 $
1!
#964000
0!
#966000
b0 %
b11110010 $
1!
#968000
0!
#970000
b0 %
b11110011 $
1!
#972000
0!
#974000
b0 %
b11110100 $
1!
#976000
0!
#978000
b0 %
b11110101 $
1!
#980000
0!
#982000
b0 %
b11110110 $
1!
#984000
0!
#986000
b0 %
b11110111 $
1!
#988000
0!
#990000
b0 %
b11111000 $
1!
#992000
0!
#994000
b0 %
b11111001 $
1!
#996000
0!
#998000
b0 %
b11111010 $
1!
#1000000
0!
#1002000
b0 %
b11111011 $
1!
#1004000
0!
#1006000
b0 %
b11111100 $
1!
#1008000
0!
#1010000
b0 %
b11111101 $
1!
#1012000
0!
#1014000
b0 %
b11111110 $
1!
#1016000
0!
#1018000
b0 %
b11111111 $
1!
#1020000
0!
#1022000
b0 %
b100000000 $
1!
#1024000
0!
#1026000
b0 %
b100000001 $
1!
#1028000
0!
#1030000
b0 %
b100000010 $
1!
#1032000
0!
#1034000
b0 %
b100000011 $
1!
#1036000
0!
#1038000
b0 %
b100000100 $
1!
#1040000
0!
#1042000
b0 %
b100000101 $
1!
#1044000
0!
#1046000
b0 %
b100000110 $
1!
#1048000
0!
#1050000
b0 %
b100000111 $
1!
#1052000
0!
#1054000
b0 %
b100001000 $
1!
#1056000
0!
#1058000
b0 %
b100001001 $
1!
#1060000
0!
#1062000
b0 %
b100001010 $
1!
#1064000
0!
#1066000
b0 %
b100001011 $
1!
#1068000
0!
#1070000
b0 %
b100001100 $
1!
#1072000
0!
#1074000
b0 %
b100001101 $
1!
#1076000
0!
#1078000
b0 %
b100001110 $
1!
#1080000
0!
#1082000
b0 %
b100001111 $
1!
#1084000
0!
#1086000
b0 %
b100010000 $
1!
#1088000
0!
#1090000
b0 %
b100010001 $
1!
#1092000
0!
#1094000
b0 %
b100010010 $
1!
#1096000
0!
#1098000
b0 %
b100010011 $
1!
#1100000
0!
#1102000
b0 %
b100010100 $
1!
#1104000
0!
#1106000
b0 %
b100010101 $
1!
#1108000
0!
#1110000
b0 %
b100010110 $
1!
#1112000
0!
#1114000
b0 %
b100010111 $
1!
#1116000
0!
#1118000
b0 %
b100011000 $
1!
#1120000
0!
#1122000
b0 %
b100011001 $
1!
#1124000
0!
#1126000
b0 %
b100011010 $
1!
#1128000
0!
#1130000
b0 %
b100011011 $
1!
#1132000
0!
#1134000
b0 %
b100011100 $
1!
#1136000
0!
#1138000
b0 %
b100011101 $
1!
#1140000
0!
#1142000
b0 %
b100011110 $
1!
#1144000
0!
#1146000
b0 %
b100011111 $
1!
#1148000
0!
#1150000
b0 %
b100100000 $
1!
#1152000
0!
#1154000
b0 %
b100100001 $
1!
#1156000
0!
#1158000
b0 %
b100100010 $
1!
#1160000
0!
#1162000
b0 %
b100100011 $
1!
#1164000
0!
#1166000
b0 %
b100100100 $
1!
#1168000
0!
#1170000
b0 %
b100100101 $
1!
#1172000
0!
#1174000
b0 %
b100100110 $
1!
#1176000
0!
#1178000
b0 %
b100100111 $
1!
#1180000
0!
#1182000
b0 %
b100101000 $
1!
#1184000
0!
#1186000
b0 %
b100101001 $
1!
#1188000
0!
#1190000
b0 %
b100101010 $
1!
#1192000
0!
#1194000
b0 %
b100101011 $
1!
#1196000
0!
#1198000
b0 %
b100101100 $
1!
#1200000
0!
#1202000
b0 %
b100101101 $
1!
#1204000
0!
#1206000
b0 %
b100101110 $
1!
#1208000
0!
#1210000
b0 %
b100101111 $
1!
#1212000
0!
#1214000
b0 %
b100110000 $
1!
#1216000
0!
#1218000
b0 %
b100110001 $
1!
#1220000
0!
#1222000
b0 %
b100110010 $
1!
#1224000
0!
#1226000
b0 %
b100110011 $
1!
#1228000
0!
#1230000
b0 %
b100110100 $
1!
#1232000
0!
#1234000
b0 %
b100110101 $
1!
#1236000
0!
#1238000
b0 %
b100110110 $
1!
#1240000
0!
#1242000
b0 %
b100110111 $
1!
#1244000
0!
#1246000
b0 %
b100111000 $
1!
#1248000
0!
#1250000
b0 %
b100111001 $
1!
#1252000
0!
#1254000
b0 %
b100111010 $
1!
#1256000
0!
#1258000
b0 %
b100111011 $
1!
#1260000
0!
#1262000
b0 %
b100111100 $
1!
#1264000
0!
#1266000
b0 %
b100111101 $
1!
#1268000
0!
#1270000
b0 %
b100111110 $
1!
#1272000
0!
#1274000
b0 %
b100111111 $
1!
#1276000
0!
#1278000
b0 %
b101000000 $
1!
#1280000
0!
#1282000
b0 %
b101000001 $
1!
#1284000
0!
#1286000
b0 %
b101000010 $
1!
#1288000
0!
#1290000
b0 %
b101000011 $
1!
#1292000
0!
#1294000
b0 %
b101000100 $
1!
#1296000
0!
#1298000
b0 %
b101000101 $
1!
#1300000
0!
#1302000
b0 %
b101000110 $
1!
#1304000
0!
#1306000
b0 %
b101000111 $
1!
#1308000
0!
#1310000
b0 %
b101001000 $
1!
#1312000
0!
#1314000
b0 %
b101001001 $
1!
#1316000
0!
#1318000
b0 %
b101001010 $
1!
#1320000
0!
#1322000
b0 %
b101001011 $
1!
#1324000
0!
#1326000
b0 %
b101001100 $
1!
#1328000
0!
#1330000
b0 %
b101001101 $
1!
#1332000
0!
#1334000
b0 %
b101001110 $
1!
#1336000
0!
#1338000
b0 %
b101001111 $
1!
#1340000
0!
#1342000
b0 %
b101010000 $
1!
#1344000
0!
#1346000
b0 %
b101010001 $
1!
#1348000
0!
#1350000
b0 %
b101010010 $
1!
#1352000
0!
#1354000
b0 %
b101010011 $
1!
#1356000
0!
#1358000
b0 %
b101010100 $
1!
#1360000
0!
#1362000
b0 %
b101010101 $
1!
#1364000
0!
#1366000
b0 %
b101010110 $
1!
#1368000
0!
#1370000
b0 %
b101010111 $
1!
#1372000
0!
#1374000
b0 %
b101011000 $
1!
#1376000
0!
#1378000
b0 %
b101011001 $
1!
#1380000
0!
#1382000
b0 %
b101011010 $
1!
#1384000
0!
#1386000
b0 %
b101011011 $
1!
#1388000
0!
#1390000
b0 %
b101011100 $
1!
#1392000
0!
#1394000
b0 %
b101011101 $
1!
#1396000
0!
#1398000
b0 %
b101011110 $
1!
#1400000
0!
#1402000
b0 %
b101011111 $
1!
#1404000
0!
#1406000
b0 %
b101100000 $
1!
#1408000
0!
#1410000
b0 %
b101100001 $
1!
#1412000
0!
#1414000
b0 %
b101100010 $
1!
#1416000
0!
#1418000
b0 %
b101100011 $
1!
#1420000
0!
#1422000
b0 %
b101100100 $
1!
#1424000
0!
#1426000
b0 %
b101100101 $
1!
#1428000
0!
#1430000
b0 %
b101100110 $
1!
#1432000
0!
#1434000
b0 %
b101100111 $
1!
#1436000
0!
#1438000
b0 %
b101101000 $
1!
#1440000
0!
#1442000
b0 %
b101101001 $
1!
#1444000
0!
#1446000
b0 %
b101101010 $
1!
#1448000
0!
#1450000
b0 %
b101101011 $
1!
#1452000
0!
#1454000
b0 %
b101101100 $
1!
#1456000
0!
#1458000
b0 %
b101101101 $
1!
#1460000
0!
#1462000
b0 %
b101101110 $
1!
#1464000
0!
#1466000
b0 %
b101101111 $
1!
#1468000
0!
#1470000
b0 %
b101110000 $
1!
#1472000
0!
#1474000
b0 %
b101110001 $
1!
#1476000
0!
#1478000
b0 %
b101110010 $
1!
#1480000
0!
#1482000
b0 %
b101110011 $
1!
#1484000
0!
#1486000
b0 %
b101110100 $
1!
#1488000
0!
#1490000
b0 %
b101110101 $
1!
#1492000
0!
#1494000
b0 %
b101110110 $
1!
#1496000
0!
#1498000
b0 %
b101110111 $
1!
#1500000
0!
#1502000
b0 %
b101111000 $
1!
#1504000
0!
#1506000
b0 %
b101111001 $
1!
#1508000
0!
#1510000
b0 %
b101111010 $
1!
#1512000
0!
#1514000
b0 %
b101111011 $
1!
#1516000
0!
#1518000
b0 %
b101111100 $
1!
#1520000
0!
#1522000
b0 %
b101111101 $
1!
#1524000
0!
#1526000
b0 %
b101111110 $
1!
#1528000
0!
#1530000
b0 %
b101111111 $
1!
#1532000
0!
#1534000
b0 %
b110000000 $
1!
#1536000
0!
#1538000
b0 %
b110000001 $
1!
#1540000
0!
#1542000
b0 %
b110000010 $
1!
#1544000
0!
#1546000
b0 %
b110000011 $
1!
#1548000
0!
#1550000
b0 %
b110000100 $
1!
#1552000
0!
#1554000
b0 %
b110000101 $
1!
#1556000
0!
#1558000
b0 %
b110000110 $
1!
#1560000
0!
#1562000
b0 %
b110000111 $
1!
#1564000
0!
#1566000
b0 %
b110001000 $
1!
#1568000
0!
#1570000
b0 %
b110001001 $
1!
#1572000
0!
#1574000
b0 %
b110001010 $
1!
#1576000
0!
#1578000
b0 %
b110001011 $
1!
#1580000
0!
#1582000
b0 %
b110001100 $
1!
#1584000
0!
#1586000
b0 %
b110001101 $
1!
#1588000
0!
#1590000
b0 %
b110001110 $
1!
#1592000
0!
#1594000
b0 %
b110001111 $
1!
#1596000
0!
#1598000
b0 %
b110010000 $
1!
#1600000
0!
#1602000
b0 %
b110010001 $
1!
#1604000
0!
#1606000
b0 %
b110010010 $
1!
#1608000
0!
#1610000
b0 %
b110010011 $
1!
#1612000
0!
#1614000
b0 %
b110010100 $
1!
#1616000
0!
#1618000
b0 %
b110010101 $
1!
#1620000
0!
#1622000
b0 %
b110010110 $
1!
#1624000
0!
#1626000
b0 %
b110010111 $
1!
#1628000
0!
#1630000
b0 %
b110011000 $
1!
#1632000
0!
#1634000
b0 %
b110011001 $
1!
#1636000
0!
#1638000
b0 %
b110011010 $
1!
#1640000
0!
#1642000
b0 %
b110011011 $
1!
#1644000
0!
#1646000
b0 %
b110011100 $
1!
#1648000
0!
#1650000
b0 %
b110011101 $
1!
#1652000
0!
#1654000
b0 %
b110011110 $
1!
#1656000
0!
#1658000
b0 %
b110011111 $
1!
#1660000
0!
#1662000
b0 %
b110100000 $
1!
#1664000
0!
#1666000
b0 %
b110100001 $
1!
#1668000
0!
#1670000
b0 %
b110100010 $
1!
#1672000
0!
#1674000
b0 %
b110100011 $
1!
#1676000
0!
#1678000
b0 %
b110100100 $
1!
#1680000
0!
#1682000
b0 %
b110100101 $
1!
#1684000
0!
#1686000
b0 %
b110100110 $
1!
#1688000
0!
#1690000
b0 %
b110100111 $
1!
#1692000
0!
#1694000
b0 %
b110101000 $
1!
#1696000
0!
#1698000
b0 %
b110101001 $
1!
#1700000
0!
#1702000
b0 %
b110101010 $
1!
#1704000
0!
#1706000
b0 %
b110101011 $
1!
#1708000
0!
#1710000
b0 %
b110101100 $
1!
#1712000
0!
#1714000
b0 %
b110101101 $
1!
#1716000
0!
#1718000
b0 %
b110101110 $
1!
#1720000
0!
#1722000
b0 %
b110101111 $
1!
#1724000
0!
#1726000
b0 %
b110110000 $
1!
#1728000
0!
#1730000
b0 %
b110110001 $
1!
#1732000
0!
#1734000
b0 %
b110110010 $
1!
#1736000
0!
#1738000
b0 %
b110110011 $
1!
#1740000
0!
#1742000
b0 %
b110110100 $
1!
#1744000
0!
#1746000
b0 %
b110110101 $
1!
#1748000
0!
#1750000
b0 %
b110110110 $
1!
#1752000
0!
#1754000
b0 %
b110110111 $
1!
#1756000
0!
#1758000
b0 %
b110111000 $
1!
#1760000
0!
#1762000
b0 %
b110111001 $
1!
#1764000
0!
#1766000
b0 %
b110111010 $
1!
#1768000
0!
#1770000
b0 %
b110111011 $
1!
#1772000
0!
#1774000
b0 %
b110111100 $
1!
#1776000
0!
#1778000
b0 %
b110111101 $
1!
#1780000
0!
#1782000
b0 %
b110111110 $
1!
#1784000
0!
#1786000
b0 %
b110111111 $
1!
#1788000
0!
#1790000
b0 %
b111000000 $
1!
#1792000
0!
#1794000
b0 %
b111000001 $
1!
#1796000
0!
#1798000
b0 %
b111000010 $
1!
#1800000
0!
#1802000
b0 %
b111000011 $
1!
#1804000
0!
#1806000
b0 %
b111000100 $
1!
#1808000
0!
#1810000
b0 %
b111000101 $
1!
#1812000
0!
#1814000
b0 %
b111000110 $
1!
#1816000
0!
#1818000
b0 %
b111000111 $
1!
#1820000
0!
#1822000
b0 %
b111001000 $
1!
#1824000
0!
#1826000
b0 %
b111001001 $
1!
#1828000
0!
#1830000
b0 %
b111001010 $
1!
#1832000
0!
#1834000
b0 %
b111001011 $
1!
#1836000
0!
#1838000
b0 %
b111001100 $
1!
#1840000
0!
#1842000
b0 %
b111001101 $
1!
#1844000
0!
#1846000
b0 %
b111001110 $
1!
#1848000
0!
#1850000
b0 %
b111001111 $
1!
#1852000
0!
#1854000
b0 %
b111010000 $
1!
#1856000
0!
#1858000
b0 %
b111010001 $
1!
#1860000
0!
#1862000
b0 %
b111010010 $
1!
#1864000
0!
#1866000
b0 %
b111010011 $
1!
#1868000
0!
#1870000
b0 %
b111010100 $
1!
#1872000
0!
#1874000
b0 %
b111010101 $
1!
#1876000
0!
#1878000
b0 %
b111010110 $
1!
#1880000
0!
#1882000
b0 %
b111010111 $
1!
#1884000
0!
#1886000
b0 %
b111011000 $
1!
#1888000
0!
#1890000
b0 %
b111011001 $
1!
#1892000
0!
#1894000
b0 %
b111011010 $
1!
#1896000
0!
#1898000
b0 %
b111011011 $
1!
#1900000
0!
#1902000
b0 %
b111011100 $
1!
#1904000
0!
#1906000
b0 %
b111011101 $
1!
#1908000
0!
#1910000
b0 %
b111011110 $
1!
#1912000
0!
#1914000
b0 %
b111011111 $
1!
#1916000
0!
#1918000
b0 %
b111100000 $
1!
#1920000
0!
#1922000
b0 %
b111100001 $
1!
#1924000
0!
#1926000
b0 %
b111100010 $
1!
#1928000
0!
#1930000
b0 %
b111100011 $
1!
#1932000
0!
#1934000
b0 %
b111100100 $
1!
#1936000
0!
#1938000
b0 %
b111100101 $
1!
#1940000
0!
#1942000
b0 %
b111100110 $
1!
#1944000
0!
#1946000
b0 %
b111100111 $
1!
#1948000
0!
#1950000
b0 %
b111101000 $
1!
#1952000
0!
#1954000
b0 %
b111101001 $
1!
#1956000
0!
#1958000
b0 %
b111101010 $
1!
#1960000
0!
#1962000
b0 %
b111101011 $
1!
#1964000
0!
#1966000
b0 %
b111101100 $
1!
#1968000
0!
#1970000
b0 %
b111101101 $
1!
#1972000
0!
#1974000
b0 %
b111101110 $
1!
#1976000
0!
#1978000
b0 %
b111101111 $
1!
#1980000
0!
#1982000
b0 %
b111110000 $
1!
#1984000
0!
#1986000
b0 %
b111110001 $
1!
#1988000
0!
#1990000
b0 %
b111110010 $
1!
#1992000
0!
#1994000
b0 %
b111110011 $
1!
#1996000
0!
#1998000
b0 %
b111110100 $
1!
#2000000
0!
#2002000
b0 %
b111110101 $
1!
#2004000
0!
#2006000
b0 %
b111110110 $
1!
#2008000
0!
#2010000
b0 %
b111110111 $
1!
#2012000
0!
#2014000
b0 %
b111111000 $
1!
#2016000
0!
#2018000
b0 %
b111111001 $
1!
#2020000
0!
#2022000
b0 %
b111111010 $
1!
#2024000
0!
