VGA/Pattern_Generator.v
module Pattern_Generator(
input CLK,
input i_SW1, i_SW2, i_SW3, i_SW4,
input i_HSync,
input i_VSync,
output reg o_HSync_PG = 0, 
output reg o_VSync_PG = 0,
output reg [2:0] Red = 0,
output reg [2:0] Green = 0,
output reg [2:0] Blue = 0
);

always @(posedge CLK)
begin
  o_HSync_PG <= i_HSync;
  o_VSync_PG <= i_VSync;
  if (i_SW1) begin //!,1,A,Q,a,q
    Red <= (i_HSync && i_VSync) ? 3'b111 : 0;
    Green <= 0;
    Blue <= 0; end
  else if (i_SW2) begin //",2,B,R,b,r
    Red <= 0;
    Green <= (i_HSync && i_VSync) ? 3'b111 : 0;
    Blue <= 0; end
  else if (i_SW3) begin //#,3...
    Red <= 0;
    Green <= 0;
    Blue <= (i_HSync && i_VSync) ? 3'b111 : 0; end
  else if (i_SW4) begin //anything else makes screen Black
    Red <= 0; 
    Green <= 0;
    Blue <= 0; end
end 

endmodule

VGA/Sync_Porch.v
//This module alters the Sync_pulse signal to include the front & back porch

//Whole area -> 800x525, Visible area -> 640x480
//Hsync -> front: 18, back: 50, pulse: 92
//Vsync -> front: 10, back: 33, pulse: 2


module Sync_Porch(
  input CLK,
  input i_H_Sync,
  input i_V_Sync,
  output reg o_H_Sync = 1'b1, 
  output reg o_V_Sync = 1'b1);
  
  reg r_H_Sync = 1'b1;
  reg [4:0] r_HCountBP = 0;
  reg [6:0] r_HCountPulse = 0;
  
  reg r_V_Sync = 1'b1;
  reg [4:0] r_VCountBP = 0;
  reg [6:0] r_VCountPulse = 0;
  
  always @(posedge CLK)
  begin
    if (i_H_Sync == 0 && r_HCountBP !== 17) //falling edge
      r_HCountBP <= r_HCountBP + 1;
    else
      r_H_Sync <= 0;
      
    if (r_HCountBP == 17 && r_HCountPulse !== 92)
      r_HCountPulse <= r_HCountPulse + 1;
    else
      r_H_Sync <= 1;
      
    if (i_H_Sync == 1) 
      begin
      r_HCountBP <= 0;
      r_HCountPulse <= 0; 
      end
  end
  
  
  always @(posedge CLK)
  begin
    if (i_V_Sync == 0 && r_VCountBP !== 9) //falling edge
      r_VCountBP <= r_VCountBP + 1;
    else
      r_V_Sync <= 0;
      
    if (r_VCountBP == 9 && r_VCountPulse !== 2)
      r_VCountPulse <= r_VCountPulse + 1;
    else
      r_V_Sync <= 1;
      
    if (i_V_Sync == 1) 
      begin
      r_VCountBP <= 0;
      r_VCountPulse <= 0; 
      end
   end
   
  assign o_H_Sync = r_H_Sync;
  assign o_V_Sync = r_V_Sync;
  
endmodule

VGA/Sync_Pulse.v
module Sync_Pulse( //IMPROVE: add parameters
input CLK,
output o_HSync, o_VSync,
output reg [9:0] o_CountCol = 0,
output reg [9:0] o_CountRow = 0
);

always @(posedge CLK)
  begin
  if (o_CountCol < 799) //target-1
    o_CountCol <= o_CountCol + 1;
  else 
    begin
    o_CountCol <= 0;
    if (o_CountRow < 524) 
      o_CountRow <= o_CountRow + 1; 
    else
      o_CountRow <= 0;
    end
end

assign o_HSync = (o_CountCol < 640) ? 1'b1 : 1'b0;
assign o_VSync = (o_CountRow < 480) ? 1'b1 : 1'b0;

endmodule

// 800 Col by 525 Row
// 640 Col Active, 160 Col H-Sync
// 480 Row Active, 45 Row V-Sync

// 25 Mhz Clock / (800 by 525) Area = 60 Hz refresh rate (60 clock cycles per pixel per second)

Seven_Seg_Counter/Debounce_Switch.v
module Debounce_Switch(
	input CLK,
	input Switch,
	output o_Switch);
	
parameter c_DEBOUNCE_LIMIT = 250000;// 10 ms at 25 MHz

reg r_State = 1'b0;
reg [17:0] r_Count = 0;

always @(posedge CLK) begin// COUNTER LOGIC
	if (Switch !== r_State && r_Count < c_DEBOUNCE_LIMIT)
		r_Count <= r_Count + 1;
	else if (r_Count == c_DEBOUNCE_LIMIT) begin
		r_Count <= 0;
		r_State <= Switch;end
	else
		r_Count <= 0;
	end

assign o_Switch = r_State;

endmodule

VGA/top_VGA.v
//TODO: 
// add parameters
// change variable names
// improve Sync_Pulse and Sync_Porch logic like using '?:' in assign statements
// use case for Pattern Gen
// implement RX and TX, keyboard input, and display
// figure out VGA display and UART on windows
 
module top_VGA(
input CLK,
input SW1, SW2, SW3, SW4,
output VGA_HS, VGA_VS, 
output VGA_R0, VGA_R1, VGA_R2,
output VGA_G0, VGA_G1, VGA_G2, 
output VGA_B0, VGA_B1, VGA_B2
);

wire w_SW1, w_SW2, w_SW3, w_SW4;
wire w_HSync, w_VSync, w_HSynch_Porch, w_VSync_Porch, w_HSync_PG, w_VSync_PG;
wire [9:0] w_CountCol, w_CountRow;
wire [2:0] w_Red;
wire [2:0] w_Green;
wire [2:0] w_Blue;

Debounce_Switch debounceInst1
  (.CLK(CLK),
   .Switch(SW1),
   .o_Switch(w_SW1));
Debounce_Switch debounceInst2
  (.CLK(CLK),
   .Switch(SW2),
   .o_Switch(w_SW2));
Debounce_Switch debounceInst3
  (.CLK(CLK),
   .Switch(SW3),
   .o_Switch(w_SW3));
Debounce_Switch debounceInst4
  (.CLK(CLK),
   .Switch(SW4),
   .o_Switch(w_SW4));
   
Sync_Pulse PulseInst
 (.CLK(CLK),
  .o_HSync(w_HSync),
  .o_VSync(w_VSync),
  .o_CountCol(w_CountCol),
  .o_CountRow(w_CountRow)
  );

Sync_Porch PorchInst
 (.CLK(CLK),
  .i_H_Sync(w_HSync),
  .i_V_Sync(w_VSync),
  .o_H_Sync(w_HSync_Porch),
  .o_V_Sync(w_VSync_Porch)
  );

Pattern_Generator Pattern_GenInst
 (.CLK(CLK),
  .i_SW1(SW1), 
  .i_SW2(SW2), 
  .i_SW3(SW3), 
  .i_SW4(SW4),
  .i_HSync(w_HSync_Porch),
  .i_VSync(w_VSync_Porch),
  .o_HSync_PG(w_HSync_PG),
  .o_VSync_PG(w_VSync_PG),
  .Red(w_Red), 
  .Green(w_Green),
  .Blue(w_Blue)
  );

assign VGA_HS = w_HSync_PG;
assign VGA_VS = w_VSync_PG;

assign VGA_R0 = w_Red[0];
assign VGA_R1 = w_Red[1];
assign VGA_R2 = w_Red[2];

assign VGA_G0 = w_Green[0];
assign VGA_G1 = w_Green[1];
assign VGA_G2 = w_Green[2];

assign VGA_B0 = w_Blue[0];
assign VGA_B1 = w_Blue[1];
assign VGA_B2 = w_Blue[2];

endmodule

VGA/Sync_Pulse_tb.v
//RUN TB: iverilog -o simulation_tb Sync_Pulse.v Sync_Pulse_tb.v
//	  vvp simulation_tb


`timescale 1ns/1ns
module Sync_Pulse_tb();
  
  reg r_Clock = 0;
  wire H_Sync, V_Sync, r0,r1,r2,g0,g1,g2,b0,b1,b2;
  
 top_VGA inst
  (.CLK(r_Clock),
   .SW1(1'b1),
   .SW2(1'b0),
   .SW3(1'b0),
   .SW4(1'b0),
   .VGA_HS(H_Sync),
   .VGA_VS(V_Sync),
   .VGA_R0(r0),
   .VGA_R1(r1),
   .VGA_R2(r2),
   .VGA_G0(g0),
   .VGA_G1(g1),
   .VGA_G2(g2),
   .VGA_B0(b0),
   .VGA_B1(b1),
   .VGA_B2(b2)
   );
  
  always #(20)
    r_Clock <= ~r_Clock;

  always @(posedge r_Clock)
    begin
    end
  
  initial
    begin
    $dumpfile("dump.vcd");
    $dumpvars(0);
    
    #500000
    $finish;
    end
  
endmodule

VGA/dump.vcd
$date
	Fri Jul 19 11:22:14 2024
$end
$version
	Icarus Verilog
$end
$timescale
	1ns
$end
$scope module Sync_Pulse_tb $end
$var wire 1 ! r2 $end
$var wire 1 " r1 $end
$var wire 1 # r0 $end
$var wire 1 $ g2 $end
$var wire 1 % g1 $end
$var wire 1 & g0 $end
$var wire 1 ' b2 $end
$var wire 1 ( b1 $end
$var wire 1 ) b0 $end
$var wire 1 * V_Sync $end
$var wire 1 + H_Sync $end
$var reg 1 , r_Clock $end
$scope module inst $end
$var wire 1 , CLK $end
$var wire 1 - SW1 $end
$var wire 1 . SW2 $end
$var wire 1 / SW3 $end
$var wire 1 0 SW4 $end
$var wire 1 + VGA_HS $end
$var wire 1 * VGA_VS $end
$var wire 1 1 w_VSync_Porch $end
$var wire 1 2 w_VSync_PG $end
$var wire 1 3 w_VSync $end
$var wire 1 4 w_SW4 $end
$var wire 1 5 w_SW3 $end
$var wire 1 6 w_SW2 $end
$var wire 1 7 w_SW1 $end
$var wire 3 8 w_Red [2:0] $end
$var wire 1 9 w_HSync_Porch $end
$var wire 1 : w_HSync_PG $end
$var wire 1 ; w_HSync $end
$var wire 3 < w_Green [2:0] $end
$var wire 10 = w_CountRow [9:0] $end
$var wire 10 > w_CountCol [9:0] $end
$var wire 3 ? w_Blue [2:0] $end
$var wire 1 ! VGA_R2 $end
$var wire 1 " VGA_R1 $end
$var wire 1 # VGA_R0 $end
$var wire 1 $ VGA_G2 $end
$var wire 1 % VGA_G1 $end
$var wire 1 & VGA_G0 $end
$var wire 1 ' VGA_B2 $end
$var wire 1 ( VGA_B1 $end
$var wire 1 ) VGA_B0 $end
$scope module Pattern_GenInst $end
$var wire 1 , CLK $end
$var wire 1 - i_SW1 $end
$var wire 1 . i_SW2 $end
$var wire 1 / i_SW3 $end
$var wire 1 0 i_SW4 $end
$var wire 1 1 i_VSync $end
$var wire 1 9 i_HSync $end
$var reg 3 @ Blue [2:0] $end
$var reg 3 A Green [2:0] $end
$var reg 3 B Red [2:0] $end
$var reg 1 : o_HSync_PG $end
$var reg 1 2 o_VSync_PG $end
$upscope $end
$scope module PorchInst $end
$var wire 1 , CLK $end
$var wire 1 3 i_V_Sync $end
$var wire 1 ; i_H_Sync $end
$var reg 1 9 o_H_Sync $end
$var reg 1 1 o_V_Sync $end
$var reg 5 C r_HCountBP [4:0] $end
$var reg 7 D r_HCountPulse [6:0] $end
$var reg 1 E r_H_Sync $end
$var reg 5 F r_VCountBP [4:0] $end
$var reg 7 G r_VCountPulse [6:0] $end
$var reg 1 H r_V_Sync $end
$upscope $end
$scope module PulseInst $end
$var wire 1 , CLK $end
$var wire 1 3 o_VSync $end
$var wire 1 ; o_HSync $end
$var reg 10 I o_CountCol [9:0] $end
$var reg 10 J o_CountRow [9:0] $end
$upscope $end
$scope module debounceInst1 $end
$var wire 1 , CLK $end
$var wire 1 - Switch $end
$var wire 1 7 o_Switch $end
$var parameter 32 K c_DEBOUNCE_LIMIT $end
$var reg 18 L r_Count [17:0] $end
$var reg 1 M r_State $end
$upscope $end
$scope module debounceInst2 $end
$var wire 1 , CLK $end
$var wire 1 . Switch $end
$var wire 1 6 o_Switch $end
$var parameter 32 N c_DEBOUNCE_LIMIT $end
$var reg 18 O r_Count [17:0] $end
$var reg 1 P r_State $end
$upscope $end
$scope module debounceInst3 $end
$var wire 1 , CLK $end
$var wire 1 / Switch $end
$var wire 1 5 o_Switch $end
$var parameter 32 Q c_DEBOUNCE_LIMIT $end
$var reg 18 R r_Count [17:0] $end
$var reg 1 S r_State $end
$upscope $end
$scope module debounceInst4 $end
$var wire 1 , CLK $end
$var wire 1 0 Switch $end
$var wire 1 4 o_Switch $end
$var parameter 32 T c_DEBOUNCE_LIMIT $end
$var reg 18 U r_Count [17:0] $end
$var reg 1 V r_State $end
$upscope $end
$upscope $end
$upscope $end
$enddefinitions $end
$comment Show the parameter values. $end
$dumpall
b111101000010010000 T
b111101000010010000 Q
b111101000010010000 N
b111101000010010000 K
$end
#0
$dumpvars
0V
b0 U
0S
b0 R
0P
b0 O
0M
b0 L
b0 J
b0 I
1H
b0 G
b0 F
1E
b0 D
b0 C
b0 B
b0 A
b0 @
b0 ?
b0 >
b0 =
b0 <
1;
0:
19
b0 8
07
06
05
04
13
02
11
00
0/
0.
1-
0,
0+
0*
0)
0(
0'
0&
0%
0$
0#
0"
0!
$end
#20
1!
1"
1#
b1 L
b1 >
b1 I
19
1E
11
1H
b111 8
b111 B
1*
12
1+
1:
1,
#40
0,
#60
11
1H
19
1E
b10 >
b10 I
b10 L
1,
#80
0,
#100
b11 L
b11 >
b11 I
19
1E
11
1H
1,
#120
0,
#140
11
1H
19
1E
b100 >
b100 I
b100 L
1,
#160
0,
#180
b101 L
b101 >
b101 I
19
1E
11
1H
1,
#200
0,
#220
11
1H
19
1E
b110 >
b110 I
b110 L
1,
#240
0,
#260
b111 L
b111 >
b111 I
19
1E
11
1H
1,
#280
0,
#300
11
1H
19
1E
b1000 >
b1000 I
b1000 L
1,
#320
0,
#340
b1001 L
b1001 >
b1001 I
19
1E
11
1H
1,
#360
0,
#380
11
1H
19
1E
b1010 >
b1010 I
b1010 L
1,
#400
0,
#420
b1011 L
b1011 >
b1011 I
19
1E
11
1H
1,
#440
0,
#460
11
1H
19
1E
b1100 >
b1100 I
b1100 L
1,
#480
0,
#500
b1101 L
b1101 >
b1101 I
19
1E
11
1H
1,
#520
0,
#540
11
1H
19
1E
b1110 >
b1110 I
b1110 L
1,
#560
0,
#580
b1111 L
b1111 >
b1111 I
19
1E
11
1H
1,
#600
0,
#620
11
1H
19
1E
b10000 >
b10000 I
b10000 L
1,
#640
0,
#660
b10001 L
b10001 >
b10001 I
19
1E
11
1H
1,
#680
0,
#700
11
1H
19
1E
b10010 >
b10010 I
b10010 L
1,
#720
0,
#740
b10011 L
b10011 >
b10011 I
19
1E
11
1H
1,
#760
0,
#780
11
1H
19
1E
b10100 >
b10100 I
b10100 L
1,
#800
0,
#820
b10101 L
b10101 >
b10101 I
19
1E
11
1H
1,
#840
0,
#860
11
1H
19
1E
b10110 >
b10110 I
b10110 L
1,
#880
0,
#900
b10111 L
b10111 >
b10111 I
19
1E
11
1H
1,
#920
0,
#940
11
1H
19
1E
b11000 >
b11000 I
b11000 L
1,
#960
0,
#980
b11001 L
b11001 >
b11001 I
19
1E
11
1H
1,
#1000
0,
#1020
11
1H
19
1E
b11010 >
b11010 I
b11010 L
1,
#1040
0,
#1060
b11011 L
b11011 >
b11011 I
19
1E
11
1H
1,
#1080
0,
#1100
11
1H
19
1E
b11100 >
b11100 I
b11100 L
1,
#1120
0,
#1140
b11101 L
b11101 >
b11101 I
19
1E
11
1H
1,
#1160
0,
#1180
11
1H
19
1E
b11110 >
b11110 I
b11110 L
1,
#1200
0,
#1220
b11111 L
b11111 >
b11111 I
19
1E
11
1H
1,
#1240
0,
#1260
11
1H
19
1E
b100000 >
b100000 I
b100000 L
1,
#1280
0,
#1300
b100001 L
b100001 >
b100001 I
19
1E
11
1H
1,
#1320
0,
#1340
11
1H
19
1E
b100010 >
b100010 I
b100010 L
1,
#1360
0,
#1380
b100011 L
b100011 >
b100011 I
19
1E
11
1H
1,
#1400
0,
#1420
11
1H
19
1E
b100100 >
b100100 I
b100100 L
1,
#1440
0,
#1460
b100101 L
b100101 >
b100101 I
19
1E
11
1H
1,
#1480
0,
#1500
11
1H
19
1E
b100110 >
b100110 I
b100110 L
1,
#1520
0,
#1540
b100111 L
b100111 >
b100111 I
19
1E
11
1H
1,
#1560
0,
#1580
11
1H
19
1E
b101000 >
b101000 I
b101000 L
1,
#1600
0,
#1620
b101001 L
b101001 >
b101001 I
19
1E
11
1H
1,
#1640
0,
#1660
11
1H
19
1E
b101010 >
b101010 I
b101010 L
1,
#1680
0,
#1700
b101011 L
b101011 >
b101011 I
19
1E
11
1H
1,
#1720
0,
#1740
11
1H
19
1E
b101100 >
b101100 I
b101100 L
1,
#1760
0,
#1780
b101101 L
b101101 >
b101101 I
19
1E
11
1H
1,
#1800
0,
#1820
11
1H
19
1E
b101110 >
b101110 I
b101110 L
1,
#1840
0,
#1860
b101111 L
b101111 >
b101111 I
19
1E
11
1H
1,
#1880
0,
#1900
11
1H
19
1E
b110000 >
b110000 I
b110000 L
1,
#1920
0,
#1940
b110001 L
b110001 >
b110001 I
19
1E
11
1H
1,
#1960
0,
#1980
11
1H
19
1E
b110010 >
b110010 I
b110010 L
1,
#2000
0,
#2020
b110011 L
b110011 >
b110011 I
19
1E
11
1H
1,
#2040
0,
#2060
11
1H
19
1E
b110100 >
b110100 I
b110100 L
1,
#2080
0,
#2100
b110101 L
b110101 >
b110101 I
19
1E
11
1H
1,
#2120
0,
#2140
11
1H
19
1E
b110110 >
b110110 I
b110110 L
1,
#2160
0,
#2180
b110111 L
b110111 >
b110111 I
19
1E
11
1H
1,
#2200
0,
#2220
11
1H
19
1E
b111000 >
b111000 I
b111000 L
1,
#2240
0,
#2260
b111001 L
b111001 >
b111001 I
19
1E
11
1H
1,
#2280
0,
#2300
11
1H
19
1E
b111010 >
b111010 I
b111010 L
1,
#2320
0,
#2340
b111011 L
b111011 >
b111011 I
19
1E
11
1H
1,
#2360
0,
#2380
11
1H
19
1E
b111100 >
b111100 I
b111100 L
1,
#2400
0,
#2420
b111101 L
b111101 >
b111101 I
19
1E
11
1H
1,
#2440
0,
#2460
11
1H
19
1E
b111110 >
b111110 I
b111110 L
1,
#2480
0,
#2500
b111111 L
b111111 >
b111111 I
19
1E
11
1H
1,
#2520
0,
#2540
11
1H
19
1E
b1000000 >
b1000000 I
b1000000 L
1,
#2560
0,
#2580
b1000001 L
b1000001 >
b1000001 I
19
1E
11
1H
1,
#2600
0,
#2620
11
1H
19
1E
b1000010 >
b1000010 I
b1000010 L
1,
#2640
0,
#2660
b1000011 L
b1000011 >
b1000011 I
19
1E
11
1H
1,
#2680
0,
#2700
11
1H
19
1E
b1000100 >
b1000100 I
b1000100 L
1,
#2720
0,
#2740
b1000101 L
b1000101 >
b1000101 I
19
1E
11
1H
1,
#2760
0,
#2780
11
1H
19
1E
b1000110 >
b1000110 I
b1000110 L
1,
#2800
0,
#2820
b1000111 L
b1000111 >
b1000111 I
19
1E
11
1H
1,
#2840
0,
#2860
11
1H
19
1E
b1001000 >
b1001000 I
b1001000 L
1,
#2880
0,
#2900
b1001001 L
b1001001 >
b1001001 I
19
1E
11
1H
1,
#2920
0,
#2940
11
1H
19
1E
b1001010 >
b1001010 I
b1001010 L
1,
#2960
0,
#2980
b1001011 L
b1001011 >
b1001011 I
19
1E
11
1H
1,
#3000
0,
#3020
11
1H
19
1E
b1001100 >
b1001100 I
b1001100 L
1,
#3040
0,
#3060
b1001101 L
b1001101 >
b1001101 I
19
1E
11
1H
1,
#3080
0,
#3100
11
1H
19
1E
b1001110 >
b1001110 I
b1001110 L
1,
#3120
0,
#3140
b1001111 L
b1001111 >
b1001111 I
19
1E
11
1H
1,
#3160
0,
#3180
11
1H
19
1E
b1010000 >
b1010000 I
b1010000 L
1,
#3200
0,
#3220
b1010001 L
b1010001 >
b1010001 I
19
1E
11
1H
1,
#3240
0,
#3260
11
1H
19
1E
b1010010 >
b1010010 I
b1010010 L
1,
#3280
0,
#3300
b1010011 L
b1010011 >
b1010011 I
19
1E
11
1H
1,
#3320
0,
#3340
11
1H
19
1E
b1010100 >
b1010100 I
b1010100 L
1,
#3360
0,
#3380
b1010101 L
b1010101 >
b1010101 I
19
1E
11
1H
1,
#3400
0,
#3420
11
1H
19
1E
b1010110 >
b1010110 I
b1010110 L
1,
#3440
0,
#3460
b1010111 L
b1010111 >
b1010111 I
19
1E
11
1H
1,
#3480
0,
#3500
11
1H
19
1E
b1011000 >
b1011000 I
b1011000 L
1,
#3520
0,
#3540
b1011001 L
b1011001 >
b1011001 I
19
1E
11
1H
1,
#3560
0,
#3580
11
1H
19
1E
b1011010 >
b1011010 I
b1011010 L
1,
#3600
0,
#3620
b1011011 L
b1011011 >
b1011011 I
19
1E
11
1H
1,
#3640
0,
#3660
11
1H
19
1E
b1011100 >
b1011100 I
b1011100 L
1,
#3680
0,
#3700
b1011101 L
b1011101 >
b1011101 I
19
1E
11
1H
1,
#3720
0,
#3740
11
1H
19
1E
b1011110 >
b1011110 I
b1011110 L
1,
#3760
0,
#3780
b1011111 L
b1011111 >
b1011111 I
19
1E
11
1H
1,
#3800
0,
#3820
11
1H
19
1E
b1100000 >
b1100000 I
b1100000 L
1,
#3840
0,
#3860
b1100001 L
b1100001 >
b1100001 I
19
1E
11
1H
1,
#3880
0,
#3900
11
1H
19
1E
b1100010 >
b1100010 I
b1100010 L
1,
#3920
0,
#3940
b1100011 L
b1100011 >
b1100011 I
19
1E
11
1H
1,
#3960
0,
#3980
11
1H
19
1E
b1100100 >
b1100100 I
b1100100 L
1,
#4000
0,
#4020
b1100101 L
b1100101 >
b1100101 I
19
1E
11
1H
1,
#4040
0,
#4060
11
1H
19
1E
b1100110 >
b1100110 I
b1100110 L
1,
#4080
0,
#4100
b1100111 L
b1100111 >
b1100111 I
19
1E
11
1H
1,
#4120
0,
#4140
11
1H
19
1E
b1101000 >
b1101000 I
b1101000 L
1,
#4160
0,
#4180
b1101001 L
b1101001 >
b1101001 I
19
1E
11
1H
1,
#4200
0,
#4220
11
1H
19
1E
b1101010 >
b1101010 I
b1101010 L
1,
#4240
0,
#4260
b1101011 L
b1101011 >
b1101011 I
19
1E
11
1H
1,
#4280
0,
#4300
11
1H
19
1E
b1101100 >
b1101100 I
b1101100 L
1,
#4320
0,
#4340
b1101101 L
b1101101 >
b1101101 I
19
1E
11
1H
1,
#4360
0,
#4380
11
1H
19
1E
b1101110 >
b1101110 I
b1101110 L
1,
#4400
0,
#4420
b1101111 L
b1101111 >
b1101111 I
19
1E
11
1H
1,
#4440
0,
#4460
11
1H
19
1E
b1110000 >
b1110000 I
b1110000 L
1,
#4480
0,
#4500
b1110001 L
b1110001 >
b1110001 I
19
1E
11
1H
1,
#4520
0,
#4540
11
1H
19
1E
b1110010 >
b1110010 I
b1110010 L
1,
#4560
0,
#4580
b1110011 L
b1110011 >
b1110011 I
19
1E
11
1H
1,
#4600
0,
#4620
11
1H
19
1E
b1110100 >
b1110100 I
b1110100 L
1,
#4640
0,
#4660
b1110101 L
b1110101 >
b1110101 I
19
1E
11
1H
1,
#4680
0,
#4700
11
1H
19
1E
b1110110 >
b1110110 I
b1110110 L
1,
#4720
0,
#4740
b1110111 L
b1110111 >
b1110111 I
19
1E
11
1H
1,
#4760
0,
#4780
11
1H
19
1E
b1111000 >
b1111000 I
b1111000 L
1,
#4800
0,
#4820
b1111001 L
b1111001 >
b1111001 I
19
1E
11
1H
1,
#4840
0,
#4860
11
1H
19
1E
b1111010 >
b1111010 I
b1111010 L
1,
#4880
0,
#4900
b1111011 L
b1111011 >
b1111011 I
19
1E
11
1H
1,
#4920
0,
#4940
11
1H
19
1E
b1111100 >
b1111100 I
b1111100 L
1,
#4960
0,
#4980
b1111101 L
b1111101 >
b1111101 I
19
1E
11
1H
1,
#5000
0,
#5020
11
1H
19
1E
b1111110 >
b1111110 I
b1111110 L
1,
#5040
0,
#5060
b1111111 L
b1111111 >
b1111111 I
19
1E
11
1H
1,
#5080
0,
#5100
11
1H
19
1E
b10000000 >
b10000000 I
b10000000 L
1,
#5120
0,
#5140
b10000001 L
b10000001 >
b10000001 I
19
1E
11
1H
1,
#5160
0,
#5180
11
1H
19
1E
b10000010 >
b10000010 I
b10000010 L
1,
#5200
0,
#5220
b10000011 L
b10000011 >
b10000011 I
19
1E
11
1H
1,
#5240
0,
#5260
11
1H
19
1E
b10000100 >
b10000100 I
b10000100 L
1,
#5280
0,
#5300
b10000101 L
b10000101 >
b10000101 I
19
1E
11
1H
1,
#5320
0,
#5340
11
1H
19
1E
b10000110 >
b10000110 I
b10000110 L
1,
#5360
0,
#5380
b10000111 L
b10000111 >
b10000111 I
19
1E
11
1H
1,
#5400
0,
#5420
11
1H
19
1E
b10001000 >
b10001000 I
b10001000 L
1,
#5440
0,
#5460
b10001001 L
b10001001 >
b10001001 I
19
1E
11
1H
1,
#5480
0,
#5500
11
1H
19
1E
b10001010 >
b10001010 I
b10001010 L
1,
#5520
0,
#5540
b10001011 L
b10001011 >
b10001011 I
19
1E
11
1H
1,
#5560
0,
#5580
11
1H
19
1E
b10001100 >
b10001100 I
b10001100 L
1,
#5600
0,
#5620
b10001101 L
b10001101 >
b10001101 I
19
1E
11
1H
1,
#5640
0,
#5660
11
1H
19
1E
b10001110 >
b10001110 I
b10001110 L
1,
#5680
0,
#5700
b10001111 L
b10001111 >
b10001111 I
19
1E
11
1H
1,
#5720
0,
#5740
11
1H
19
1E
b10010000 >
b10010000 I
b10010000 L
1,
#5760
0,
#5780
b10010001 L
b10010001 >
b10010001 I
19
1E
11
1H
1,
#5800
0,
#5820
11
1H
19
1E
b10010010 >
b10010010 I
b10010010 L
1,
#5840
0,
#5860
b10010011 L
b10010011 >
b10010011 I
19
1E
11
1H
1,
#5880
0,
#5900
11
1H
19
1E
b10010100 >
b10010100 I
b10010100 L
1,
#5920
0,
#5940
b10010101 L
b10010101 >
b10010101 I
19
1E
11
1H
1,
#5960
0,
#5980
11
1H
19
1E
b10010110 >
b10010110 I
b10010110 L
1,
#6000
0,
#6020
b10010111 L
b10010111 >
b10010111 I
19
1E
11
1H
1,
#6040
0,
#6060
11
1H
19
1E
b10011000 >
b10011000 I
b10011000 L
1,
#6080
0,
#6100
b10011001 L
b10011001 >
b10011001 I
19
1E
11
1H
1,
#6120
0,
#6140
11
1H
19
1E
b10011010 >
b10011010 I
b10011010 L
1,
#6160
0,
#6180
b10011011 L
b10011011 >
b10011011 I
19
1E
11
1H
1,
#6200
0,
#6220
11
1H
19
1E
b10011100 >
b10011100 I
b10011100 L
1,
#6240
0,
#6260
b10011101 L
b10011101 >
b10011101 I
19
1E
11
1H
1,
#6280
0,
#6300
11
1H
19
1E
b10011110 >
b10011110 I
b10011110 L
1,
#6320
0,
#6340
b10011111 L
b10011111 >
b10011111 I
19
1E
11
1H
1,
#6360
0,
#6380
11
1H
19
1E
b10100000 >
b10100000 I
b10100000 L
1,
#6400
0,
#6420
b10100001 L
b10100001 >
b10100001 I
19
1E
11
1H
1,
#6440
0,
#6460
11
1H
19
1E
b10100010 >
b10100010 I
b10100010 L
1,
#6480
0,
#6500
b10100011 L
b10100011 >
b10100011 I
19
1E
11
1H
1,
#6520
0,
#6540
11
1H
19
1E
b10100100 >
b10100100 I
b10100100 L
1,
#6560
0,
#6580
b10100101 L
b10100101 >
b10100101 I
19
1E
11
1H
1,
#6600
0,
#6620
11
1H
19
1E
b10100110 >
b10100110 I
b10100110 L
1,
#6640
0,
#6660
b10100111 L
b10100111 >
b10100111 I
19
1E
11
1H
1,
#6680
0,
#6700
11
1H
19
1E
b10101000 >
b10101000 I
b10101000 L
1,
#6720
0,
#6740
b10101001 L
b10101001 >
b10101001 I
19
1E
11
1H
1,
#6760
0,
#6780
11
1H
19
1E
b10101010 >
b10101010 I
b10101010 L
1,
#6800
0,
#6820
b10101011 L
b10101011 >
b10101011 I
19
1E
11
1H
1,
#6840
0,
#6860
11
1H
19
1E
b10101100 >
b10101100 I
b10101100 L
1,
#6880
0,
#6900
b10101101 L
b10101101 >
b10101101 I
19
1E
11
1H
1,
#6920
0,
#6940
11
1H
19
1E
b10101110 >
b10101110 I
b10101110 L
1,
#6960
0,
#6980
b10101111 L
b10101111 >
b10101111 I
19
1E
11
1H
1,
#7000
0,
#7020
11
1H
19
1E
b10110000 >
b10110000 I
b10110000 L
1,
#7040
0,
#7060
b10110001 L
b10110001 >
b10110001 I
19
1E
11
1H
1,
#7080
0,
#7100
11
1H
19
1E
b10110010 >
b10110010 I
b10110010 L
1,
#7120
0,
#7140
b10110011 L
b10110011 >
b10110011 I
19
1E
11
1H
1,
#7160
0,
#7180
11
1H
19
1E
b10110100 >
b10110100 I
b10110100 L
1,
#7200
0,
#7220
b10110101 L
b10110101 >
b10110101 I
19
1E
11
1H
1,
#7240
0,
#7260
11
1H
19
1E
b10110110 >
b10110110 I
b10110110 L
1,
#7280
0,
#7300
b10110111 L
b10110111 >
b10110111 I
19
1E
11
1H
1,
#7320
0,
#7340
11
1H
19
1E
b10111000 >
b10111000 I
b10111000 L
1,
#7360
0,
#7380
b10111001 L
b10111001 >
b10111001 I
19
1E
11
1H
1,
#7400
0,
#7420
11
1H
19
1E
b10111010 >
b10111010 I
b10111010 L
1,
#7440
0,
#7460
b10111011 L
b10111011 >
b10111011 I
19
1E
11
1H
1,
#7480
0,
#7500
11
1H
19
1E
b10111100 >
b10111100 I
b10111100 L
1,
#7520
0,
#7540
b10111101 L
b10111101 >
b10111101 I
19
1E
11
1H
1,
#7560
0,
#7580
11
1H
19
1E
b10111110 >
b10111110 I
b10111110 L
1,
#7600
0,
#7620
b10111111 L
b10111111 >
b10111111 I
19
1E
11
1H
1,
#7640
0,
#7660
11
1H
19
1E
b11000000 >
b11000000 I
b11000000 L
1,
#7680
0,
#7700
b11000001 L
b11000001 >
b11000001 I
19
1E
11
1H
1,
#7720
0,
#7740
11
1H
19
1E
b11000010 >
b11000010 I
b11000010 L
1,
#7760
0,
#7780
b11000011 L
b11000011 >
b11000011 I
19
1E
11
1H
1,
#7800
0,
#7820
11
1H
19
1E
b11000100 >
b11000100 I
b11000100 L
1,
#7840
0,
#7860
b11000101 L
b11000101 >
b11000101 I
19
1E
11
1H
1,
#7880
0,
#7900
11
1H
19
1E
b11000110 >
b11000110 I
b11000110 L
1,
#7920
0,
#7940
b11000111 L
b11000111 >
b11000111 I
19
1E
11
1H
1,
#7960
0,
#7980
11
1H
19
1E
b11001000 >
b11001000 I
b11001000 L
1,
#8000
0,
#8020
b11001001 L
b11001001 >
b11001001 I
19
1E
11
1H
1,
#8040
0,
#8060
11
1H
19
1E
b11001010 >
b11001010 I
b11001010 L
1,
#8080
0,
#8100
b11001011 L
b11001011 >
b11001011 I
19
1E
11
1H
1,
#8120
0,
#8140
11
1H
19
1E
b11001100 >
b11001100 I
b11001100 L
1,
#8160
0,
#8180
b11001101 L
b11001101 >
b11001101 I
19
1E
11
1H
1,
#8200
0,
#8220
11
1H
19
1E
b11001110 >
b11001110 I
b11001110 L
1,
#8240
0,
#8260
b11001111 L
b11001111 >
b11001111 I
19
1E
11
1H
1,
#8280
0,
