VGA/Sync_Pulse.v
module Sync_Pulse( //IMPROVE: add parameters
input CLK,
output reg H_Sync = 1'b1,
output reg V_Sync = 1'b1,
output reg [9:0] CountCol = 0,
output reg [9:0] CountRow = 0
);

// 800 Col by 525 Row
// 640 Col Active, 160 Col H-Sync
// 480 Row Active, 45 Row V-Sync

// 25Mhz Clock / (800 by 525) Area = 60Hz refresh rate (60 clock cycles per pixel per second)

always @(posedge CLK)
begin
  if (CountCol < 639) begin //target-1
    H_Sync <= 1'b1;
    CountCol <= CountCol + 1; end
  else if (CountCol < 799) begin
    H_Sync <= 1'b0;
    CountCol <= CountCol + 1; end
  else 
  begin
    CountCol <= 0;
    H_Sync <= 1'b1;
    
    if (CountRow < 479) begin
      V_Sync <= 1'b1;
      CountRow <= CountRow + 1; end
    else if (CountRow < 524) begin 
      V_Sync <= 1'b0;
      CountRow <= CountRow + 1; end
    else begin
      CountRow <= 0;
      V_Sync <= 1'b1; end
  end
end

//assign H_Sync = 

//IMPROVE: logic above and assignment statements using ?:

endmodule

VGA/Pattern_Generator.v
module Pattern_Generator(
input CLK,
input i_SW1, i_SW2, i_SW3, i_SW4,
output reg [2:0] Red = 0,
output reg [2:0] Green = 0,
output reg [2:0] Blue = 0
);

wire [9:0] w_CountCol = 0;
wire [9:0] w_CountRow = 0;
reg [9:0] r_CountCol = 0;
reg [9:0] r_CountRow = 0;

Sync_Pulse Inst (
 .CLK(CLK),
 .H_Sync(),
 .V_Sync(),
 .CountCol(w_CountCol),
 .CountRow(w_CountRow)
 );

always @(posedge CLK)
begin
  r_CountCol <= w_CountCol;
  r_CountRow <= w_CountRow;
  if (i_SW1) begin //!,1,A,Q,a,q
    Red <= (w_CountCol < 640 && w_CountRow < 480) ? 3'b111 : 0;
    Green <= 0;
    Blue <= 0; end
  else if (i_SW2) begin //",2,B,R,b,r
    Red <= 0;
    Green <= (w_CountCol < 640 && w_CountRow < 480) ? 3'b111 : 0;
    Blue <= 0; end
  else if (i_SW3) begin //#,3...
    Red <= 0;
    Green <= 0;
    Blue <= (w_CountCol < 640 && w_CountRow < 480) ? 3'b111 : 0; end
  else if (i_SW4) begin //anything else makes screen Black
    Red <= 0; 
    Green <= 0;
    Blue <= 0; end
end

endmodule

VGA/Sync_Porch.v
//This module alters the Sync_pulse signal to include the front & back porch

//Whole area -> 800x525, Visible area -> 640x480
//Hsync -> front: 18, back: 50, pulse: 92
//Vsync -> front: 10, back: 33, pulse: 2


module Sync_Porch(
  input CLK,
  input i_H_Sync,
  input i_V_Sync,
  output reg o_H_Sync = 1'b1, 
  output reg o_V_Sync = 1'b1);
  
  reg r_H_Sync = 1'b1;
  reg [4:0] r_HCountBP = 0;
  reg [6:0] r_HCountPulse = 0;
  
  reg r_V_Sync = 1'b1;
  reg [4:0] r_VCountBP = 0;
  reg [6:0] r_VCountPulse = 0;
  
  always @(posedge CLK)
  begin
    if (i_H_Sync == 0 && r_HCountBP !== 17) //falling edge
      r_HCountBP <= r_HCountBP + 1;
    else
      r_H_Sync <= 0;
      
    if (r_HCountBP == 17 && r_HCountPulse !== 92)
      r_HCountPulse <= r_HCountPulse + 1;
    else
      r_H_Sync <= 1;
      
    if (i_H_Sync == 1) 
      begin
      r_HCountBP <= 0;
      r_HCountPulse <= 0; 
      end
  end
  
  
  always @(posedge CLK)
  begin
    if (i_V_Sync == 0 && r_VCountBP !== 9) //falling edge
      r_VCountBP <= r_VCountBP + 1;
    else
      r_V_Sync <= 0;
      
    if (r_VCountBP == 9 && r_VCountPulse !== 2)
      r_VCountPulse <= r_VCountPulse + 1;
    else
      r_V_Sync <= 1;
      
    if (i_V_Sync == 1) 
      begin
      r_VCountBP <= 0;
      r_VCountPulse <= 0; 
      end

    assign o_H_Sync = r_H_Sync;
    assign o_V_Sync = r_V_Sync;
  end
  
endmodule

Seven_Seg_Counter/Debounce_Switch.v
module Debounce_Switch(
	input CLK,
	input Switch,
	output o_Switch);
	
parameter c_DEBOUNCE_LIMIT = 250000;// 10 ms at 25 MHz

reg r_State = 1'b0;
reg [17:0] r_Count = 0;

always @(posedge CLK) begin// COUNTER LOGIC
	if (Switch !== r_State && r_Count < c_DEBOUNCE_LIMIT)
		r_Count <= r_Count + 1;
	else if (r_Count == c_DEBOUNCE_LIMIT) begin
		r_Count <= 0;
		r_State <= Switch;end
	else
		r_Count <= 0;
	end

assign o_Switch = r_State;

endmodule

VGA/top_VGA.v
//TODO: 
// add parameters
// change variable names
// improve Sync_Pulse and Sync_Porch logic like using '?:' in assign statements
// use case for Pattern Gen
// implement RX and TX, keyboard input, and display
// figure out VGA display and UART on windows
 
module top_VGA(
input CLK,
input SW1, SW2, SW3, SW4,
output VGA_HS, VGA_VS, 
output VGA_R0, VGA_R1, VGA_R2,
output VGA_G0, VGA_G1, VGA_G2, 
output VGA_B0, VGA_B1, VGA_B2
);

wire w_SW1, w_SW2, w_SW3, w_SW4;
wire w_H_Sync, w_V_Sync;
wire [2:0] w_Red;
wire [2:0] w_Green;
wire [2:0] w_Blue;

Debounce_Switch debounceInst1
  (.CLK(CLK),
   .Switch(SW1),
   .o_Switch(w_SW1));
Debounce_Switch debounceInst2
  (.CLK(CLK),
   .Switch(SW2),
   .o_Switch(w_SW2));
Debounce_Switch debounceInst3
  (.CLK(CLK),
   .Switch(SW3),
   .o_Switch(w_SW3));
Debounce_Switch debounceInst4
  (.CLK(CLK),
   .Switch(SW4),
   .o_Switch(w_SW4));
   
Sync_Pulse PulseInst
 (.CLK(CLK),
  .H_Sync(w_H_Sync),
  .V_Sync(w_H_Sync),
  .CountCol(),
  .CountRow()
  );
  
Sync_Porch PorchInst
 (.CLK(CLK),
  .i_H_Sync(w_H_Sync),
  .i_V_Sync(w_V_Sync),
  .o_H_Sync(VGA_HS),
  .o_V_Sync(VGA_VS)
  );

Pattern_Generator Pattern_GenInst
 (.CLK(CLK),
  .i_SW1(SW1), 
  .i_SW2(SW2), 
  .i_SW3(SW3), 
  .i_SW4(SW4),
  .Red(w_Red), 
  .Green(w_Green),
  .Blue(w_Blue)
  );

assign r_H_Sync = w_H_Sync;

assign VGA_R0 = w_Red[0];
assign VGA_R1 = w_Red[1];
assign VGA_R2 = w_Red[2];

assign VGA_G0 = w_Green[0];
assign VGA_G1 = w_Green[1];
assign VGA_G2 = w_Green[2];

assign VGA_B0 = w_Blue[0];
assign VGA_B1 = w_Blue[1];
assign VGA_B2 = w_Blue[2];

endmodule;

VGA/Sync_Pulse_tb.v
//RUN TB: iverilog -o simulation_tb Sync_Pulse.v Sync_Pulse_tb.v
//	  vvp simulation_tb


`timescale 1ns/1ns
module Sync_Pulse_tb();
  
  reg r_Clock = 0;
  wire H_Sync, V_Sync, r0,r1,r2,g0,g1,g2,b0,b1,b2;
  
 top_VGA inst
  (.CLK(r_Clock),
   .SW1(1'b1),
   .SW2(1'b0),
   .SW3(1'b0),
   .SW4(1'b0),
   .VGA_HS(H_Sync),
   .VGA_VS(V_Sync),
   .VGA_R0(r0),
   .VGA_R1(r1),
   .VGA_R2(r2),
   .VGA_G0(g0),
   .VGA_G1(g1),
   .VGA_G2(g2),
   .VGA_B0(b0),
   .VGA_B1(b1),
   .VGA_B2(b2)
   );
  
  always #(20)
    r_Clock <= ~r_Clock;

  always @(posedge r_Clock)
    begin
    end
  
  initial
    begin
    $dumpfile("dump.vcd");
    $dumpvars(0);
    
    #500000
    $finish;
    end
  
endmodule

VGA/dump.vcd
$date
	Wed Jul 17 18:07:09 2024
$end
$version
	Icarus Verilog
$end
$timescale
	1ns
$end
$scope module Sync_Pulse_tb $end
$var wire 1 ! r2 $end
$var wire 1 " r1 $end
$var wire 1 # r0 $end
$var wire 1 $ g2 $end
$var wire 1 % g1 $end
$var wire 1 & g0 $end
$var wire 1 ' b2 $end
$var wire 1 ( b1 $end
$var wire 1 ) b0 $end
$var wire 1 * V_Sync $end
$var wire 1 + H_Sync $end
$var reg 1 , r_Clock $end
$scope module inst $end
$var wire 1 , CLK $end
$var wire 1 - SW1 $end
$var wire 1 . SW2 $end
$var wire 1 / SW3 $end
$var wire 1 0 SW4 $end
$var wire 1 1 w_H_Sync $end
$var wire 1 2 w_V_Sync $end
$var wire 1 3 w_SW4 $end
$var wire 1 4 w_SW3 $end
$var wire 1 5 w_SW2 $end
$var wire 1 6 w_SW1 $end
$var wire 3 7 w_Red [2:0] $end
$var wire 3 8 w_Green [2:0] $end
$var wire 3 9 w_Blue [2:0] $end
$var wire 1 * VGA_VS $end
$var wire 1 ! VGA_R2 $end
$var wire 1 " VGA_R1 $end
$var wire 1 # VGA_R0 $end
$var wire 1 + VGA_HS $end
$var wire 1 $ VGA_G2 $end
$var wire 1 % VGA_G1 $end
$var wire 1 & VGA_G0 $end
$var wire 1 ' VGA_B2 $end
$var wire 1 ( VGA_B1 $end
$var wire 1 ) VGA_B0 $end
$scope module Pattern_GenInst $end
$var wire 1 , CLK $end
$var wire 1 - i_SW1 $end
$var wire 1 . i_SW2 $end
$var wire 1 / i_SW3 $end
$var wire 1 0 i_SW4 $end
$var wire 10 : w_CountCol [9:0] $end
$var wire 10 ; w_CountRow [9:0] $end
$var reg 3 < Blue [2:0] $end
$var reg 3 = Green [2:0] $end
$var reg 3 > Red [2:0] $end
$var reg 10 ? r_CountCol [9:0] $end
$var reg 10 @ r_CountRow [9:0] $end
$scope module Inst $end
$var wire 1 , CLK $end
$var reg 10 A CountCol [9:0] $end
$var reg 10 B CountRow [9:0] $end
$var reg 1 C H_Sync $end
$var reg 1 D V_Sync $end
$upscope $end
$upscope $end
$scope module PorchInst $end
$var wire 1 , CLK $end
$var wire 1 1 i_H_Sync $end
$var wire 1 2 i_V_Sync $end
$var reg 1 + o_H_Sync $end
$var reg 1 * o_V_Sync $end
$var reg 5 E r_HCountBP [4:0] $end
$var reg 7 F r_HCountPulse [6:0] $end
$var reg 1 G r_H_Sync $end
$var reg 5 H r_VCountBP [4:0] $end
$var reg 7 I r_VCountPulse [6:0] $end
$var reg 1 J r_V_Sync $end
$upscope $end
$scope module PulseInst $end
$var wire 1 , CLK $end
$var reg 10 K CountCol [9:0] $end
$var reg 10 L CountRow [9:0] $end
$var reg 1 M H_Sync $end
$var reg 1 N V_Sync $end
$upscope $end
$scope module debounceInst1 $end
$var wire 1 , CLK $end
$var wire 1 - Switch $end
$var wire 1 6 o_Switch $end
$var parameter 32 O c_DEBOUNCE_LIMIT $end
$var reg 18 P r_Count [17:0] $end
$var reg 1 Q r_State $end
$upscope $end
$scope module debounceInst2 $end
$var wire 1 , CLK $end
$var wire 1 . Switch $end
$var wire 1 5 o_Switch $end
$var parameter 32 R c_DEBOUNCE_LIMIT $end
$var reg 18 S r_Count [17:0] $end
$var reg 1 T r_State $end
$upscope $end
$scope module debounceInst3 $end
$var wire 1 , CLK $end
$var wire 1 / Switch $end
$var wire 1 4 o_Switch $end
$var parameter 32 U c_DEBOUNCE_LIMIT $end
$var reg 18 V r_Count [17:0] $end
$var reg 1 W r_State $end
$upscope $end
$scope module debounceInst4 $end
$var wire 1 , CLK $end
$var wire 1 0 Switch $end
$var wire 1 3 o_Switch $end
$var parameter 32 X c_DEBOUNCE_LIMIT $end
$var reg 18 Y r_Count [17:0] $end
$var reg 1 Z r_State $end
$upscope $end
$upscope $end
$upscope $end
$enddefinitions $end
$comment Show the parameter values. $end
$dumpall
b111101000010010000 X
b111101000010010000 U
b111101000010010000 R
b111101000010010000 O
$end
#0
$dumpvars
0Z
b0 Y
0W
b0 V
0T
b0 S
0Q
b0 P
1N
1M
b0 L
b0 K
1J
b0 I
b0 H
1G
b0 F
b0 E
1D
1C
b0 B
b0 A
b0 @
b0 ?
b0 >
b0 =
b0 <
b0 ;
b0 :
b0 9
b0 8
b0 7
06
05
04
03
z2
11
00
0/
0.
1-
0,
1+
1*
0)
0(
0'
0&
0%
0$
0#
0"
0!
$end
#20
1!
1"
1#
b1 P
b1 K
1+
1G
1*
1J
b0x :
b1 A
b111 7
b111 >
1,
#40
0,
#60
x!
x"
x#
bx 7
bx >
b0x ?
b0x0 :
b10 A
1*
1J
1+
1G
b10 K
b10 P
1,
#80
0,
#100
b11 P
b11 K
1+
1G
1*
1J
b0xx :
b11 A
b0x0 ?
1,
#120
0,
#140
b0xx ?
b0x00 :
b100 A
1*
1J
1+
1G
b100 K
b100 P
1,
#160
0,
#180
b101 P
b101 K
1+
1G
1*
1J
b0x0x :
b101 A
b0x00 ?
1,
#200
0,
#220
b0x0x ?
b0xx0 :
b110 A
1*
1J
1+
1G
b110 K
b110 P
1,
#240
0,
#260
b111 P
b111 K
1+
1G
1*
1J
b0xxx :
b111 A
b0xx0 ?
1,
#280
0,
#300
b0xxx ?
b0x000 :
b1000 A
1*
1J
1+
1G
b1000 K
b1000 P
1,
#320
0,
#340
b1001 P
b1001 K
1+
1G
1*
1J
b0x00x :
b1001 A
b0x000 ?
1,
#360
0,
#380
b0x00x ?
b0x0x0 :
b1010 A
1*
1J
1+
1G
b1010 K
b1010 P
1,
#400
0,
#420
b1011 P
b1011 K
1+
1G
1*
1J
b0x0xx :
b1011 A
b0x0x0 ?
1,
#440
0,
#460
b0x0xx ?
b0xx00 :
b1100 A
1*
1J
1+
1G
b1100 K
b1100 P
1,
#480
0,
#500
b1101 P
b1101 K
1+
1G
1*
1J
b0xx0x :
b1101 A
b0xx00 ?
1,
#520
0,
#540
b0xx0x ?
b0xxx0 :
b1110 A
1*
1J
1+
1G
b1110 K
b1110 P
1,
#560
0,
#580
b1111 P
b1111 K
1+
1G
1*
1J
b0xxxx :
b1111 A
b0xxx0 ?
1,
#600
0,
#620
b0xxxx ?
b0x0000 :
b10000 A
1*
1J
1+
1G
b10000 K
b10000 P
1,
#640
0,
#660
b10001 P
b10001 K
1+
1G
1*
1J
b0x000x :
b10001 A
b0x0000 ?
1,
#680
0,
#700
b0x000x ?
b0x00x0 :
b10010 A
1*
1J
1+
1G
b10010 K
b10010 P
1,
#720
0,
#740
b10011 P
b10011 K
1+
1G
1*
1J
b0x00xx :
b10011 A
b0x00x0 ?
1,
#760
0,
#780
b0x00xx ?
b0x0x00 :
b10100 A
1*
1J
1+
1G
b10100 K
b10100 P
1,
#800
0,
#820
b10101 P
b10101 K
1+
1G
1*
1J
b0x0x0x :
b10101 A
b0x0x00 ?
1,
#840
0,
#860
b0x0x0x ?
b0x0xx0 :
b10110 A
1*
1J
1+
1G
b10110 K
b10110 P
1,
#880
0,
#900
b10111 P
b10111 K
1+
1G
1*
1J
b0x0xxx :
b10111 A
b0x0xx0 ?
1,
#920
0,
#940
b0x0xxx ?
b0xx000 :
b11000 A
1*
1J
1+
1G
b11000 K
b11000 P
1,
#960
0,
#980
b11001 P
b11001 K
1+
1G
1*
1J
b0xx00x :
b11001 A
b0xx000 ?
1,
#1000
0,
#1020
b0xx00x ?
b0xx0x0 :
b11010 A
1*
1J
1+
1G
b11010 K
b11010 P
1,
#1040
0,
#1060
b11011 P
b11011 K
1+
1G
1*
1J
b0xx0xx :
b11011 A
b0xx0x0 ?
1,
#1080
0,
#1100
b0xx0xx ?
b0xxx00 :
b11100 A
1*
1J
1+
1G
b11100 K
b11100 P
1,
#1120
0,
#1140
b11101 P
b11101 K
1+
1G
1*
1J
b0xxx0x :
b11101 A
b0xxx00 ?
1,
#1160
0,
#1180
b0xxx0x ?
b0xxxx0 :
b11110 A
1*
1J
1+
1G
b11110 K
b11110 P
1,
#1200
0,
#1220
b11111 P
b11111 K
1+
1G
1*
1J
b0xxxxx :
b11111 A
b0xxxx0 ?
1,
#1240
0,
#1260
b0xxxxx ?
b0x00000 :
b100000 A
1*
1J
1+
1G
b100000 K
b100000 P
1,
#1280
0,
#1300
b100001 P
b100001 K
1+
1G
1*
1J
b0x0000x :
b100001 A
b0x00000 ?
1,
#1320
0,
#1340
b0x0000x ?
b0x000x0 :
b100010 A
1*
1J
1+
1G
b100010 K
b100010 P
1,
#1360
0,
#1380
b100011 P
b100011 K
1+
1G
1*
1J
b0x000xx :
b100011 A
b0x000x0 ?
1,
#1400
0,
#1420
b0x000xx ?
b0x00x00 :
b100100 A
1*
1J
1+
1G
b100100 K
b100100 P
1,
#1440
0,
#1460
b100101 P
b100101 K
1+
1G
1*
1J
b0x00x0x :
b100101 A
b0x00x00 ?
1,
#1480
0,
#1500
b0x00x0x ?
b0x00xx0 :
b100110 A
1*
1J
1+
1G
b100110 K
b100110 P
1,
#1520
0,
#1540
b100111 P
b100111 K
1+
1G
1*
1J
b0x00xxx :
b100111 A
b0x00xx0 ?
1,
#1560
0,
#1580
b0x00xxx ?
b0x0x000 :
b101000 A
1*
1J
1+
1G
b101000 K
b101000 P
1,
#1600
0,
#1620
b101001 P
b101001 K
1+
1G
1*
1J
b0x0x00x :
b101001 A
b0x0x000 ?
1,
#1640
0,
#1660
b0x0x00x ?
b0x0x0x0 :
b101010 A
1*
1J
1+
1G
b101010 K
b101010 P
1,
#1680
0,
#1700
b101011 P
b101011 K
1+
1G
1*
1J
b0x0x0xx :
b101011 A
b0x0x0x0 ?
1,
#1720
0,
#1740
b0x0x0xx ?
b0x0xx00 :
b101100 A
1*
1J
1+
1G
b101100 K
b101100 P
1,
#1760
0,
#1780
b101101 P
b101101 K
1+
1G
1*
1J
b0x0xx0x :
b101101 A
b0x0xx00 ?
1,
#1800
0,
#1820
b0x0xx0x ?
b0x0xxx0 :
b101110 A
1*
1J
1+
1G
b101110 K
b101110 P
1,
#1840
0,
#1860
b101111 P
b101111 K
1+
1G
1*
1J
b0x0xxxx :
b101111 A
b0x0xxx0 ?
1,
#1880
0,
#1900
b0x0xxxx ?
b0xx0000 :
b110000 A
1*
1J
1+
1G
b110000 K
b110000 P
1,
#1920
0,
#1940
b110001 P
b110001 K
1+
1G
1*
1J
b0xx000x :
b110001 A
b0xx0000 ?
1,
#1960
0,
#1980
b0xx000x ?
b0xx00x0 :
b110010 A
1*
1J
1+
1G
b110010 K
b110010 P
1,
#2000
0,
#2020
b110011 P
b110011 K
1+
1G
1*
1J
b0xx00xx :
b110011 A
b0xx00x0 ?
1,
#2040
0,
#2060
b0xx00xx ?
b0xx0x00 :
b110100 A
1*
1J
1+
1G
b110100 K
b110100 P
1,
#2080
0,
#2100
b110101 P
b110101 K
1+
1G
1*
1J
b0xx0x0x :
b110101 A
b0xx0x00 ?
1,
#2120
0,
#2140
b0xx0x0x ?
b0xx0xx0 :
b110110 A
1*
1J
1+
1G
b110110 K
b110110 P
1,
#2160
0,
#2180
b110111 P
b110111 K
1+
1G
1*
1J
b0xx0xxx :
b110111 A
b0xx0xx0 ?
1,
#2200
0,
#2220
b0xx0xxx ?
b0xxx000 :
b111000 A
1*
1J
1+
1G
b111000 K
b111000 P
1,
#2240
0,
#2260
b111001 P
b111001 K
1+
1G
1*
1J
b0xxx00x :
b111001 A
b0xxx000 ?
1,
#2280
0,
#2300
b0xxx00x ?
b0xxx0x0 :
b111010 A
1*
1J
1+
1G
b111010 K
b111010 P
1,
#2320
0,
#2340
b111011 P
b111011 K
1+
1G
1*
1J
b0xxx0xx :
b111011 A
b0xxx0x0 ?
1,
#2360
0,
#2380
b0xxx0xx ?
b0xxxx00 :
b111100 A
1*
1J
1+
1G
b111100 K
b111100 P
1,
#2400
0,
#2420
b111101 P
b111101 K
1+
1G
1*
1J
b0xxxx0x :
b111101 A
b0xxxx00 ?
1,
#2440
0,
#2460
b0xxxx0x ?
b0xxxxx0 :
b111110 A
1*
1J
1+
1G
b111110 K
b111110 P
1,
#2480
0,
#2500
b111111 P
b111111 K
1+
1G
1*
1J
b0xxxxxx :
b111111 A
b0xxxxx0 ?
1,
#2520
0,
#2540
b0xxxxxx ?
b0x000000 :
b1000000 A
1*
1J
1+
1G
b1000000 K
b1000000 P
1,
#2560
0,
#2580
b1000001 P
b1000001 K
1+
1G
1*
1J
b0x00000x :
b1000001 A
b0x000000 ?
1,
#2600
0,
#2620
b0x00000x ?
b0x0000x0 :
b1000010 A
1*
1J
1+
1G
b1000010 K
b1000010 P
1,
#2640
0,
#2660
b1000011 P
b1000011 K
1+
1G
1*
1J
b0x0000xx :
b1000011 A
b0x0000x0 ?
1,
#2680
0,
#2700
b0x0000xx ?
b0x000x00 :
b1000100 A
1*
1J
1+
1G
b1000100 K
b1000100 P
1,
#2720
0,
#2740
b1000101 P
b1000101 K
1+
1G
1*
1J
b0x000x0x :
b1000101 A
b0x000x00 ?
1,
#2760
0,
#2780
b0x000x0x ?
b0x000xx0 :
b1000110 A
1*
1J
1+
1G
b1000110 K
b1000110 P
1,
#2800
0,
#2820
b1000111 P
b1000111 K
1+
1G
1*
1J
b0x000xxx :
b1000111 A
b0x000xx0 ?
1,
#2840
0,
#2860
b0x000xxx ?
b0x00x000 :
b1001000 A
1*
1J
1+
1G
b1001000 K
b1001000 P
1,
#2880
0,
#2900
b1001001 P
b1001001 K
1+
1G
1*
1J
b0x00x00x :
b1001001 A
b0x00x000 ?
1,
#2920
0,
#2940
b0x00x00x ?
b0x00x0x0 :
b1001010 A
1*
1J
1+
1G
b1001010 K
b1001010 P
1,
#2960
0,
#2980
b1001011 P
b1001011 K
1+
1G
1*
1J
b0x00x0xx :
b1001011 A
b0x00x0x0 ?
1,
#3000
0,
#3020
b0x00x0xx ?
b0x00xx00 :
b1001100 A
1*
1J
1+
1G
b1001100 K
b1001100 P
1,
#3040
0,
#3060
b1001101 P
b1001101 K
1+
1G
1*
1J
b0x00xx0x :
b1001101 A
b0x00xx00 ?
1,
#3080
0,
#3100
b0x00xx0x ?
b0x00xxx0 :
b1001110 A
1*
1J
1+
1G
b1001110 K
b1001110 P
1,
#3120
0,
#3140
b1001111 P
b1001111 K
1+
1G
1*
1J
b0x00xxxx :
b1001111 A
b0x00xxx0 ?
1,
#3160
0,
#3180
b0x00xxxx ?
b0x0x0000 :
b1010000 A
1*
1J
1+
1G
b1010000 K
b1010000 P
1,
#3200
0,
#3220
b1010001 P
b1010001 K
1+
1G
1*
1J
b0x0x000x :
b1010001 A
b0x0x0000 ?
1,
#3240
0,
#3260
b0x0x000x ?
b0x0x00x0 :
b1010010 A
1*
1J
1+
1G
b1010010 K
b1010010 P
1,
#3280
0,
#3300
b1010011 P
b1010011 K
1+
1G
1*
1J
b0x0x00xx :
b1010011 A
b0x0x00x0 ?
1,
#3320
0,
#3340
b0x0x00xx ?
b0x0x0x00 :
b1010100 A
1*
1J
1+
1G
b1010100 K
b1010100 P
1,
#3360
0,
#3380
b1010101 P
b1010101 K
1+
1G
1*
1J
b0x0x0x0x :
b1010101 A
b0x0x0x00 ?
1,
#3400
0,
#3420
b0x0x0x0x ?
b0x0x0xx0 :
b1010110 A
1*
1J
1+
1G
b1010110 K
b1010110 P
1,
#3440
0,
#3460
b1010111 P
b1010111 K
1+
1G
1*
1J
b0x0x0xxx :
b1010111 A
b0x0x0xx0 ?
1,
#3480
0,
#3500
b0x0x0xxx ?
b0x0xx000 :
b1011000 A
1*
1J
1+
1G
b1011000 K
b1011000 P
1,
#3520
0,
#3540
b1011001 P
b1011001 K
1+
1G
1*
1J
b0x0xx00x :
b1011001 A
b0x0xx000 ?
1,
#3560
0,
#3580
b0x0xx00x ?
b0x0xx0x0 :
b1011010 A
1*
1J
1+
1G
b1011010 K
b1011010 P
1,
#3600
0,
#3620
b1011011 P
b1011011 K
1+
1G
1*
1J
b0x0xx0xx :
b1011011 A
b0x0xx0x0 ?
1,
#3640
0,
#3660
b0x0xx0xx ?
b0x0xxx00 :
b1011100 A
1*
1J
1+
1G
b1011100 K
b1011100 P
1,
#3680
0,
#3700
b1011101 P
b1011101 K
1+
1G
1*
1J
b0x0xxx0x :
b1011101 A
b0x0xxx00 ?
1,
#3720
0,
#3740
b0x0xxx0x ?
b0x0xxxx0 :
b1011110 A
1*
1J
1+
1G
b1011110 K
b1011110 P
1,
#3760
0,
#3780
b1011111 P
b1011111 K
1+
1G
1*
1J
b0x0xxxxx :
b1011111 A
b0x0xxxx0 ?
1,
#3800
0,
#3820
b0x0xxxxx ?
b0xx00000 :
b1100000 A
1*
1J
1+
1G
b1100000 K
b1100000 P
1,
#3840
0,
#3860
b1100001 P
b1100001 K
1+
1G
1*
1J
b0xx0000x :
b1100001 A
b0xx00000 ?
1,
#3880
0,
#3900
b0xx0000x ?
b0xx000x0 :
b1100010 A
1*
1J
1+
1G
b1100010 K
b1100010 P
1,
#3920
0,
#3940
b1100011 P
b1100011 K
1+
1G
1*
1J
b0xx000xx :
b1100011 A
b0xx000x0 ?
1,
#3960
0,
#3980
b0xx000xx ?
b0xx00x00 :
b1100100 A
1*
1J
1+
1G
b1100100 K
b1100100 P
1,
#4000
0,
#4020
b1100101 P
b1100101 K
1+
1G
1*
1J
b0xx00x0x :
b1100101 A
b0xx00x00 ?
1,
#4040
0,
#4060
b0xx00x0x ?
b0xx00xx0 :
b1100110 A
1*
1J
1+
1G
b1100110 K
b1100110 P
1,
#4080
0,
#4100
b1100111 P
b1100111 K
1+
1G
1*
1J
b0xx00xxx :
b1100111 A
b0xx00xx0 ?
1,
#4120
0,
#4140
b0xx00xxx ?
b0xx0x000 :
b1101000 A
1*
1J
1+
1G
b1101000 K
b1101000 P
1,
#4160
0,
#4180
b1101001 P
b1101001 K
1+
1G
1*
1J
b0xx0x00x :
b1101001 A
b0xx0x000 ?
1,
#4200
0,
#4220
b0xx0x00x ?
b0xx0x0x0 :
b1101010 A
1*
1J
1+
1G
b1101010 K
b1101010 P
1,
#4240
0,
#4260
b1101011 P
b1101011 K
1+
1G
1*
1J
b0xx0x0xx :
b1101011 A
b0xx0x0x0 ?
1,
#4280
0,
#4300
b0xx0x0xx ?
b0xx0xx00 :
b1101100 A
1*
1J
1+
1G
b1101100 K
b1101100 P
1,
#4320
0,
#4340
b1101101 P
b1101101 K
1+
1G
1*
1J
b0xx0xx0x :
b1101101 A
b0xx0xx00 ?
1,
#4360
0,
#4380
b0xx0xx0x ?
b0xx0xxx0 :
b1101110 A
1*
1J
1+
1G
b1101110 K
b1101110 P
1,
#4400
0,
#4420
b1101111 P
b1101111 K
1+
1G
1*
1J
b0xx0xxxx :
b1101111 A
b0xx0xxx0 ?
1,
#4440
0,
#4460
b0xx0xxxx ?
b0xxx0000 :
b1110000 A
1*
1J
1+
1G
b1110000 K
b1110000 P
1,
#4480
0,
#4500
b1110001 P
b1110001 K
1+
1G
1*
1J
b0xxx000x :
b1110001 A
b0xxx0000 ?
1,
#4520
0,
#4540
b0xxx000x ?
b0xxx00x0 :
b1110010 A
1*
1J
1+
1G
b1110010 K
b1110010 P
1,
#4560
0,
#4580
b1110011 P
b1110011 K
1+
1G
1*
1J
b0xxx00xx :
b1110011 A
b0xxx00x0 ?
1,
#4600
0,
#4620
b0xxx00xx ?
b0xxx0x00 :
b1110100 A
1*
1J
1+
1G
b1110100 K
b1110100 P
1,
#4640
0,
#4660
b1110101 P
b1110101 K
1+
1G
1*
1J
b0xxx0x0x :
b1110101 A
b0xxx0x00 ?
1,
#4680
0,
#4700
b0xxx0x0x ?
b0xxx0xx0 :
b1110110 A
1*
1J
1+
1G
b1110110 K
b1110110 P
1,
#4720
0,
#4740
b1110111 P
b1110111 K
1+
1G
1*
1J
b0xxx0xxx :
b1110111 A
b0xxx0xx0 ?
1,
#4760
0,
#4780
b0xxx0xxx ?
b0xxxx000 :
b1111000 A
1*
1J
1+
1G
b1111000 K
b1111000 P
1,
#4800
0,
#4820
b1111001 P
b1111001 K
1+
1G
1*
1J
b0xxxx00x :
b1111001 A
b0xxxx000 ?
1,
#4840
0,
#4860
b0xxxx00x ?
b0xxxx0x0 :
b1111010 A
1*
1J
1+
1G
b1111010 K
b1111010 P
1,
#4880
0,
#4900
b1111011 P
b1111011 K
1+
1G
1*
1J
b0xxxx0xx :
b1111011 A
b0xxxx0x0 ?
1,
#4920
0,
#4940
b0xxxx0xx ?
b0xxxxx00 :
b1111100 A
1*
1J
1+
1G
b1111100 K
b1111100 P
1,
#4960
0,
#4980
b1111101 P
b1111101 K
1+
1G
1*
1J
b0xxxxx0x :
b1111101 A
b0xxxxx00 ?
1,
#5000
0,
#5020
b0xxxxx0x ?
b0xxxxxx0 :
b1111110 A
1*
1J
1+
1G
b1111110 K
b1111110 P
1,
#5040
0,
#5060
b1111111 P
b1111111 K
1+
1G
1*
1J
b0xxxxxxx :
b1111111 A
b0xxxxxx0 ?
1,
#5080
0,
#5100
b0xxxxxxx ?
b0x0000000 :
b10000000 A
1*
1J
1+
1G
b10000000 K
b10000000 P
1,
#5120
0,
#5140
b10000001 P
b10000001 K
1+
1G
1*
1J
b0x000000x :
b10000001 A
b0x0000000 ?
1,
#5160
0,
#5180
b0x000000x ?
b0x00000x0 :
b10000010 A
1*
1J
1+
1G
b10000010 K
b10000010 P
1,
#5200
0,
#5220
b10000011 P
b10000011 K
1+
1G
1*
1J
b0x00000xx :
b10000011 A
b0x00000x0 ?
1,
#5240
0,
#5260
b0x00000xx ?
b0x0000x00 :
b10000100 A
1*
1J
1+
1G
b10000100 K
b10000100 P
1,
#5280
0,
#5300
b10000101 P
b10000101 K
1+
1G
1*
1J
b0x0000x0x :
b10000101 A
b0x0000x00 ?
1,
#5320
0,
#5340
b0x0000x0x ?
b0x0000xx0 :
b10000110 A
1*
1J
1+
1G
b10000110 K
b10000110 P
1,
#5360
0,
#5380
b10000111 P
b10000111 K
1+
1G
1*
1J
b0x0000xxx :
b10000111 A
b0x0000xx0 ?
1,
#5400
0,
#5420
b0x0000xxx ?
b0x000x000 :
b10001000 A
1*
1J
1+
1G
b10001000 K
b10001000 P
1,
#5440
0,
#5460
b10001001 P
b10001001 K
1+
1G
1*
1J
b0x000x00x :
b10001001 A
b0x000x000 ?
1,
#5480
0,
