VGA/Sync_Porch.v
//This module alters the Sync_pulse signal to include the front & back porch

//Whole area -> 800x525, Visible area -> 640x480
//Hsync -> front: 18, back: 50, pulse: 92
//Vsync -> front: 10, back: 33, pulse: 2


module Sync_Porch(
  input CLK,
  input i_H_Sync,
  input i_V_Sync,
  output reg o_H_Sync = 1'b1, 
  output reg o_V_Sync = 1'b1);
  
  reg r_H_Sync = 1'b1;
  reg [4:0] r_HCountBP = 0;
  reg [6:0] r_HCountPulse = 0;
  
  reg r_V_Sync = 1'b1;
  reg [4:0] r_VCountBP = 0;
  reg [6:0] r_VCountPulse = 0;
  
  always @(posedge CLK)
  begin
    if (i_H_Sync == 0 && r_HCountBP !== 17) //falling edge
      r_HCountBP <= r_HCountBP + 1;
    else
      r_H_Sync <= 0;
      
    if (r_HCountBP == 17 && r_HCountPulse !== 92)
      r_HCountPulse <= r_HCountPulse + 1;
    else
      r_H_Sync <= 1;
      
    if (i_H_Sync == 1) 
      begin
      r_HCountBP <= 0;
      r_HCountPulse <= 0; 
      end
  end
  
  
  always @(posedge CLK)
  begin
    if (i_V_Sync == 0 && r_VCountBP !== 9) //falling edge
      r_VCountBP <= r_VCountBP + 1;
    else
      r_V_Sync <= 0;
      
    if (r_VCountBP == 9 && r_VCountPulse !== 2)
      r_VCountPulse <= r_VCountPulse + 1;
    else
      r_V_Sync <= 1;
      
    if (i_V_Sync == 1) 
      begin
      r_VCountBP <= 0;
      r_VCountPulse <= 0; 
      end
   end
   
  assign o_H_Sync = r_H_Sync;
  assign o_V_Sync = r_V_Sync;
  
endmodule

VGA/Pattern_Generator.v
module Pattern_Generator(
input CLK,
input i_SW1, i_SW2, i_SW3, i_SW4,
input i_HSync,
input i_VSync,
output reg o_HSync = 0,
output reg o_VSync = 0,
output reg [2:0] Red = 0,
output reg [2:0] Green = 0,
output reg [2:0] Blue = 0
);

always @(posedge CLK)
begin
  o_HSync <= i_Hsync;
  o_VSync <= i_VSync;
  if (i_SW1) begin //!,1,A,Q,a,q
    Red <= (i_HSync && i_VSync) ? 3'b111 : 0;
    Green <= 0;
    Blue <= 0; end
  else if (i_SW2) begin //",2,B,R,b,r
    Red <= 0;
    Green <= (i_HSync && i_VSync) ? 3'b111 : 0;
    Blue <= 0; end
  else if (i_SW3) begin //#,3...
    Red <= 0;
    Green <= 0;
    Blue <= (i_HSync && i_VSync) ? 3'b111 : 0; end
  else if (i_SW4) begin //anything else makes screen Black
    Red <= 0; 
    Green <= 0;
    Blue <= 0; end
end

endmodule

VGA/Sync_Pulse.v
module Sync_Pulse( //IMPROVE: add parameters
input CLK,
output o_HSync, o_VSync,
output reg [9:0] o_CountCol = 0,
output reg [9:0] o_CountRow = 0
);

always @(posedge CLK)
  begin
  if (o_CountCol < 799) //target-1
    o_CountCol <= o_CountCol + 1;
  else 
    begin
    o_CountCol <= 0;
    if (o_CountRow < 524) 
      o_CountRow <= o_CountRow + 1; 
    else
      o_CountRow <= 0;
    end
end

assign o_HSync = (o_CountCol < 640) ? 1'b1 : 1'b0;
assign o_VSync = (o_CountRow < 480) ? 1'b1 : 1'b0;

endmodule

// 800 Col by 525 Row
// 640 Col Active, 160 Col H-Sync
// 480 Row Active, 45 Row V-Sync

// 25 Mhz Clock / (800 by 525) Area = 60 Hz refresh rate (60 clock cycles per pixel per second)

Seven_Seg_Counter/Debounce_Switch.v
module Debounce_Switch(
	input CLK,
	input Switch,
	output o_Switch);
	
parameter c_DEBOUNCE_LIMIT = 250000;// 10 ms at 25 MHz

reg r_State = 1'b0;
reg [17:0] r_Count = 0;

always @(posedge CLK) begin// COUNTER LOGIC
	if (Switch !== r_State && r_Count < c_DEBOUNCE_LIMIT)
		r_Count <= r_Count + 1;
	else if (r_Count == c_DEBOUNCE_LIMIT) begin
		r_Count <= 0;
		r_State <= Switch;end
	else
		r_Count <= 0;
	end

assign o_Switch = r_State;

endmodule

VGA/top_VGA.v
//TODO: 
// add parameters
// change variable names
// improve Sync_Pulse and Sync_Porch logic like using '?:' in assign statements
// use case for Pattern Gen
// implement RX and TX, keyboard input, and display
// figure out VGA display and UART on windows
 
module top_VGA(
input CLK,
input SW1, SW2, SW3, SW4,
output VGA_HS, VGA_VS, 
output VGA_R0, VGA_R1, VGA_R2,
output VGA_G0, VGA_G1, VGA_G2, 
output VGA_B0, VGA_B1, VGA_B2
);

wire w_SW1, w_SW2, w_SW3, w_SW4;
wire w_HSync, w_VSync, w_HSync_PG, w_VSync_PG, w_HSync_Porch, w_VSync_Porch;
wire [9:0] w_CountCol, w_CountRow;
wire [2:0] w_Red;
wire [2:0] w_Green;
wire [2:0] w_Blue;

Debounce_Switch debounceInst1
  (.CLK(CLK),
   .Switch(SW1),
   .o_Switch(w_SW1));
Debounce_Switch debounceInst2
  (.CLK(CLK),
   .Switch(SW2),
   .o_Switch(w_SW2));
Debounce_Switch debounceInst3
  (.CLK(CLK),
   .Switch(SW3),
   .o_Switch(w_SW3));
Debounce_Switch debounceInst4
  (.CLK(CLK),
   .Switch(SW4),
   .o_Switch(w_SW4));
   
Sync_Pulse PulseInst
 (.CLK(CLK),
  .o_HSync(w_HSync),
  .o_VSync(w_VSync),
  .o_CountCol(w_CountCol),
  .o_CountRow(w_CountRow)
  );

Pattern_Generator Pattern_GenInst
 (.CLK(CLK),
  .i_SW1(SW1), 
  .i_SW2(SW2), 
  .i_SW3(SW3), 
  .i_SW4(SW4),
  .i_HSync(w_HSync),
  .i_VSync(w_VSync),
  .o_HSync(w_HSync_PG),
  .o_VSync(w_VSync_PG),
  .Red(w_Red), 
  .Green(w_Green),
  .Blue(w_Blue)
  );

Sync_Porch PorchInst
 (.CLK(CLK),
  .i_H_Sync(w_HSync_PG),
  .i_V_Sync(w_VSync_PG),
  .o_H_Sync(VGA_HS),
  .o_V_Sync(VGA_VS)
  );

//assign r_H_Sync = w_H_Sync;

//assign VGA_HS = w_HSync_Porch;
//assign VGA_VS = w_VSync_Porch;

assign VGA_R0 = w_Red[0];
assign VGA_R1 = w_Red[1];
assign VGA_R2 = w_Red[2];

assign VGA_G0 = w_Green[0];
assign VGA_G1 = w_Green[1];
assign VGA_G2 = w_Green[2];

assign VGA_B0 = w_Blue[0];
assign VGA_B1 = w_Blue[1];
assign VGA_B2 = w_Blue[2];

endmodule;

VGA/Sync_Pulse_tb.v
//RUN TB: iverilog -o simulation_tb Sync_Pulse.v Sync_Pulse_tb.v
//	  vvp simulation_tb


`timescale 1ns/1ns
module Sync_Pulse_tb();
  
  reg r_Clock = 0;
  wire H_Sync, V_Sync, r0,r1,r2,g0,g1,g2,b0,b1,b2;
  
 top_VGA inst
  (.CLK(r_Clock),
   .SW1(1'b1),
   .SW2(1'b0),
   .SW3(1'b0),
   .SW4(1'b0),
   .VGA_HS(H_Sync),
   .VGA_VS(V_Sync),
   .VGA_R0(r0),
   .VGA_R1(r1),
   .VGA_R2(r2),
   .VGA_G0(g0),
   .VGA_G1(g1),
   .VGA_G2(g2),
   .VGA_B0(b0),
   .VGA_B1(b1),
   .VGA_B2(b2)
   );
  
  always #(20)
    r_Clock <= ~r_Clock;

  always @(posedge r_Clock)
    begin
    end
  
  initial
    begin
    $dumpfile("dump.vcd");
    $dumpvars(0);
    
    #500000
    $finish;
    end
  
endmodule

VGA/dump.vcd
$date
	Thu Jul 18 16:11:18 2024
$end
$version
	Icarus Verilog
$end
$timescale
	1ns
$end
$scope module Sync_Pulse_tb $end
$var wire 1 ! r2 $end
$var wire 1 " r1 $end
$var wire 1 # r0 $end
$var wire 1 $ g2 $end
$var wire 1 % g1 $end
$var wire 1 & g0 $end
$var wire 1 ' b2 $end
$var wire 1 ( b1 $end
$var wire 1 ) b0 $end
$var wire 1 * V_Sync $end
$var wire 1 + H_Sync $end
$var reg 1 , r_Clock $end
$scope module inst $end
$var wire 1 , CLK $end
$var wire 1 - SW1 $end
$var wire 1 . SW2 $end
$var wire 1 / SW3 $end
$var wire 1 0 SW4 $end
$var wire 1 1 w_HSync_PG $end
$var wire 1 2 w_VSync_PG $end
$var wire 1 3 w_VSync $end
$var wire 1 4 w_SW4 $end
$var wire 1 5 w_SW3 $end
$var wire 1 6 w_SW2 $end
$var wire 1 7 w_SW1 $end
$var wire 3 8 w_Red [2:0] $end
$var wire 1 9 w_HSync $end
$var wire 3 : w_Green [2:0] $end
$var wire 10 ; w_CountRow [9:0] $end
$var wire 10 < w_CountCol [9:0] $end
$var wire 3 = w_Blue [2:0] $end
$var wire 1 * VGA_VS $end
$var wire 1 ! VGA_R2 $end
$var wire 1 " VGA_R1 $end
$var wire 1 # VGA_R0 $end
$var wire 1 + VGA_HS $end
$var wire 1 $ VGA_G2 $end
$var wire 1 % VGA_G1 $end
$var wire 1 & VGA_G0 $end
$var wire 1 ' VGA_B2 $end
$var wire 1 ( VGA_B1 $end
$var wire 1 ) VGA_B0 $end
$scope module Pattern_GenInst $end
$var wire 1 , CLK $end
$var wire 1 - i_SW1 $end
$var wire 1 . i_SW2 $end
$var wire 1 / i_SW3 $end
$var wire 1 0 i_SW4 $end
$var wire 1 1 o_HSync $end
$var wire 1 2 o_VSync $end
$var wire 1 3 i_VSync $end
$var wire 1 9 i_HSync $end
$var reg 3 > Blue [2:0] $end
$var reg 3 ? Green [2:0] $end
$var reg 3 @ Red [2:0] $end
$upscope $end
$scope module PorchInst $end
$var wire 1 , CLK $end
$var wire 1 1 i_H_Sync $end
$var wire 1 2 i_V_Sync $end
$var reg 1 + o_H_Sync $end
$var reg 1 * o_V_Sync $end
$var reg 5 A r_HCountBP [4:0] $end
$var reg 7 B r_HCountPulse [6:0] $end
$var reg 1 C r_H_Sync $end
$var reg 5 D r_VCountBP [4:0] $end
$var reg 7 E r_VCountPulse [6:0] $end
$var reg 1 F r_V_Sync $end
$upscope $end
$scope module PulseInst $end
$var wire 1 , CLK $end
$var wire 1 3 o_VSync $end
$var wire 1 9 o_HSync $end
$var reg 10 G o_CountCol [9:0] $end
$var reg 10 H o_CountRow [9:0] $end
$upscope $end
$scope module debounceInst1 $end
$var wire 1 , CLK $end
$var wire 1 - Switch $end
$var wire 1 7 o_Switch $end
$var parameter 32 I c_DEBOUNCE_LIMIT $end
$var reg 18 J r_Count [17:0] $end
$var reg 1 K r_State $end
$upscope $end
$scope module debounceInst2 $end
$var wire 1 , CLK $end
$var wire 1 . Switch $end
$var wire 1 6 o_Switch $end
$var parameter 32 L c_DEBOUNCE_LIMIT $end
$var reg 18 M r_Count [17:0] $end
$var reg 1 N r_State $end
$upscope $end
$scope module debounceInst3 $end
$var wire 1 , CLK $end
$var wire 1 / Switch $end
$var wire 1 5 o_Switch $end
$var parameter 32 O c_DEBOUNCE_LIMIT $end
$var reg 18 P r_Count [17:0] $end
$var reg 1 Q r_State $end
$upscope $end
$scope module debounceInst4 $end
$var wire 1 , CLK $end
$var wire 1 0 Switch $end
$var wire 1 4 o_Switch $end
$var parameter 32 R c_DEBOUNCE_LIMIT $end
$var reg 18 S r_Count [17:0] $end
$var reg 1 T r_State $end
$upscope $end
$upscope $end
$upscope $end
$enddefinitions $end
$comment Show the parameter values. $end
$dumpall
b111101000010010000 R
b111101000010010000 O
b111101000010010000 L
b111101000010010000 I
$end
#0
$dumpvars
0T
b0 S
0Q
b0 P
0N
b0 M
0K
b0 J
b0 H
b0 G
1F
b0 E
b0 D
1C
b0 B
b0 A
b0 @
b0 ?
b0 >
b0 =
b0 <
b0 ;
b0 :
19
b0 8
07
06
05
04
13
z2
z1
00
0/
0.
1-
0,
1+
1*
0)
0(
0'
0&
0%
0$
0#
0"
0!
$end
#20
1!
1"
1#
b1 J
b1 <
b1 G
b111 8
b111 @
1+
1C
1*
1F
1,
#40
0,
#60
1*
1F
1+
1C
b10 <
b10 G
b10 J
1,
#80
0,
#100
b11 J
b11 <
b11 G
1+
1C
1*
1F
1,
#120
0,
#140
1*
1F
1+
1C
b100 <
b100 G
b100 J
1,
#160
0,
#180
b101 J
b101 <
b101 G
1+
1C
1*
1F
1,
#200
0,
#220
1*
1F
1+
1C
b110 <
b110 G
b110 J
1,
#240
0,
#260
b111 J
b111 <
b111 G
1+
1C
1*
1F
1,
#280
0,
#300
1*
1F
1+
1C
b1000 <
b1000 G
b1000 J
1,
#320
0,
#340
b1001 J
b1001 <
b1001 G
1+
1C
1*
1F
1,
#360
0,
#380
1*
1F
1+
1C
b1010 <
b1010 G
b1010 J
1,
#400
0,
#420
b1011 J
b1011 <
b1011 G
1+
1C
1*
1F
1,
#440
0,
#460
1*
1F
1+
1C
b1100 <
b1100 G
b1100 J
1,
#480
0,
#500
b1101 J
b1101 <
b1101 G
1+
1C
1*
1F
1,
#520
0,
#540
1*
1F
1+
1C
b1110 <
b1110 G
b1110 J
1,
#560
0,
#580
b1111 J
b1111 <
b1111 G
1+
1C
1*
1F
1,
#600
0,
#620
1*
1F
1+
1C
b10000 <
b10000 G
b10000 J
1,
#640
0,
#660
b10001 J
b10001 <
b10001 G
1+
1C
1*
1F
1,
#680
0,
#700
1*
1F
1+
1C
b10010 <
b10010 G
b10010 J
1,
#720
0,
#740
b10011 J
b10011 <
b10011 G
1+
1C
1*
1F
1,
#760
0,
#780
1*
1F
1+
1C
b10100 <
b10100 G
b10100 J
1,
#800
0,
#820
b10101 J
b10101 <
b10101 G
1+
1C
1*
1F
1,
#840
0,
#860
1*
1F
1+
1C
b10110 <
b10110 G
b10110 J
1,
#880
0,
#900
b10111 J
b10111 <
b10111 G
1+
1C
1*
1F
1,
#920
0,
#940
1*
1F
1+
1C
b11000 <
b11000 G
b11000 J
1,
#960
0,
#980
b11001 J
b11001 <
b11001 G
1+
1C
1*
1F
1,
#1000
0,
#1020
1*
1F
1+
1C
b11010 <
b11010 G
b11010 J
1,
#1040
0,
#1060
b11011 J
b11011 <
b11011 G
1+
1C
1*
1F
1,
#1080
0,
#1100
1*
1F
1+
1C
b11100 <
b11100 G
b11100 J
1,
#1120
0,
#1140
b11101 J
b11101 <
b11101 G
1+
1C
1*
1F
1,
#1160
0,
#1180
1*
1F
1+
1C
b11110 <
b11110 G
b11110 J
1,
#1200
0,
#1220
b11111 J
b11111 <
b11111 G
1+
1C
1*
1F
1,
#1240
0,
#1260
1*
1F
1+
1C
b100000 <
b100000 G
b100000 J
1,
#1280
0,
#1300
b100001 J
b100001 <
b100001 G
1+
1C
1*
1F
1,
#1320
0,
#1340
1*
1F
1+
1C
b100010 <
b100010 G
b100010 J
1,
#1360
0,
#1380
b100011 J
b100011 <
b100011 G
1+
1C
1*
1F
1,
#1400
0,
#1420
1*
1F
1+
1C
b100100 <
b100100 G
b100100 J
1,
#1440
0,
#1460
b100101 J
b100101 <
b100101 G
1+
1C
1*
1F
1,
#1480
0,
#1500
1*
1F
1+
1C
b100110 <
b100110 G
b100110 J
1,
#1520
0,
#1540
b100111 J
b100111 <
b100111 G
1+
1C
1*
1F
1,
#1560
0,
#1580
1*
1F
1+
1C
b101000 <
b101000 G
b101000 J
1,
#1600
0,
#1620
b101001 J
b101001 <
b101001 G
1+
1C
1*
1F
1,
#1640
0,
#1660
1*
1F
1+
1C
b101010 <
b101010 G
b101010 J
1,
#1680
0,
#1700
b101011 J
b101011 <
b101011 G
1+
1C
1*
1F
1,
#1720
0,
#1740
1*
1F
1+
1C
b101100 <
b101100 G
b101100 J
1,
#1760
0,
#1780
b101101 J
b101101 <
b101101 G
1+
1C
1*
1F
1,
#1800
0,
#1820
1*
1F
1+
1C
b101110 <
b101110 G
b101110 J
1,
#1840
0,
#1860
b101111 J
b101111 <
b101111 G
1+
1C
1*
1F
1,
#1880
0,
#1900
1*
1F
1+
1C
b110000 <
b110000 G
b110000 J
1,
#1920
0,
#1940
b110001 J
b110001 <
b110001 G
1+
1C
1*
1F
1,
#1960
0,
#1980
1*
1F
1+
1C
b110010 <
b110010 G
b110010 J
1,
#2000
0,
#2020
b110011 J
b110011 <
b110011 G
1+
1C
1*
1F
1,
#2040
0,
#2060
1*
1F
1+
1C
b110100 <
b110100 G
b110100 J
1,
#2080
0,
#2100
b110101 J
b110101 <
b110101 G
1+
1C
1*
1F
1,
#2120
0,
#2140
1*
1F
1+
1C
b110110 <
b110110 G
b110110 J
1,
#2160
0,
#2180
b110111 J
b110111 <
b110111 G
1+
1C
1*
1F
1,
#2200
0,
#2220
1*
1F
1+
1C
b111000 <
b111000 G
b111000 J
1,
#2240
0,
#2260
b111001 J
b111001 <
b111001 G
1+
1C
1*
1F
1,
#2280
0,
#2300
1*
1F
1+
1C
b111010 <
b111010 G
b111010 J
1,
#2320
0,
#2340
b111011 J
b111011 <
b111011 G
1+
1C
1*
1F
1,
#2360
0,
#2380
1*
1F
1+
1C
b111100 <
b111100 G
b111100 J
1,
#2400
0,
#2420
b111101 J
b111101 <
b111101 G
1+
1C
1*
1F
1,
#2440
0,
#2460
1*
1F
1+
1C
b111110 <
b111110 G
b111110 J
1,
#2480
0,
#2500
b111111 J
b111111 <
b111111 G
1+
1C
1*
1F
1,
#2520
0,
#2540
1*
1F
1+
1C
b1000000 <
b1000000 G
b1000000 J
1,
#2560
0,
#2580
b1000001 J
b1000001 <
b1000001 G
1+
1C
1*
1F
1,
#2600
0,
#2620
1*
1F
1+
1C
b1000010 <
b1000010 G
b1000010 J
1,
#2640
0,
#2660
b1000011 J
b1000011 <
b1000011 G
1+
1C
1*
1F
1,
#2680
0,
#2700
1*
1F
1+
1C
b1000100 <
b1000100 G
b1000100 J
1,
#2720
0,
#2740
b1000101 J
b1000101 <
b1000101 G
1+
1C
1*
1F
1,
#2760
0,
#2780
1*
1F
1+
1C
b1000110 <
b1000110 G
b1000110 J
1,
#2800
0,
#2820
b1000111 J
b1000111 <
b1000111 G
1+
1C
1*
1F
1,
#2840
0,
#2860
1*
1F
1+
1C
b1001000 <
b1001000 G
b1001000 J
1,
#2880
0,
#2900
b1001001 J
b1001001 <
b1001001 G
1+
1C
1*
1F
1,
#2920
0,
#2940
1*
1F
1+
1C
b1001010 <
b1001010 G
b1001010 J
1,
#2960
0,
#2980
b1001011 J
b1001011 <
b1001011 G
1+
1C
1*
1F
1,
#3000
0,
#3020
1*
1F
1+
1C
b1001100 <
b1001100 G
b1001100 J
1,
#3040
0,
#3060
b1001101 J
b1001101 <
b1001101 G
1+
1C
1*
1F
1,
#3080
0,
#3100
1*
1F
1+
1C
b1001110 <
b1001110 G
b1001110 J
1,
#3120
0,
#3140
b1001111 J
b1001111 <
b1001111 G
1+
1C
1*
1F
1,
#3160
0,
#3180
1*
1F
1+
1C
b1010000 <
b1010000 G
b1010000 J
1,
#3200
0,
#3220
b1010001 J
b1010001 <
b1010001 G
1+
1C
1*
1F
1,
#3240
0,
#3260
1*
1F
1+
1C
b1010010 <
b1010010 G
b1010010 J
1,
#3280
0,
#3300
b1010011 J
b1010011 <
b1010011 G
1+
1C
1*
1F
1,
#3320
0,
#3340
1*
1F
1+
1C
b1010100 <
b1010100 G
b1010100 J
1,
#3360
0,
#3380
b1010101 J
b1010101 <
b1010101 G
1+
1C
1*
1F
1,
#3400
0,
#3420
1*
1F
1+
1C
b1010110 <
b1010110 G
b1010110 J
1,
#3440
0,
#3460
b1010111 J
b1010111 <
b1010111 G
1+
1C
1*
1F
1,
#3480
0,
#3500
1*
1F
1+
1C
b1011000 <
b1011000 G
b1011000 J
1,
#3520
0,
#3540
b1011001 J
b1011001 <
b1011001 G
1+
1C
1*
1F
1,
#3560
0,
#3580
1*
1F
1+
1C
b1011010 <
b1011010 G
b1011010 J
1,
#3600
0,
#3620
b1011011 J
b1011011 <
b1011011 G
1+
1C
1*
1F
1,
#3640
0,
#3660
1*
1F
1+
1C
b1011100 <
b1011100 G
b1011100 J
1,
#3680
0,
#3700
b1011101 J
b1011101 <
b1011101 G
1+
1C
1*
1F
1,
#3720
0,
#3740
1*
1F
1+
1C
b1011110 <
b1011110 G
b1011110 J
1,
#3760
0,
#3780
b1011111 J
b1011111 <
b1011111 G
1+
1C
1*
1F
1,
#3800
0,
#3820
1*
1F
1+
1C
b1100000 <
b1100000 G
b1100000 J
1,
#3840
0,
#3860
b1100001 J
b1100001 <
b1100001 G
1+
1C
1*
1F
1,
#3880
0,
#3900
1*
1F
1+
1C
b1100010 <
b1100010 G
b1100010 J
1,
#3920
0,
#3940
b1100011 J
b1100011 <
b1100011 G
1+
1C
1*
1F
1,
#3960
0,
#3980
1*
1F
1+
1C
b1100100 <
b1100100 G
b1100100 J
1,
#4000
0,
#4020
b1100101 J
b1100101 <
b1100101 G
1+
1C
1*
1F
1,
#4040
0,
#4060
1*
1F
1+
1C
b1100110 <
b1100110 G
b1100110 J
1,
#4080
0,
#4100
b1100111 J
b1100111 <
b1100111 G
1+
1C
1*
1F
1,
#4120
0,
#4140
1*
1F
1+
1C
b1101000 <
b1101000 G
b1101000 J
1,
#4160
0,
#4180
b1101001 J
b1101001 <
b1101001 G
1+
1C
1*
1F
1,
#4200
0,
#4220
1*
1F
1+
1C
b1101010 <
b1101010 G
b1101010 J
1,
#4240
0,
#4260
b1101011 J
b1101011 <
b1101011 G
1+
1C
1*
1F
1,
#4280
0,
#4300
1*
1F
1+
1C
b1101100 <
b1101100 G
b1101100 J
1,
#4320
0,
#4340
b1101101 J
b1101101 <
b1101101 G
1+
1C
1*
1F
1,
#4360
0,
#4380
1*
1F
1+
1C
b1101110 <
b1101110 G
b1101110 J
1,
#4400
0,
#4420
b1101111 J
b1101111 <
b1101111 G
1+
1C
1*
1F
1,
#4440
0,
#4460
1*
1F
1+
1C
b1110000 <
b1110000 G
b1110000 J
1,
#4480
0,
#4500
b1110001 J
b1110001 <
b1110001 G
1+
1C
1*
1F
1,
#4520
0,
#4540
1*
1F
1+
1C
b1110010 <
b1110010 G
b1110010 J
1,
#4560
0,
#4580
b1110011 J
b1110011 <
b1110011 G
1+
1C
1*
1F
1,
#4600
0,
#4620
1*
1F
1+
1C
b1110100 <
b1110100 G
b1110100 J
1,
#4640
0,
#4660
b1110101 J
b1110101 <
b1110101 G
1+
1C
1*
1F
1,
#4680
0,
#4700
1*
1F
1+
1C
b1110110 <
b1110110 G
b1110110 J
1,
#4720
0,
#4740
b1110111 J
b1110111 <
b1110111 G
1+
1C
1*
1F
1,
#4760
0,
#4780
1*
1F
1+
1C
b1111000 <
b1111000 G
b1111000 J
1,
#4800
0,
#4820
b1111001 J
b1111001 <
b1111001 G
1+
1C
1*
1F
1,
#4840
0,
#4860
1*
1F
1+
1C
b1111010 <
b1111010 G
b1111010 J
1,
#4880
0,
#4900
b1111011 J
b1111011 <
b1111011 G
1+
1C
1*
1F
1,
#4920
0,
#4940
1*
1F
1+
1C
b1111100 <
b1111100 G
b1111100 J
1,
#4960
0,
#4980
b1111101 J
b1111101 <
b1111101 G
1+
1C
1*
1F
1,
#5000
0,
#5020
1*
1F
1+
1C
b1111110 <
b1111110 G
b1111110 J
1,
#5040
0,
#5060
b1111111 J
b1111111 <
b1111111 G
1+
1C
1*
1F
1,
#5080
0,
#5100
1*
1F
1+
1C
b10000000 <
b10000000 G
b10000000 J
1,
#5120
0,
#5140
b10000001 J
b10000001 <
b10000001 G
1+
1C
1*
1F
1,
#5160
0,
#5180
1*
1F
1+
1C
b10000010 <
b10000010 G
b10000010 J
1,
#5200
0,
#5220
b10000011 J
b10000011 <
b10000011 G
1+
1C
1*
1F
1,
#5240
0,
#5260
1*
1F
1+
1C
b10000100 <
b10000100 G
b10000100 J
1,
#5280
0,
#5300
b10000101 J
b10000101 <
b10000101 G
1+
1C
1*
1F
1,
#5320
0,
#5340
1*
1F
1+
1C
b10000110 <
b10000110 G
b10000110 J
1,
#5360
0,
#5380
b10000111 J
b10000111 <
b10000111 G
1+
1C
1*
1F
1,
#5400
0,
#5420
1*
1F
1+
1C
b10001000 <
b10001000 G
b10001000 J
1,
#5440
0,
#5460
b10001001 J
b10001001 <
b10001001 G
1+
1C
1*
1F
1,
#5480
0,
#5500
1*
1F
1+
1C
b10001010 <
b10001010 G
b10001010 J
1,
#5520
0,
#5540
b10001011 J
b10001011 <
b10001011 G
1+
1C
1*
1F
1,
#5560
0,
#5580
1*
1F
1+
1C
b10001100 <
b10001100 G
b10001100 J
1,
#5600
0,
#5620
b10001101 J
b10001101 <
b10001101 G
1+
1C
1*
1F
1,
#5640
0,
#5660
1*
1F
1+
1C
b10001110 <
b10001110 G
b10001110 J
1,
#5680
0,
#5700
b10001111 J
b10001111 <
b10001111 G
1+
1C
1*
1F
1,
#5720
0,
#5740
1*
1F
1+
1C
b10010000 <
b10010000 G
b10010000 J
1,
#5760
0,
#5780
b10010001 J
b10010001 <
b10010001 G
1+
1C
1*
1F
1,
#5800
0,
#5820
1*
1F
1+
1C
b10010010 <
b10010010 G
b10010010 J
1,
#5840
0,
#5860
b10010011 J
b10010011 <
b10010011 G
1+
1C
1*
1F
1,
#5880
0,
#5900
1*
1F
1+
1C
b10010100 <
b10010100 G
b10010100 J
1,
#5920
0,
#5940
b10010101 J
b10010101 <
b10010101 G
1+
1C
1*
1F
1,
#5960
0,
#5980
1*
1F
1+
1C
b10010110 <
b10010110 G
b10010110 J
1,
#6000
0,
#6020
b10010111 J
b10010111 <
b10010111 G
1+
1C
1*
1F
1,
#6040
0,
#6060
1*
1F
1+
1C
b10011000 <
b10011000 G
b10011000 J
1,
#6080
0,
#6100
b10011001 J
b10011001 <
b10011001 G
1+
1C
1*
1F
1,
#6120
0,
#6140
1*
1F
1+
1C
b10011010 <
b10011010 G
b10011010 J
1,
#6160
0,
#6180
b10011011 J
b10011011 <
b10011011 G
1+
1C
1*
1F
1,
#6200
0,
#6220
1*
1F
1+
1C
b10011100 <
b10011100 G
b10011100 J
1,
#6240
0,
#6260
b10011101 J
b10011101 <
b10011101 G
1+
1C
1*
1F
1,
#6280
0,
#6300
1*
1F
1+
1C
b10011110 <
b10011110 G
b10011110 J
1,
#6320
0,
#6340
b10011111 J
b10011111 <
b10011111 G
1+
1C
1*
1F
1,
#6360
0,
#6380
1*
1F
1+
1C
b10100000 <
b10100000 G
b10100000 J
1,
#6400
0,
#6420
b10100001 J
b10100001 <
b10100001 G
1+
1C
1*
1F
1,
#6440
0,
#6460
1*
1F
1+
1C
b10100010 <
b10100010 G
b10100010 J
1,
#6480
0,
#6500
b10100011 J
b10100011 <
b10100011 G
1+
1C
1*
1F
1,
#6520
0,
#6540
1*
1F
1+
1C
b10100100 <
b10100100 G
b10100100 J
1,
#6560
0,
#6580
b10100101 J
b10100101 <
b10100101 G
1+
1C
1*
1F
1,
#6600
0,
#6620
1*
1F
1+
1C
b10100110 <
b10100110 G
b10100110 J
1,
#6640
0,
#6660
b10100111 J
b10100111 <
b10100111 G
1+
1C
1*
1F
1,
#6680
0,
#6700
1*
1F
1+
1C
b10101000 <
b10101000 G
b10101000 J
1,
#6720
0,
#6740
b10101001 J
b10101001 <
b10101001 G
1+
1C
1*
1F
1,
#6760
0,
#6780
1*
1F
1+
1C
b10101010 <
b10101010 G
b10101010 J
1,
#6800
0,
#6820
b10101011 J
b10101011 <
b10101011 G
1+
1C
1*
1F
1,
#6840
0,
#6860
1*
1F
1+
1C
b10101100 <
b10101100 G
b10101100 J
1,
#6880
0,
#6900
b10101101 J
b10101101 <
b10101101 G
1+
1C
1*
1F
1,
#6920
0,
#6940
1*
1F
1+
1C
b10101110 <
b10101110 G
b10101110 J
1,
#6960
0,
#6980
b10101111 J
b10101111 <
b10101111 G
1+
1C
1*
1F
1,
#7000
0,
#7020
1*
1F
1+
1C
b10110000 <
b10110000 G
b10110000 J
1,
#7040
0,
#7060
b10110001 J
b10110001 <
b10110001 G
1+
1C
1*
1F
1,
#7080
0,
#7100
1*
1F
1+
1C
b10110010 <
b10110010 G
b10110010 J
1,
#7120
0,
#7140
b10110011 J
b10110011 <
b10110011 G
1+
1C
1*
1F
1,
#7160
0,
#7180
1*
1F
1+
1C
b10110100 <
b10110100 G
b10110100 J
1,
#7200
0,
#7220
b10110101 J
b10110101 <
b10110101 G
1+
1C
1*
1F
1,
#7240
0,
#7260
1*
1F
1+
1C
b10110110 <
b10110110 G
b10110110 J
1,
#7280
0,
#7300
b10110111 J
b10110111 <
b10110111 G
1+
1C
1*
1F
1,
#7320
0,
#7340
1*
1F
1+
1C
b10111000 <
b10111000 G
b10111000 J
1,
#7360
0,
#7380
b10111001 J
b10111001 <
b10111001 G
1+
1C
1*
1F
1,
#7400
0,
#7420
1*
1F
1+
1C
b10111010 <
b10111010 G
b10111010 J
1,
#7440
0,
#7460
b10111011 J
b10111011 <
b10111011 G
1+
1C
1*
1F
1,
#7480
0,
#7500
1*
1F
1+
1C
b10111100 <
b10111100 G
b10111100 J
1,
#7520
0,
#7540
b10111101 J
b10111101 <
b10111101 G
1+
1C
1*
1F
1,
#7560
0,
#7580
1*
1F
1+
1C
b10111110 <
b10111110 G
b10111110 J
1,
#7600
0,
#7620
b10111111 J
b10111111 <
b10111111 G
1+
1C
1*
1F
1,
#7640
0,
#7660
1*
1F
1+
1C
b11000000 <
b11000000 G
b11000000 J
1,
#7680
0,
#7700
b11000001 J
b11000001 <
b11000001 G
1+
1C
1*
1F
1,
#7720
0,
#7740
1*
1F
1+
1C
b11000010 <
b11000010 G
b11000010 J
1,
#7760
0,
#7780
b11000011 J
b11000011 <
b11000011 G
1+
1C
1*
1F
1,
#7800
0,
#7820
1*
1F
1+
1C
b11000100 <
b11000100 G
b11000100 J
1,
#7840
0,
#7860
b11000101 J
b11000101 <
b11000101 G
1+
1C
1*
1F
1,
#7880
0,
#7900
1*
1F
1+
1C
b11000110 <
b11000110 G
b11000110 J
1,
#7920
0,
#7940
b11000111 J
b11000111 <
b11000111 G
1+
1C
1*
1F
1,
#7960
0,
#7980
1*
1F
1+
1C
b11001000 <
b11001000 G
b11001000 J
1,
#8000
0,
