VGA/Sync_Porch.v
//This module alters the Sync_pulse signal to include the front & back porch

//Whole area -> 800x525, Visible area -> 640x480
//Hsync -> front: 18, back: 50, pulse: 92
//Vsync -> front: 10, back: 33, pulse: 2


module Sync_Porch(
  input CLK,
  input i_H_Sync,
  input i_V_Sync,
  output o_H_Sync = 1'b1, 
  output o_V_Sync = 1'b1);
  
  reg r_H_Sync = 1'b1;
  reg [4:0] r_HCountBP = 0;
  reg [6:0] r_HCountPulse = 0;
  
  reg r_V_Sync = 1'b1;
  reg [4:0] r_VCountBP = 0;
  reg [6:0] r_VCountPulse = 0;
  
  always @(posedge CLK)
  begin
    if (i_H_Sync == 0 && r_HCountBP !== 17) //falling edge
      r_HCountBP <= r_HCountBP + 1;
    else
      r_H_Sync <= 0;
      
    if (r_HCountBP == 17 && r_HCountPulse !== 92)
      r_HCountPulse <= r_HCountPulse + 1;
    else
      r_H_Sync <= 1;
      
    if (i_H_Sync == 1) 
      begin
      r_HCountBP <= 0;
      r_HCountPulse <= 0; 
      end
  end
  
  
  always @(posedge CLK)
  begin
    if (i_V_Sync == 0 && r_VCountBP !== 9) //falling edge
      r_VCountBP <= r_VCountBP + 1;
    else
      r_V_Sync <= 0;
      
    if (r_VCountBP == 9 && r_VCountPulse !== 2)
      r_VCountPulse <= r_VCountPulse + 1;
    else
      r_V_Sync <= 1;
      
    if (i_V_Sync == 1) 
      begin
      r_VCountBP <= 0;
      r_VCountPulse <= 0; 
      end

    assign o_H_Sync = r_H_Sync;
    assign o_V_Sync = r_V_Sync;
  end
  
endmodule

VGA/Sync_Pulse.v
module Sync_Pulse( //IMPROVE: add parameters
input CLK,
output reg H_Sync = 1'b1,
output reg V_Sync = 1'b1,
output reg [9:0] CountCol = 0,
output reg [9:0] CountRow = 0
);

// 800 Col by 525 Row
// 640 Col Active, 160 Col H-Sync
// 480 Row Active, 45 Row V-Sync

// 25Mhz Clock / (800 by 525) Area = 60Hz refresh rate (60 clock cycles per pixel per second)

reg [9:0] r_CountCol = 0;
reg [9:0] r_CountRow = 0;

always @(posedge CLK)
begin
  if (r_CountCol < 639) begin //target-1
    H_Sync <= 1'b1;
    r_CountCol <= r_CountCol + 1; end
  else if (r_CountCol < 799) begin
    H_Sync <= 1'b0;
    r_CountCol <= r_CountCol + 1; end
  else 
  begin
    r_CountCol <= 0;
    H_Sync <= 1'b1;
    
    if (r_CountRow < 479) begin
      V_Sync <= 1'b1;
      r_CountRow <= r_CountRow + 1; end
    else if (r_CountRow < 524) begin 
      V_Sync <= 1'b0;
      r_CountRow <= r_CountRow + 1; end
    else begin
      r_CountRow <= 0;
      V_Sync <= 1'b1; end
  end
  
  CountCol <= r_CountCol;
  CountRow <= r_CountRow;
end

//IMPROVE: logic above and assignment statements using ?:

endmodule

VGA/Sync_Pulse_tb.v
//RUN TB: iverilog -o simulation_tb Sync_Pulse.v Sync_Pulse_tb.v
//	  vvp simulation_tb


`timescale 1ns/1ns
module Sync_Pulse_tb();
  
  reg r_Clock = 0;
  wire H_Sync, V_Sync, oHSync, oVSync;
  
  Sync_Pulse inst1(
    .CLK(r_Clock),
    .H_Sync(H_Sync),
    .V_Sync(V_Sync),
    .CountCol(),
    .CountRow());
    
  Sync_Porch inst2(
    .CLK(r_Clock),
    .i_H_Sync(H_Sync),
    .i_V_Sync(V_Sync),
    .o_H_Sync(oHSync),
    .o_V_Sync(oVSync));
  
  always #(20)
    r_Clock <= ~r_Clock;

  always @(posedge r_Clock)
    begin
    end
  
  initial
    begin
    $dumpfile("dump.vcd");
    $dumpvars(0);
    
    #500000
    $finish;
    end
  
endmodule

VGA/dump.vcd
$date
	Tue Jul 16 22:33:32 2024
$end
$version
	Icarus Verilog
$end
$timescale
	1ns
$end
$scope module Sync_Pulse_tb $end
$var wire 1 ! oVSync $end
$var wire 1 " oHSync $end
$var wire 1 # V_Sync $end
$var wire 1 $ H_Sync $end
$var reg 1 % r_Clock $end
$scope module inst1 $end
$var wire 1 % CLK $end
$var reg 10 & CountCol [9:0] $end
$var reg 10 ' CountRow [9:0] $end
$var reg 1 $ H_Sync $end
$var reg 1 # V_Sync $end
$var reg 10 ( r_CountCol [9:0] $end
$var reg 10 ) r_CountRow [9:0] $end
$upscope $end
$scope module inst2 $end
$var wire 1 % CLK $end
$var wire 1 $ i_H_Sync $end
$var wire 1 # i_V_Sync $end
$var reg 1 " o_H_Sync $end
$var reg 1 ! o_V_Sync $end
$var reg 5 * r_HCountBP [4:0] $end
$var reg 7 + r_HCountPulse [6:0] $end
$var reg 1 , r_H_Sync $end
$var reg 5 - r_VCountBP [4:0] $end
$var reg 7 . r_VCountPulse [6:0] $end
$var reg 1 / r_V_Sync $end
$upscope $end
$upscope $end
$enddefinitions $end
$comment Show the parameter values. $end
$dumpall
$end
#0
$dumpvars
1/
b0 .
b0 -
1,
b0 +
b0 *
b0 )
b0 (
b0 '
b0 &
0%
1$
1#
1"
1!
$end
#20
b1 (
1"
1,
1!
1/
1%
#40
0%
#60
1!
1/
1"
1,
b1 &
b10 (
1%
#80
0%
#100
b10 &
b11 (
1"
1,
1!
1/
1%
#120
0%
#140
1!
1/
1"
1,
b11 &
b100 (
1%
#160
0%
#180
b100 &
b101 (
1"
1,
1!
1/
1%
#200
0%
#220
1!
1/
1"
1,
b101 &
b110 (
1%
#240
0%
#260
b110 &
b111 (
1"
1,
1!
1/
1%
#280
0%
#300
1!
1/
1"
1,
b111 &
b1000 (
1%
#320
0%
#340
b1000 &
b1001 (
1"
1,
1!
1/
1%
#360
0%
#380
1!
1/
1"
1,
b1001 &
b1010 (
1%
#400
0%
#420
b1010 &
b1011 (
1"
1,
1!
1/
1%
#440
0%
#460
1!
1/
1"
1,
b1011 &
b1100 (
1%
#480
0%
#500
b1100 &
b1101 (
1"
1,
1!
1/
1%
#520
0%
#540
1!
1/
1"
1,
b1101 &
b1110 (
1%
#560
0%
#580
b1110 &
b1111 (
1"
1,
1!
1/
1%
#600
0%
#620
1!
1/
1"
1,
b1111 &
b10000 (
1%
#640
0%
#660
b10000 &
b10001 (
1"
1,
1!
1/
1%
#680
0%
#700
1!
1/
1"
1,
b10001 &
b10010 (
1%
#720
0%
#740
b10010 &
b10011 (
1"
1,
1!
1/
1%
#760
0%
#780
1!
1/
1"
1,
b10011 &
b10100 (
1%
#800
0%
#820
b10100 &
b10101 (
1"
1,
1!
1/
1%
#840
0%
#860
1!
1/
1"
1,
b10101 &
b10110 (
1%
#880
0%
#900
b10110 &
b10111 (
1"
1,
1!
1/
1%
#920
0%
#940
1!
1/
1"
1,
b10111 &
b11000 (
1%
#960
0%
#980
b11000 &
b11001 (
1"
1,
1!
1/
1%
#1000
0%
#1020
1!
1/
1"
1,
b11001 &
b11010 (
1%
#1040
0%
#1060
b11010 &
b11011 (
1"
1,
1!
1/
1%
#1080
0%
#1100
1!
1/
1"
1,
b11011 &
b11100 (
1%
#1120
0%
#1140
b11100 &
b11101 (
1"
1,
1!
1/
1%
#1160
0%
#1180
1!
1/
1"
1,
b11101 &
b11110 (
1%
#1200
0%
#1220
b11110 &
b11111 (
1"
1,
1!
1/
1%
#1240
0%
#1260
1!
1/
1"
1,
b11111 &
b100000 (
1%
#1280
0%
#1300
b100000 &
b100001 (
1"
1,
1!
1/
1%
#1320
0%
#1340
1!
1/
1"
1,
b100001 &
b100010 (
1%
#1360
0%
#1380
b100010 &
b100011 (
1"
1,
1!
1/
1%
#1400
0%
#1420
1!
1/
1"
1,
b100011 &
b100100 (
1%
#1440
0%
#1460
b100100 &
b100101 (
1"
1,
1!
1/
1%
#1480
0%
#1500
1!
1/
1"
1,
b100101 &
b100110 (
1%
#1520
0%
#1540
b100110 &
b100111 (
1"
1,
1!
1/
1%
#1560
0%
#1580
1!
1/
1"
1,
b100111 &
b101000 (
1%
#1600
0%
#1620
b101000 &
b101001 (
1"
1,
1!
1/
1%
#1640
0%
#1660
1!
1/
1"
1,
b101001 &
b101010 (
1%
#1680
0%
#1700
b101010 &
b101011 (
1"
1,
1!
1/
1%
#1720
0%
#1740
1!
1/
1"
1,
b101011 &
b101100 (
1%
#1760
0%
#1780
b101100 &
b101101 (
1"
1,
1!
1/
1%
#1800
0%
#1820
1!
1/
1"
1,
b101101 &
b101110 (
1%
#1840
0%
#1860
b101110 &
b101111 (
1"
1,
1!
1/
1%
#1880
0%
#1900
1!
1/
1"
1,
b101111 &
b110000 (
1%
#1920
0%
#1940
b110000 &
b110001 (
1"
1,
1!
1/
1%
#1960
0%
#1980
1!
1/
1"
1,
b110001 &
b110010 (
1%
#2000
0%
#2020
b110010 &
b110011 (
1"
1,
1!
1/
1%
#2040
0%
#2060
1!
1/
1"
1,
b110011 &
b110100 (
1%
#2080
0%
#2100
b110100 &
b110101 (
1"
1,
1!
1/
1%
#2120
0%
#2140
1!
1/
1"
1,
b110101 &
b110110 (
1%
#2160
0%
#2180
b110110 &
b110111 (
1"
1,
1!
1/
1%
#2200
0%
#2220
1!
1/
1"
1,
b110111 &
b111000 (
1%
#2240
0%
#2260
b111000 &
b111001 (
1"
1,
1!
1/
1%
#2280
0%
#2300
1!
1/
1"
1,
b111001 &
b111010 (
1%
#2320
0%
#2340
b111010 &
b111011 (
1"
1,
1!
1/
1%
#2360
0%
#2380
1!
1/
1"
1,
b111011 &
b111100 (
1%
#2400
0%
#2420
b111100 &
b111101 (
1"
1,
1!
1/
1%
#2440
0%
#2460
1!
1/
1"
1,
b111101 &
b111110 (
1%
#2480
0%
#2500
b111110 &
b111111 (
1"
1,
1!
1/
1%
#2520
0%
#2540
1!
1/
1"
1,
b111111 &
b1000000 (
1%
#2560
0%
#2580
b1000000 &
b1000001 (
1"
1,
1!
1/
1%
#2600
0%
#2620
1!
1/
1"
1,
b1000001 &
b1000010 (
1%
#2640
0%
#2660
b1000010 &
b1000011 (
1"
1,
1!
1/
1%
#2680
0%
#2700
1!
1/
1"
1,
b1000011 &
b1000100 (
1%
#2720
0%
#2740
b1000100 &
b1000101 (
1"
1,
1!
1/
1%
#2760
0%
#2780
1!
1/
1"
1,
b1000101 &
b1000110 (
1%
#2800
0%
#2820
b1000110 &
b1000111 (
1"
1,
1!
1/
1%
#2840
0%
#2860
1!
1/
1"
1,
b1000111 &
b1001000 (
1%
#2880
0%
#2900
b1001000 &
b1001001 (
1"
1,
1!
1/
1%
#2920
0%
#2940
1!
1/
1"
1,
b1001001 &
b1001010 (
1%
#2960
0%
#2980
b1001010 &
b1001011 (
1"
1,
1!
1/
1%
#3000
0%
#3020
1!
1/
1"
1,
b1001011 &
b1001100 (
1%
#3040
0%
#3060
b1001100 &
b1001101 (
1"
1,
1!
1/
1%
#3080
0%
#3100
1!
1/
1"
1,
b1001101 &
b1001110 (
1%
#3120
0%
#3140
b1001110 &
b1001111 (
1"
1,
1!
1/
1%
#3160
0%
#3180
1!
1/
1"
1,
b1001111 &
b1010000 (
1%
#3200
0%
#3220
b1010000 &
b1010001 (
1"
1,
1!
1/
1%
#3240
0%
#3260
1!
1/
1"
1,
b1010001 &
b1010010 (
1%
#3280
0%
#3300
b1010010 &
b1010011 (
1"
1,
1!
1/
1%
#3320
0%
#3340
1!
1/
1"
1,
b1010011 &
b1010100 (
1%
#3360
0%
#3380
b1010100 &
b1010101 (
1"
1,
1!
1/
1%
#3400
0%
#3420
1!
1/
1"
1,
b1010101 &
b1010110 (
1%
#3440
0%
#3460
b1010110 &
b1010111 (
1"
1,
1!
1/
1%
#3480
0%
#3500
1!
1/
1"
1,
b1010111 &
b1011000 (
1%
#3520
0%
#3540
b1011000 &
b1011001 (
1"
1,
1!
1/
1%
#3560
0%
#3580
1!
1/
1"
1,
b1011001 &
b1011010 (
1%
#3600
0%
#3620
b1011010 &
b1011011 (
1"
1,
1!
1/
1%
#3640
0%
#3660
1!
1/
1"
1,
b1011011 &
b1011100 (
1%
#3680
0%
#3700
b1011100 &
b1011101 (
1"
1,
1!
1/
1%
#3720
0%
#3740
1!
1/
1"
1,
b1011101 &
b1011110 (
1%
#3760
0%
#3780
b1011110 &
b1011111 (
1"
1,
1!
1/
1%
#3800
0%
#3820
1!
1/
1"
1,
b1011111 &
b1100000 (
1%
#3840
0%
#3860
b1100000 &
b1100001 (
1"
1,
1!
1/
1%
#3880
0%
#3900
1!
1/
1"
1,
b1100001 &
b1100010 (
1%
#3920
0%
#3940
b1100010 &
b1100011 (
1"
1,
1!
1/
1%
#3960
0%
#3980
1!
1/
1"
1,
b1100011 &
b1100100 (
1%
#4000
0%
#4020
b1100100 &
b1100101 (
1"
1,
1!
1/
1%
#4040
0%
#4060
1!
1/
1"
1,
b1100101 &
b1100110 (
1%
#4080
0%
#4100
b1100110 &
b1100111 (
1"
1,
1!
1/
1%
#4120
0%
#4140
1!
1/
1"
1,
b1100111 &
b1101000 (
1%
#4160
0%
#4180
b1101000 &
b1101001 (
1"
1,
1!
1/
1%
#4200
0%
#4220
1!
1/
1"
1,
b1101001 &
b1101010 (
1%
#4240
0%
#4260
b1101010 &
b1101011 (
1"
1,
1!
1/
1%
#4280
0%
#4300
1!
1/
1"
1,
b1101011 &
b1101100 (
1%
#4320
0%
#4340
b1101100 &
b1101101 (
1"
1,
1!
1/
1%
#4360
0%
#4380
1!
1/
1"
1,
b1101101 &
b1101110 (
1%
#4400
0%
#4420
b1101110 &
b1101111 (
1"
1,
1!
1/
1%
#4440
0%
#4460
1!
1/
1"
1,
b1101111 &
b1110000 (
1%
#4480
0%
#4500
b1110000 &
b1110001 (
1"
1,
1!
1/
1%
#4520
0%
#4540
1!
1/
1"
1,
b1110001 &
b1110010 (
1%
#4560
0%
#4580
b1110010 &
b1110011 (
1"
1,
1!
1/
1%
#4600
0%
#4620
1!
1/
1"
1,
b1110011 &
b1110100 (
1%
#4640
0%
#4660
b1110100 &
b1110101 (
1"
1,
1!
1/
1%
#4680
0%
#4700
1!
1/
1"
1,
b1110101 &
b1110110 (
1%
#4720
0%
#4740
b1110110 &
b1110111 (
1"
1,
1!
1/
1%
#4760
0%
#4780
1!
1/
1"
1,
b1110111 &
b1111000 (
1%
#4800
0%
#4820
b1111000 &
b1111001 (
1"
1,
1!
1/
1%
#4840
0%
#4860
1!
1/
1"
1,
b1111001 &
b1111010 (
1%
#4880
0%
#4900
b1111010 &
b1111011 (
1"
1,
1!
1/
1%
#4920
0%
#4940
1!
1/
1"
1,
b1111011 &
b1111100 (
1%
#4960
0%
#4980
b1111100 &
b1111101 (
1"
1,
1!
1/
1%
#5000
0%
#5020
1!
1/
1"
1,
b1111101 &
b1111110 (
1%
#5040
0%
#5060
b1111110 &
b1111111 (
1"
1,
1!
1/
1%
#5080
0%
#5100
1!
1/
1"
1,
b1111111 &
b10000000 (
1%
#5120
0%
#5140
b10000000 &
b10000001 (
1"
1,
1!
1/
1%
#5160
0%
#5180
1!
1/
1"
1,
b10000001 &
b10000010 (
1%
#5200
0%
#5220
b10000010 &
b10000011 (
1"
1,
1!
1/
1%
#5240
0%
#5260
1!
1/
1"
1,
b10000011 &
b10000100 (
1%
#5280
0%
#5300
b10000100 &
b10000101 (
1"
1,
1!
1/
1%
#5320
0%
#5340
1!
1/
1"
1,
b10000101 &
b10000110 (
1%
#5360
0%
#5380
b10000110 &
b10000111 (
1"
1,
1!
1/
1%
#5400
0%
#5420
1!
1/
1"
1,
b10000111 &
b10001000 (
1%
#5440
0%
#5460
b10001000 &
b10001001 (
1"
1,
1!
1/
1%
#5480
0%
#5500
1!
1/
1"
1,
b10001001 &
b10001010 (
1%
#5520
0%
#5540
b10001010 &
b10001011 (
1"
1,
1!
1/
1%
#5560
0%
#5580
1!
1/
1"
1,
b10001011 &
b10001100 (
1%
#5600
0%
#5620
b10001100 &
b10001101 (
1"
1,
1!
1/
1%
#5640
0%
#5660
1!
1/
1"
1,
b10001101 &
b10001110 (
1%
#5680
0%
#5700
b10001110 &
b10001111 (
1"
1,
1!
1/
1%
#5720
0%
#5740
1!
1/
1"
1,
b10001111 &
b10010000 (
1%
#5760
0%
#5780
b10010000 &
b10010001 (
1"
1,
1!
1/
1%
#5800
0%
#5820
1!
1/
1"
1,
b10010001 &
b10010010 (
1%
#5840
0%
#5860
b10010010 &
b10010011 (
1"
1,
1!
1/
1%
#5880
0%
#5900
1!
1/
1"
1,
b10010011 &
b10010100 (
1%
#5920
0%
#5940
b10010100 &
b10010101 (
1"
1,
1!
1/
1%
#5960
0%
#5980
1!
1/
1"
1,
b10010101 &
b10010110 (
1%
#6000
0%
#6020
b10010110 &
b10010111 (
1"
1,
1!
1/
1%
#6040
0%
#6060
1!
1/
1"
1,
b10010111 &
b10011000 (
1%
#6080
0%
#6100
b10011000 &
b10011001 (
1"
1,
1!
1/
1%
#6120
0%
#6140
1!
1/
1"
1,
b10011001 &
b10011010 (
1%
#6160
0%
#6180
b10011010 &
b10011011 (
1"
1,
1!
1/
1%
#6200
0%
#6220
1!
1/
1"
1,
b10011011 &
b10011100 (
1%
#6240
0%
#6260
b10011100 &
b10011101 (
1"
1,
1!
1/
1%
#6280
0%
#6300
1!
1/
1"
1,
b10011101 &
b10011110 (
1%
#6320
0%
#6340
b10011110 &
b10011111 (
1"
1,
1!
1/
1%
#6360
0%
#6380
1!
1/
1"
1,
b10011111 &
b10100000 (
1%
#6400
0%
#6420
b10100000 &
b10100001 (
1"
1,
1!
1/
1%
#6440
0%
#6460
1!
1/
1"
1,
b10100001 &
b10100010 (
1%
#6480
0%
#6500
b10100010 &
b10100011 (
1"
1,
1!
1/
1%
#6520
0%
#6540
1!
1/
1"
1,
b10100011 &
b10100100 (
1%
#6560
0%
#6580
b10100100 &
b10100101 (
1"
1,
1!
1/
1%
#6600
0%
#6620
1!
1/
1"
1,
b10100101 &
b10100110 (
1%
#6640
0%
#6660
b10100110 &
b10100111 (
1"
1,
1!
1/
1%
#6680
0%
#6700
1!
1/
1"
1,
b10100111 &
b10101000 (
1%
#6720
0%
#6740
b10101000 &
b10101001 (
1"
1,
1!
1/
1%
#6760
0%
#6780
1!
1/
1"
1,
b10101001 &
b10101010 (
1%
#6800
0%
#6820
b10101010 &
b10101011 (
1"
1,
1!
1/
1%
#6840
0%
#6860
1!
1/
1"
1,
b10101011 &
b10101100 (
1%
#6880
0%
#6900
b10101100 &
b10101101 (
1"
1,
1!
1/
1%
#6920
0%
#6940
1!
1/
1"
1,
b10101101 &
b10101110 (
1%
#6960
0%
#6980
b10101110 &
b10101111 (
1"
1,
1!
1/
1%
#7000
0%
#7020
1!
1/
1"
1,
b10101111 &
b10110000 (
1%
#7040
0%
#7060
b10110000 &
b10110001 (
1"
1,
1!
1/
1%
#7080
0%
#7100
1!
1/
1"
1,
b10110001 &
b10110010 (
1%
#7120
0%
#7140
b10110010 &
b10110011 (
1"
1,
1!
1/
1%
#7160
0%
#7180
1!
1/
1"
1,
b10110011 &
b10110100 (
1%
#7200
0%
#7220
b10110100 &
b10110101 (
1"
1,
1!
1/
1%
#7240
0%
#7260
1!
1/
1"
1,
b10110101 &
b10110110 (
1%
#7280
0%
#7300
b10110110 &
b10110111 (
1"
1,
1!
1/
1%
#7320
0%
#7340
1!
1/
1"
1,
b10110111 &
b10111000 (
1%
#7360
0%
#7380
b10111000 &
b10111001 (
1"
1,
1!
1/
1%
#7400
0%
#7420
1!
1/
1"
1,
b10111001 &
b10111010 (
1%
#7440
0%
#7460
b10111010 &
b10111011 (
1"
1,
1!
1/
1%
#7480
0%
#7500
1!
1/
1"
1,
b10111011 &
b10111100 (
1%
#7520
0%
#7540
b10111100 &
b10111101 (
1"
1,
1!
1/
1%
#7560
0%
#7580
1!
1/
1"
1,
b10111101 &
b10111110 (
1%
#7600
0%
#7620
b10111110 &
b10111111 (
1"
1,
1!
1/
1%
#7640
0%
#7660
1!
1/
1"
1,
b10111111 &
b11000000 (
1%
#7680
0%
#7700
b11000000 &
b11000001 (
1"
1,
1!
1/
1%
#7720
0%
#7740
1!
1/
1"
1,
b11000001 &
b11000010 (
1%
#7760
0%
#7780
b11000010 &
b11000011 (
1"
1,
1!
1/
1%
#7800
0%
#7820
1!
1/
1"
1,
b11000011 &
b11000100 (
1%
#7840
0%
#7860
b11000100 &
b11000101 (
1"
1,
1!
1/
1%
#7880
0%
#7900
1!
1/
1"
1,
b11000101 &
b11000110 (
1%
#7920
0%
#7940
b11000110 &
b11000111 (
1"
1,
1!
1/
1%
#7960
0%
#7980
1!
1/
1"
1,
b11000111 &
b11001000 (
1%
#8000
0%
#8020
b11001000 &
b11001001 (
1"
1,
1!
1/
1%
#8040
0%
#8060
1!
1/
1"
1,
b11001001 &
b11001010 (
1%
#8080
0%
#8100
b11001010 &
b11001011 (
1"
1,
1!
1/
1%
#8120
0%
#8140
1!
1/
1"
1,
b11001011 &
b11001100 (
1%
#8160
0%
#8180
b11001100 &
b11001101 (
1"
1,
1!
1/
1%
#8200
0%
#8220
1!
1/
1"
1,
b11001101 &
b11001110 (
1%
#8240
0%
#8260
b11001110 &
b11001111 (
1"
1,
1!
1/
1%
#8280
0%
#8300
1!
1/
1"
1,
b11001111 &
b11010000 (
1%
#8320
0%
#8340
b11010000 &
b11010001 (
1"
1,
1!
1/
1%
#8360
0%
#8380
1!
1/
1"
1,
b11010001 &
b11010010 (
1%
#8400
0%
#8420
b11010010 &
b11010011 (
1"
1,
1!
1/
1%
#8440
0%
#8460
1!
1/
1"
1,
b11010011 &
b11010100 (
1%
#8480
0%
#8500
b11010100 &
b11010101 (
1"
1,
1!
1/
1%
#8520
0%
#8540
1!
1/
1"
1,
b11010101 &
b11010110 (
1%
#8560
0%
#8580
b11010110 &
b11010111 (
1"
1,
1!
1/
1%
#8600
0%
#8620
1!
1/
1"
1,
b11010111 &
b11011000 (
1%
#8640
0%
#8660
b11011000 &
b11011001 (
1"
1,
1!
1/
1%
#8680
0%
#8700
1!
1/
1"
1,
b11011001 &
b11011010 (
1%
#8720
0%
#8740
b11011010 &
b11011011 (
1"
1,
1!
1/
1%
#8760
0%
#8780
1!
1/
1"
1,
b11011011 &
b11011100 (
1%
#8800
0%
#8820
b11011100 &
b11011101 (
1"
1,
1!
1/
1%
#8840
0%
#8860
1!
1/
1"
1,
b11011101 &
b11011110 (
1%
#8880
0%
#8900
b11011110 &
b11011111 (
1"
1,
1!
1/
1%
#8920
0%
#8940
1!
1/
1"
1,
b11011111 &
b11100000 (
1%
#8960
0%
#8980
b11100000 &
b11100001 (
1"
1,
1!
1/
1%
#9000
0%
#9020
1!
1/
1"
1,
b11100001 &
b11100010 (
1%
#9040
0%
#9060
b11100010 &
b11100011 (
1"
1,
1!
1/
1%
#9080
0%
#9100
1!
1/
1"
1,
b11100011 &
b11100100 (
1%
#9120
0%
#9140
b11100100 &
b11100101 (
1"
1,
1!
1/
1%
#9160
0%
#9180
1!
1/
1"
1,
b11100101 &
b11100110 (
1%
#9200
0%
#9220
b11100110 &
b11100111 (
1"
1,
1!
1/
1%
#9240
0%
#9260
1!
1/
1"
1,
b11100111 &
b11101000 (
1%
#9280
0%
#9300
b11101000 &
b11101001 (
1"
1,
1!
1/
1%
#9320
0%
#9340
1!
1/
1"
1,
b11101001 &
b11101010 (
1%
#9360
0%
#9380
b11101010 &
b11101011 (
1"
1,
1!
1/
1%
#9400
0%
#9420
1!
1/
1"
1,
b11101011 &
b11101100 (
1%
#9440
0%
#9460
b11101100 &
b11101101 (
1"
1,
1!
1/
1%
#9480
0%
#9500
1!
1/
1"
1,
b11101101 &
b11101110 (
1%
#9520
0%
#9540
b11101110 &
b11101111 (
1"
1,
1!
1/
1%
#9560
0%
#9580
1!
1/
1"
1,
b11101111 &
b11110000 (
1%
#9600
0%
#9620
b11110000 &
b11110001 (
1"
1,
1!
1/
1%
#9640
0%
#9660
1!
1/
1"
1,
b11110001 &
b11110010 (
1%
#9680
0%
#9700
b11110010 &
b11110011 (
1"
1,
1!
1/
1%
#9720
0%
#9740
1!
1/
1"
1,
b11110011 &
b11110100 (
1%
#9760
0%
#9780
b11110100 &
b11110101 (
1"
1,
1!
1/
1%
#9800
0%
#9820
1!
1/
1"
1,
b11110101 &
b11110110 (
1%
#9840
0%
#9860
b11110110 &
b11110111 (
1"
1,
1!
1/
1%
#9880
0%
#9900
1!
1/
1"
1,
b11110111 &
b11111000 (
1%
#9920
0%
#9940
b11111000 &
b11111001 (
1"
1,
1!
1/
1%
#9960
0%
#9980
1!
1/
1"
1,
b11111001 &
b11111010 (
1%
#10000
0%
#10020
b11111010 &
b11111011 (
1"
1,
1!
1/
1%
#10040
0%
#10060
1!
1/
1"
1,
b11111011 &
b11111100 (
1%
#10080
0%
#10100
b11111100 &
b11111101 (
1"
1,
1!
1/
1%
#10120
0%
#10140
1!
1/
1"
1,
b11111101 &
b11111110 (
1%
#10160
0%
#10180
b11111110 &
b11111111 (
1"
1,
1!
1/
1%
#10200
0%
#10220
1!
1/
1"
1,
b11111111 &
b100000000 (
1%
#10240
0%
#10260
b100000000 &
b100000001 (
1"
1,
1!
1/
1%
#10280
0%
#10300
1!
1/
1"
1,
b100000001 &
b100000010 (
1%
#10320
0%
#10340
b100000010 &
b100000011 (
1"
1,
1!
1/
1%
#10360
0%
#10380
1!
1/
1"
1,
b100000011 &
b100000100 (
1%
#10400
0%
#10420
b100000100 &
b100000101 (
1"
1,
1!
1/
1%
#10440
0%
#10460
1!
1/
1"
1,
b100000101 &
b100000110 (
1%
#10480
0%
#10500
b100000110 &
b100000111 (
1"
1,
1!
1/
1%
#10520
0%
#10540
1!
1/
1"
1,
b100000111 &
b100001000 (
1%
#10560
0%
#10580
b100001000 &
b100001001 (
1"
1,
1!
1/
1%
#10600
0%
#10620
1!
1/
1"
1,
b100001001 &
b100001010 (
1%
#10640
0%
#10660
b100001010 &
b100001011 (
1"
1,
1!
1/
1%
#10680
0%
#10700
1!
1/
1"
1,
b100001011 &
b100001100 (
1%
#10720
0%
#10740
b100001100 &
b100001101 (
1"
1,
1!
1/
1%
#10760
0%
#10780
1!
1/
1"
1,
b100001101 &
b100001110 (
1%
#10800
0%
#10820
b100001110 &
b100001111 (
1"
1,
1!
1/
1%
#10840
0%
#10860
1!
1/
1"
1,
b100001111 &
b100010000 (
1%
#10880
0%
#10900
b100010000 &
b100010001 (
1"
1,
1!
1/
1%
#10920
0%
#10940
1!
1/
1"
1,
b100010001 &
b100010010 (
1%
#10960
0%
#10980
b100010010 &
b100010011 (
1"
1,
1!
1/
1%
#11000
0%
#11020
1!
1/
1"
1,
b100010011 &
b100010100 (
1%
#11040
0%
#11060
b100010100 &
b100010101 (
1"
1,
1!
1/
1%
#11080
0%
#11100
1!
1/
1"
1,
b100010101 &
b100010110 (
1%
#11120
0%
#11140
b100010110 &
b100010111 (
1"
1,
1!
1/
1%
#11160
0%
#11180
1!
1/
1"
1,
b100010111 &
b100011000 (
1%
#11200
0%
#11220
b100011000 &
b100011001 (
1"
1,
1!
1/
1%
#11240
0%
#11260
1!
1/
1"
1,
b100011001 &
b100011010 (
1%
#11280
0%
#11300
b100011010 &
b100011011 (
1"
1,
1!
1/
1%
#11320
0%
#11340
1!
1/
1"
1,
b100011011 &
b100011100 (
1%
#11360
0%
#11380
b100011100 &
b100011101 (
1"
1,
1!
1/
1%
#11400
0%
#11420
1!
1/
1"
1,
b100011101 &
b100011110 (
1%
#11440
0%
#11460
b100011110 &
b100011111 (
1"
1,
1!
1/
1%
#11480
0%
#11500
1!
1/
1"
1,
b100011111 &
b100100000 (
1%
#11520
0%
#11540
b100100000 &
b100100001 (
1"
1,
1!
1/
1%
#11560
0%
#11580
1!
1/
1"
1,
b100100001 &
b100100010 (
1%
#11600
0%
#11620
b100100010 &
b100100011 (
1"
1,
1!
1/
1%
#11640
0%
#11660
1!
1/
1"
1,
b100100011 &
b100100100 (
1%
#11680
0%
#11700
b100100100 &
b100100101 (
1"
1,
1!
1/
1%
#11720
0%
#11740
1!
1/
1"
1,
b100100101 &
b100100110 (
1%
#11760
0%
#11780
b100100110 &
b100100111 (
1"
1,
1!
1/
1%
#11800
0%
#11820
1!
1/
1"
1,
b100100111 &
b100101000 (
1%
#11840
0%
#11860
b100101000 &
b100101001 (
1"
1,
1!
1/
1%
#11880
0%
#11900
1!
1/
1"
1,
b100101001 &
b100101010 (
1%
#11920
0%
#11940
b100101010 &
b100101011 (
1"
1,
1!
1/
1%
#11960
0%
#11980
1!
1/
1"
1,
b100101011 &
b100101100 (
1%
#12000
0%
#12020
b100101100 &
b100101101 (
1"
1,
1!
1/
1%
#12040
0%
#12060
1!
1/
1"
1,
b100101101 &
b100101110 (
1%
#12080
0%
#12100
b100101110 &
b100101111 (
1"
1,
1!
1/
1%
#12120
0%
#12140
1!
1/
1"
1,
b100101111 &
b100110000 (
1%
#12160
0%
#12180
b100110000 &
b100110001 (
1"
1,
1!
1/
1%
#12200
0%
#12220
1!
1/
1"
1,
b100110001 &
b100110010 (
1%
#12240
0%
#12260
b100110010 &
b100110011 (
1"
1,
1!
1/
1%
#12280
0%
#12300
1!
1/
1"
1,
b100110011 &
b100110100 (
1%
#12320
0%
#12340
b100110100 &
b100110101 (
1"
1,
1!
1/
1%
#12360
0%
#12380
1!
1/
1"
1,
b100110101 &
b100110110 (
1%
#12400
0%
#12420
b100110110 &
b100110111 (
1"
1,
1!
1/
1%
#12440
0%
#12460
1!
1/
1"
1,
b100110111 &
b100111000 (
1%
#12480
0%
#12500
b100111000 &
b100111001 (
1"
1,
1!
1/
1%
#12520
0%
#12540
1!
1/
1"
1,
b100111001 &
b100111010 (
1%
#12560
0%
#12580
b100111010 &
b100111011 (
1"
1,
1!
1/
1%
#12600
0%
#12620
1!
1/
1"
1,
b100111011 &
b100111100 (
1%
#12640
0%
#12660
b100111100 &
b100111101 (
1"
1,
1!
1/
1%
#12680
0%
