REFERENCE_FILES/Binary_To_Seven_Seg.v
module Binary_To_Seven_Seg(

  input CLK, 
  input [3:0] binary_num,
  output o_S1_A, 
  output o_S1_B, 
  output o_S1_C, 
  output o_S1_D,
  output o_S1_E, 
  output o_S1_F, 
  output o_S1_G
  );
  
reg [6:0] hex_encoding = 7'h00;

always @(posedge CLK)begin
  case(binary_num)
    4'b0000 : hex_encoding <= 7'h7E;
    4'b0001 : hex_encoding <= 7'h30;
    4'b0010 : hex_encoding <= 7'h6D;
    4'b0011 : hex_encoding <= 7'h79;
    4'b0100 : hex_encoding <= 7'h33;
    4'b0101 : hex_encoding <= 7'h5B;
    4'b0110 : hex_encoding <= 7'h5F;
    4'b0111 : hex_encoding <= 7'h70;
    4'b1000 : hex_encoding <= 7'h7F;
    4'b1001 : hex_encoding <= 7'h7B;
    4'b1010 : hex_encoding <= 7'h77;
    4'b1011 : hex_encoding <= 7'h1F;
    4'b1100 : hex_encoding <= 7'h4E;
    4'b1101 : hex_encoding <= 7'h3D;
    4'b1110 : hex_encoding <= 7'h4F;
    4'b1111 : hex_encoding <= 7'h47;
    endcase
  end

assign o_S1_A = hex_encoding[6];
assign o_S1_B = hex_encoding[5];
assign o_S1_C = hex_encoding[4];
assign o_S1_D = hex_encoding[3];
assign o_S1_E = hex_encoding[2];
assign o_S1_F = hex_encoding[1];
assign o_S1_G = hex_encoding[0];

endmodule

UART_TX/UART_RX.v
/////////////////////////////////////////////////////////////////////
// File Downloaded from http://www.nandland.com
/////////////////////////////////////////////////////////////////////
// This file contains the UART Receiver.  This receiver is able to
// receive 8 bits of serial data, one start bit, one stop bit,
// and no parity bit.  When receive is complete o_rx_dv will be
// driven high for one clock cycle.
// 
// Set Parameter CLKS_PER_BIT as follows:
// CLKS_PER_BIT = (Frequency of CLK)/(Frequency of UART)
// Example: 25 MHz Clock, 115200 baud UART
// (25000000)/(115200) = 217
 
module UART_RX
  #(parameter CLKS_PER_BIT = 217)
  (
   input        CLK,
   input        RX,
   output       o_RX_DV,
   output [7:0] o_RX_Byte
   );
   
  parameter IDLE         = 3'b000;
  parameter RX_START_BIT = 3'b001;
  parameter RX_DATA_BITS = 3'b010;
  parameter RX_STOP_BIT  = 3'b011;
  parameter CLEANUP      = 3'b100;
  
  reg [7:0]     r_Clock_Count = 0;
  reg [2:0]     r_Bit_Index   = 0; //8 bits total
  reg [7:0]     r_RX_Byte     = 0;
  reg           r_RX_DV       = 0;
  reg [2:0]     r_SM_Main     = 0;
  
  
  // Purpose: Control RX state machine
  always @(posedge CLK)
  begin
      
    case (r_SM_Main)
      IDLE :
        begin
          r_RX_DV       <= 1'b0;
          r_Clock_Count <= 0;
          r_Bit_Index   <= 0;
          
          if (RX == 1'b0)          // Start bit detected
            r_SM_Main <= RX_START_BIT;
          else
            r_SM_Main <= IDLE;
        end
      
      // Check middle of start bit to make sure it's still low
      RX_START_BIT :
        begin
          if (r_Clock_Count == (CLKS_PER_BIT-1)/2)
          begin
            if (RX == 1'b0)
            begin
              r_Clock_Count <= 0;  // reset counter, found the middle
              r_SM_Main     <= RX_DATA_BITS;
            end
            else
              r_SM_Main <= IDLE;
          end
          else
          begin
            r_Clock_Count <= r_Clock_Count + 1;
            r_SM_Main     <= RX_START_BIT;
          end
        end // case: RX_START_BIT
      
      
      // Wait CLKS_PER_BIT-1 clock cycles to sample serial data
      RX_DATA_BITS :
        begin
          if (r_Clock_Count < CLKS_PER_BIT-1)
          begin
            r_Clock_Count <= r_Clock_Count + 1;
            r_SM_Main     <= RX_DATA_BITS;
          end
          else
          begin
            r_Clock_Count          <= 0;
            r_RX_Byte[r_Bit_Index] <= RX;
            
            // Check if we have received all bits
            if (r_Bit_Index < 7)
            begin
              r_Bit_Index <= r_Bit_Index + 1;
              r_SM_Main   <= RX_DATA_BITS;
            end
            else
            begin
              r_Bit_Index <= 0;
              r_SM_Main   <= RX_STOP_BIT;
            end
          end
        end // case: RX_DATA_BITS
      
      
      // Receive Stop bit.  Stop bit = 1
      RX_STOP_BIT :
        begin
          // Wait CLKS_PER_BIT-1 clock cycles for Stop bit to finish
          if (r_Clock_Count < CLKS_PER_BIT-1)
          begin
            r_Clock_Count <= r_Clock_Count + 1;
     	    r_SM_Main     <= RX_STOP_BIT;
          end
          else
          begin
       	    r_RX_DV       <= 1'b1;
            r_Clock_Count <= 0;
            r_SM_Main     <= CLEANUP;
          end
        end // case: RX_STOP_BIT
      
      
      // Stay here 1 clock
      CLEANUP :
        begin
          r_SM_Main <= IDLE;
          r_RX_DV   <= 1'b0;
        end
      
      
      default :
        r_SM_Main <= IDLE;
      
    endcase
  end    
  
  assign o_RX_DV   = r_RX_DV;
  assign o_RX_Byte = r_RX_Byte;
  
endmodule // UART_RX

UART_TX/UART_TX.sv
/////////////////////////////////////////////////////////////////////
// File Downloaded from http://www.nandland.com
/////////////////////////////////////////////////////////////////////
// This file contains the UART Receiver.  This receiver is able to
// receive 8 bits of serial data, one start bit, one stop bit,
// and no parity bit.  When receive is complete o_rx_dv will be
// driven high for one clock cycle.
// 
// Set Parameter CLKS_PER_BIT as follows:
// CLKS_PER_BIT = (Frequency of CLK)/(Frequency of UART)
// Example: 25 MHz Clock, 115200 baud UART
// (25000000)/(115200) = 217
 
module UART_TX
  #(parameter CLKS_PER_BIT = 217)
  (
   input        CLK,
   input 	i_TX_DV,
   input [7:0] 	i_TX_Byte,
   output reg   TX,
   output reg	o_TX_Active,
   output reg	o_TX_Done);
   
  parameter IDLE         = 3'b000;
  parameter TX_START_BIT = 3'b001;
  parameter TX_DATA_BITS = 3'b010;
  parameter TX_STOP_BIT  = 3'b011; 
  parameter CLEANUP      = 3'b100;
  
  reg [2:0]     r_SM_Main     = 0;
  reg [7:0]     r_Clock_Count = 0;
  reg [2:0]     r_Bit_Index   = 0; //8 bits total
  reg [7:0]	r_TX_Data     = 0;
  reg		r_TX_Active   = 0;
  reg 		r_TX_Done     = 0;
  
  
  // Purpose: Control TX state machine
  always @(posedge CLK) //or nonedge i_Rst_L)
  begin
      
    case (r_SM_Main)
      IDLE :
        begin
          TX	        <= 1'b1;
          r_TX_Done	<= 1'b0;
          r_Clock_Count <= 0;
          r_Bit_Index   <= 0;
          
          if (i_TX_DV == 1'b1)          // Start bit detected
            begin
            r_TX_Active <= 1'b1;
            r_TX_Data <= i_TX_Byte;
            r_SM_Main <= TX_START_BIT;
            end
          else
            begin
            r_SM_Main <= IDLE;
            end
        end
      
      // Check middle of start bit to make sure it's still low
      TX_START_BIT :
        begin
          TX <= 1'b0;
          if (r_Clock_Count == CLKS_PER_BIT-1)
          begin
              r_Clock_Count <= 0;
              r_SM_Main     <= TX_DATA_BITS;
          end
          else
          begin
            r_Clock_Count <= r_Clock_Count + 1;
            r_SM_Main     <= TX_START_BIT;
          end
        end // case: TX_START_BIT
      
      
      // Wait CLKS_PER_BIT-1 clock cycles to sample serial data
      TX_DATA_BITS :
        begin
          TX <= r_TX_Data[r_Bit_Index];
          if (r_Clock_Count < CLKS_PER_BIT-1)
          begin
            r_Clock_Count <= r_Clock_Count + 1;
            r_SM_Main     <= TX_DATA_BITS;
          end
          else
          begin
            r_Clock_Count          <= 0;
            // Check if we have received all bits
            if (r_Bit_Index < 7)
            begin
              r_Bit_Index <= r_Bit_Index + 1;
              r_SM_Main   <= TX_DATA_BITS;
            end
            else
            begin
              r_Bit_Index <= 0;
              r_SM_Main   <= TX_STOP_BIT;
            end
          end
        end // case: TX_DATA_BITS
      
      
      // Receive Stop bit.  Stop bit = 1
      TX_STOP_BIT :
        begin
          TX <= 1'b1;
          // Wait CLKS_PER_BIT-1 clock cycles for Stop bit to finish
          if (r_Clock_Count < CLKS_PER_BIT-1)
          begin
            r_Clock_Count <= r_Clock_Count + 1;
     	    r_SM_Main     <= TX_STOP_BIT;
          end
          else
          begin
       	    r_TX_Done       <= 1'b1;
            r_Clock_Count <= 0;
            r_SM_Main     <= CLEANUP;
            r_TX_Active	  <= 1'b0;
          end
        end // case: TX_STOP_BIT
      
      CLEANUP :
	begin
	  r_TX_Done <= 1'b1;
	  r_SM_Main <= IDLE;
	end
      
      default :
        r_SM_Main <= IDLE;
    endcase
  end    
  
  assign o_TX_Active = r_TX_Active;
  assign o_TX_Done   = r_TX_Done;
  
endmodule // UART_TX

UART_TX/UART_TX_top.v
//https://wiki.emacinc.com/wiki/Getting_Started_With_Minicom
//right side usb is serial port ttyUSB1
// minicom instructions:
// UART RX is configured under minicom port created titled ttyS12
// sudo minicom -s       or ttyS12 to configure existing instance
// configure serial port settings in minicom to be 115200 8N1
// 8 = 8 data bits, N = no parity, 1 = stop bit 1
// delete all modem and dialing stuff from A-H and K
// RUN MINICOM: minicom -D /dev/ttyUSB1
//okay so i think ttyS12 is just the configuration of USB1 i made?

module UART_TX_top(
input CLK,
input RX,
output TX,
output S1_A, 
output S1_B, 
output S1_C, 
output S1_D,
output S1_E, 
output S1_F, 
output S1_G,
output S2_A, 
output S2_B, 
output S2_C, 
output S2_D,
output S2_E, 
output S2_F, 
output S2_G);

wire w_RX_DV;
wire [7:0] w_RX_Byte;
wire w_TX_Active, w_TX_Serial;

//wire w_RX;
wire w_S1_A;
wire w_S1_B;
wire w_S1_C;
wire w_S1_D;
wire w_S1_E;
wire w_S1_F;
wire w_S1_G;
wire w_S2_A;
wire w_S2_B;
wire w_S2_C;
wire w_S2_D;
wire w_S2_E;
wire w_S2_F;
wire w_S2_G;

 UART_TX #(.CLKS_PER_BIT(217)) UART_TX_Inst
  (.CLK(CLK),
   .i_TX_DV(w_RX_DV),
   .i_TX_Byte(w_RX_Byte), 
   .TX(w_TX_Serial),
   .o_TX_Active(w_TX_Active),
   .o_TX_Done());
//sudo apt-get install chromium-browser
assign TX = w_TX_Active ? w_TX_Serial : 1'b1;

UART_RX #(.CLKS_PER_BIT(217)) UART_RX_Inst(
.CLK(CLK),
.RX(RX),
.o_RX_DV(w_RX_DV),
.o_RX_Byte(w_RX_Byte));

Binary_To_Seven_Seg binary_to_7seg_Inst1(
.CLK(CLK),
.binary_num(w_RX_Byte[7:4]),
.o_S1_A(w_S1_A),
.o_S1_B(w_S1_B),
.o_S1_C(w_S1_C),
.o_S1_D(w_S1_D),
.o_S1_E(w_S1_E),
.o_S1_F(w_S1_F),
.o_S1_G(w_S1_G));

assign S1_A = ~w_S1_A;
assign S1_B = ~w_S1_B;
assign S1_C = ~w_S1_C;
assign S1_D = ~w_S1_D;
assign S1_E = ~w_S1_E;
assign S1_F = ~w_S1_F;
assign S1_G = ~w_S1_G;

Binary_To_Seven_Seg binary_to_7seg_Inst2(
.CLK(CLK),
.binary_num(w_RX_Byte[3:0]),
.o_S1_A(w_S2_A),
.o_S1_B(w_S2_B),
.o_S1_C(w_S2_C),
.o_S1_D(w_S2_D),
.o_S1_E(w_S2_E),
.o_S1_F(w_S2_F),
.o_S1_G(w_S2_G));

assign S2_A = ~w_S2_A;
assign S2_B = ~w_S2_B;
assign S2_C = ~w_S2_C;
assign S2_D = ~w_S2_D;
assign S2_E = ~w_S2_E;
assign S2_F = ~w_S2_F;
assign S2_G = ~w_S2_G;
endmodule

UART_TX/UART_TX_tb.v
/////////////////////////////////////////////////////////////////////
// File Downloaded from http://www.nandland.com
//////////////////////////////////////////////////////////////////////

// This testbench will exercise the UART RX.
// It sends out byte 0x37, and ensures the RX receives it correctly.
`timescale 1ns/10ps
module UART_TX_TB();

  // Testbench uses a 25 MHz clock (same as Go Board)
  // Want to interface to 115200 baud UART
  // 25000000 / 115200 = 217 Clocks Per Bit.
  parameter c_CLOCK_PERIOD_NS = 40;
  parameter c_CLKS_PER_BIT    = 217;
  parameter c_BIT_PERIOD      = 8600;
  
  reg r_Clock = 0;
  reg r_TX_DV = 0;
  wire w_TX_Active, w_UART_Line;
  wire w_TX_Serial;
  reg [7:0] r_TX_Byte = 0;
  wire [7:0] w_RX_Byte;
  
  UART_RX #(.CLKS_PER_BIT(c_CLKS_PER_BIT)) UART_RX_Inst
  (.CLK(r_Clock),
     .RX(w_UART_Line),
     .o_RX_DV(w_RX_DV),
     .o_RX_Byte(w_RX_Byte)
     );
  
  UART_TX #(.CLKS_PER_BIT(c_CLKS_PER_BIT)) UART_TX_Inst
  (.CLK(r_Clock),
     .i_TX_DV(r_TX_DV),
     .i_TX_Byte(r_TX_Byte),
     .TX(w_TX_Serial),
     .o_TX_Active(w_TX_Active),
     .o_TX_Done()
     );

//When transmitter is Active, we want to put the serialized data the transmitter is in control of, onto the UART line
  assign w_UART_Line = w_TX_Active ? w_TX_Serial : 1'b1;
  
  always
    #(c_CLOCK_PERIOD_NS/2) r_Clock <= !r_Clock;
  
  // Main Testing:
  initial
    begin
      // Send a command to the UART (exercise Tx)
      @(posedge r_Clock);
      @(posedge r_Clock);
        r_TX_DV <= 1'b1;
        r_TX_Byte <= 8'h3A;
      @(posedge r_Clock);
        r_TX_DV <= 1'b0;
            
      // Check that the correct command was received
      @(posedge w_RX_DV);
      if (w_RX_Byte == 8'h3A)
        $display("Test Passed - Correct Byte Received");
      else
        $display("Test Failed - Incorrect Byte Received");
    $finish();
    end
  
  initial 
  begin
    // Required to dump signals to EPWave
    $dumpfile("dump.vcd");
    $dumpvars(0);
  end
  
endmodule

UART_TX/dump.vcd
$date
	Mon Jul 22 15:08:44 2024
$end
$version
	Icarus Verilog
$end
$timescale
	10ps
$end
$scope module UART_TX_TB $end
$var wire 1 ! w_UART_Line $end
$var wire 1 " w_TX_Serial $end
$var wire 1 # w_TX_Active $end
$var wire 1 $ w_RX_DV $end
$var wire 8 % w_RX_Byte [7:0] $end
$var parameter 32 & c_BIT_PERIOD $end
$var parameter 32 ' c_CLKS_PER_BIT $end
$var parameter 32 ( c_CLOCK_PERIOD_NS $end
$var reg 1 ) r_Clock $end
$var reg 8 * r_TX_Byte [7:0] $end
$var reg 1 + r_TX_DV $end
$scope module UART_RX_Inst $end
$var wire 1 ) CLK $end
$var wire 1 ! RX $end
$var wire 8 , o_RX_Byte [7:0] $end
$var wire 1 $ o_RX_DV $end
$var parameter 3 - CLEANUP $end
$var parameter 32 . CLKS_PER_BIT $end
$var parameter 3 / IDLE $end
$var parameter 3 0 RX_DATA_BITS $end
$var parameter 3 1 RX_START_BIT $end
$var parameter 3 2 RX_STOP_BIT $end
$var reg 3 3 r_Bit_Index [2:0] $end
$var reg 8 4 r_Clock_Count [7:0] $end
$var reg 8 5 r_RX_Byte [7:0] $end
$var reg 1 6 r_RX_DV $end
$var reg 3 7 r_SM_Main [2:0] $end
$upscope $end
$scope module UART_TX_Inst $end
$var wire 1 ) CLK $end
$var wire 8 8 i_TX_Byte [7:0] $end
$var wire 1 + i_TX_DV $end
$var wire 1 9 o_TX_Done $end
$var wire 1 # o_TX_Active $end
$var parameter 3 : CLEANUP $end
$var parameter 32 ; CLKS_PER_BIT $end
$var parameter 3 < IDLE $end
$var parameter 3 = TX_DATA_BITS $end
$var parameter 3 > TX_START_BIT $end
$var parameter 3 ? TX_STOP_BIT $end
$var reg 1 " TX $end
$var reg 3 @ r_Bit_Index [2:0] $end
$var reg 8 A r_Clock_Count [7:0] $end
$var reg 3 B r_SM_Main [2:0] $end
$var reg 1 # r_TX_Active $end
$var reg 8 C r_TX_Data [7:0] $end
$var reg 1 D r_TX_Done $end
$upscope $end
$upscope $end
$scope module UART_TX_top $end
$var wire 1 E CLK $end
$var wire 1 F RX $end
$var wire 1 G S1_A $end
$var wire 1 H S1_B $end
$var wire 1 I S1_C $end
$var wire 1 J S1_D $end
$var wire 1 K S1_E $end
$var wire 1 L S1_F $end
$var wire 1 M S1_G $end
$var wire 1 N S2_A $end
$var wire 1 O S2_B $end
$var wire 1 P S2_C $end
$var wire 1 Q S2_D $end
$var wire 1 R S2_E $end
$var wire 1 S S2_F $end
$var wire 1 T S2_G $end
$var wire 1 U w_TX_Serial $end
$var wire 1 V w_TX_Active $end
$var wire 1 W w_S2_G $end
$var wire 1 X w_S2_F $end
$var wire 1 Y w_S2_E $end
$var wire 1 Z w_S2_D $end
$var wire 1 [ w_S2_C $end
$var wire 1 \ w_S2_B $end
$var wire 1 ] w_S2_A $end
$var wire 1 ^ w_S1_G $end
$var wire 1 _ w_S1_F $end
$var wire 1 ` w_S1_E $end
$var wire 1 a w_S1_D $end
$var wire 1 b w_S1_C $end
$var wire 1 c w_S1_B $end
$var wire 1 d w_S1_A $end
$var wire 1 e w_RX_DV $end
$var wire 8 f w_RX_Byte [7:0] $end
$var wire 1 g TX $end
$scope module UART_RX_Inst $end
$var wire 1 E CLK $end
$var wire 1 F RX $end
$var wire 1 e o_RX_DV $end
$var wire 8 h o_RX_Byte [7:0] $end
$var parameter 3 i CLEANUP $end
$var parameter 32 j CLKS_PER_BIT $end
$var parameter 3 k IDLE $end
$var parameter 3 l RX_DATA_BITS $end
$var parameter 3 m RX_START_BIT $end
$var parameter 3 n RX_STOP_BIT $end
$var reg 3 o r_Bit_Index [2:0] $end
$var reg 8 p r_Clock_Count [7:0] $end
$var reg 8 q r_RX_Byte [7:0] $end
$var reg 1 r r_RX_DV $end
$var reg 3 s r_SM_Main [2:0] $end
$upscope $end
$scope module UART_TX_Inst $end
$var wire 1 E CLK $end
$var wire 8 t i_TX_Byte [7:0] $end
$var wire 1 e i_TX_DV $end
$var wire 1 u o_TX_Done $end
$var wire 1 V o_TX_Active $end
$var parameter 3 v CLEANUP $end
$var parameter 32 w CLKS_PER_BIT $end
$var parameter 3 x IDLE $end
$var parameter 3 y TX_DATA_BITS $end
$var parameter 3 z TX_START_BIT $end
$var parameter 3 { TX_STOP_BIT $end
$var reg 1 U TX $end
$var reg 3 | r_Bit_Index [2:0] $end
$var reg 8 } r_Clock_Count [7:0] $end
$var reg 3 ~ r_SM_Main [2:0] $end
$var reg 1 V r_TX_Active $end
$var reg 8 !" r_TX_Data [7:0] $end
$var reg 1 "" r_TX_Done $end
$upscope $end
$scope module binary_to_7seg_Inst1 $end
$var wire 1 E CLK $end
$var wire 4 #" binary_num [3:0] $end
$var wire 1 ^ o_S1_G $end
$var wire 1 _ o_S1_F $end
$var wire 1 ` o_S1_E $end
$var wire 1 a o_S1_D $end
$var wire 1 b o_S1_C $end
$var wire 1 c o_S1_B $end
$var wire 1 d o_S1_A $end
$var reg 7 $" hex_encoding [6:0] $end
$upscope $end
$scope module binary_to_7seg_Inst2 $end
$var wire 1 E CLK $end
$var wire 4 %" binary_num [3:0] $end
$var wire 1 W o_S1_G $end
$var wire 1 X o_S1_F $end
$var wire 1 Y o_S1_E $end
$var wire 1 Z o_S1_D $end
$var wire 1 [ o_S1_C $end
$var wire 1 \ o_S1_B $end
$var wire 1 ] o_S1_A $end
$var reg 7 &" hex_encoding [6:0] $end
$upscope $end
$upscope $end
$enddefinitions $end
$comment Show the parameter values. $end
$dumpall
b11 {
b1 z
b10 y
b0 x
b11011001 w
b100 v
b11 n
b1 m
b10 l
b0 k
b11011001 j
b100 i
b11 ?
b1 >
b10 =
b0 <
b11011001 ;
b100 :
b11 2
b1 1
b10 0
b0 /
b11011001 .
b100 -
b101000 (
b11011001 '
b10000110011000 &
$end
#0
$dumpvars
b0 &"
b0 %"
b0 $"
b0 #"
0""
b0 !"
b0 ~
b0 }
b0 |
0u
b0 t
b0 s
0r
b0 q
b0 p
b0 o
b0 h
1g
b0 f
0e
0d
0c
0b
0a
0`
0_
0^
0]
0\
0[
0Z
0Y
0X
0W
0V
xU
1T
1S
1R
1Q
1P
1O
1N
1M
1L
1K
1J
1I
1H
1G
zF
zE
0D
b0 C
b0 B
b0 A
b0 @
09
b0 8
b0 7
06
b0 5
b0 4
b0 3
b0 ,
0+
b0 *
0)
b0 %
0$
0#
x"
1!
$end
#2000
1"
1)
#4000
0)
#6000
b111010 *
b111010 8
1+
1)
#8000
0)
#10000
b1 B
b111010 C
1#
0+
1)
#12000
0)
#14000
0!
b1 A
0"
1)
#16000
0)
#18000
b1 7
b10 A
1)
#20000
0)
#22000
b11 A
b1 4
1)
#24000
0)
#26000
b10 4
b100 A
1)
#28000
0)
#30000
b101 A
b11 4
1)
#32000
0)
#34000
b100 4
b110 A
1)
#36000
0)
#38000
b111 A
b101 4
1)
#40000
0)
#42000
b110 4
b1000 A
1)
#44000
0)
#46000
b1001 A
b111 4
1)
#48000
0)
#50000
b1000 4
b1010 A
1)
#52000
0)
#54000
b1011 A
b1001 4
1)
#56000
0)
#58000
b1010 4
b1100 A
1)
#60000
0)
#62000
b1101 A
b1011 4
1)
#64000
0)
#66000
b1100 4
b1110 A
1)
#68000
0)
#70000
b1111 A
b1101 4
1)
#72000
0)
#74000
b1110 4
b10000 A
1)
#76000
0)
#78000
b10001 A
b1111 4
1)
#80000
0)
#82000
b10000 4
b10010 A
1)
#84000
0)
#86000
b10011 A
b10001 4
1)
#88000
0)
#90000
b10010 4
b10100 A
1)
#92000
0)
#94000
b10101 A
b10011 4
1)
#96000
0)
#98000
b10100 4
b10110 A
1)
#100000
0)
#102000
b10111 A
b10101 4
1)
#104000
0)
#106000
b10110 4
b11000 A
1)
#108000
0)
#110000
b11001 A
b10111 4
1)
#112000
0)
#114000
b11000 4
b11010 A
1)
#116000
0)
#118000
b11011 A
b11001 4
1)
#120000
0)
#122000
b11010 4
b11100 A
1)
#124000
0)
#126000
b11101 A
b11011 4
1)
#128000
0)
#130000
b11100 4
b11110 A
1)
#132000
0)
#134000
b11111 A
b11101 4
1)
#136000
0)
#138000
b11110 4
b100000 A
1)
#140000
0)
#142000
b100001 A
b11111 4
1)
#144000
0)
#146000
b100000 4
b100010 A
1)
#148000
0)
#150000
b100011 A
b100001 4
1)
#152000
0)
#154000
b100010 4
b100100 A
1)
#156000
0)
#158000
b100101 A
b100011 4
1)
#160000
0)
#162000
b100100 4
b100110 A
1)
#164000
0)
#166000
b100111 A
b100101 4
1)
#168000
0)
#170000
b100110 4
b101000 A
1)
#172000
0)
#174000
b101001 A
b100111 4
1)
#176000
0)
#178000
b101000 4
b101010 A
1)
#180000
0)
#182000
b101011 A
b101001 4
1)
#184000
0)
#186000
b101010 4
b101100 A
1)
#188000
0)
#190000
b101101 A
b101011 4
1)
#192000
0)
#194000
b101100 4
b101110 A
1)
#196000
0)
#198000
b101111 A
b101101 4
1)
#200000
0)
#202000
b101110 4
b110000 A
1)
#204000
0)
#206000
b110001 A
b101111 4
1)
#208000
0)
#210000
b110000 4
b110010 A
1)
#212000
0)
#214000
b110011 A
b110001 4
1)
#216000
0)
#218000
b110010 4
b110100 A
1)
#220000
0)
#222000
b110101 A
b110011 4
1)
#224000
0)
#226000
b110100 4
b110110 A
1)
#228000
0)
#230000
b110111 A
b110101 4
1)
#232000
0)
#234000
b110110 4
b111000 A
1)
#236000
0)
#238000
b111001 A
b110111 4
1)
#240000
0)
#242000
b111000 4
b111010 A
1)
#244000
0)
#246000
b111011 A
b111001 4
1)
#248000
0)
#250000
b111010 4
b111100 A
1)
#252000
0)
#254000
b111101 A
b111011 4
1)
#256000
0)
#258000
b111100 4
b111110 A
1)
#260000
0)
#262000
b111111 A
b111101 4
1)
#264000
0)
#266000
b111110 4
b1000000 A
1)
#268000
0)
#270000
b1000001 A
b111111 4
1)
#272000
0)
#274000
b1000000 4
b1000010 A
1)
#276000
0)
#278000
b1000011 A
b1000001 4
1)
#280000
0)
#282000
b1000010 4
b1000100 A
1)
#284000
0)
#286000
b1000101 A
b1000011 4
1)
#288000
0)
#290000
b1000100 4
b1000110 A
1)
#292000
0)
#294000
b1000111 A
b1000101 4
1)
#296000
0)
#298000
b1000110 4
b1001000 A
1)
#300000
0)
#302000
b1001001 A
b1000111 4
1)
#304000
0)
#306000
b1001000 4
b1001010 A
1)
#308000
0)
#310000
b1001011 A
b1001001 4
1)
#312000
0)
#314000
b1001010 4
b1001100 A
1)
#316000
0)
#318000
b1001101 A
b1001011 4
1)
#320000
0)
#322000
b1001100 4
b1001110 A
1)
#324000
0)
#326000
b1001111 A
b1001101 4
1)
#328000
0)
#330000
b1001110 4
b1010000 A
1)
#332000
0)
#334000
b1010001 A
b1001111 4
1)
#336000
0)
#338000
b1010000 4
b1010010 A
1)
#340000
0)
#342000
b1010011 A
b1010001 4
1)
#344000
0)
#346000
b1010010 4
b1010100 A
1)
#348000
0)
#350000
b1010101 A
b1010011 4
1)
#352000
0)
#354000
b1010100 4
b1010110 A
1)
#356000
0)
#358000
b1010111 A
b1010101 4
1)
#360000
0)
#362000
b1010110 4
b1011000 A
1)
#364000
0)
#366000
b1011001 A
b1010111 4
1)
#368000
0)
#370000
b1011000 4
b1011010 A
1)
#372000
0)
#374000
b1011011 A
b1011001 4
1)
#376000
0)
#378000
b1011010 4
b1011100 A
1)
#380000
0)
#382000
b1011101 A
b1011011 4
1)
#384000
0)
#386000
b1011100 4
b1011110 A
1)
#388000
0)
#390000
b1011111 A
b1011101 4
1)
#392000
0)
#394000
b1011110 4
b1100000 A
1)
#396000
0)
#398000
b1100001 A
b1011111 4
1)
#400000
0)
#402000
b1100000 4
b1100010 A
1)
#404000
0)
#406000
b1100011 A
b1100001 4
1)
#408000
0)
#410000
b1100010 4
b1100100 A
1)
#412000
0)
#414000
b1100101 A
b1100011 4
1)
#416000
0)
#418000
b1100100 4
b1100110 A
1)
#420000
0)
#422000
b1100111 A
b1100101 4
1)
#424000
0)
#426000
b1100110 4
b1101000 A
1)
#428000
0)
#430000
b1101001 A
b1100111 4
1)
#432000
0)
#434000
b1101000 4
b1101010 A
1)
#436000
0)
#438000
b1101011 A
b1101001 4
1)
#440000
0)
#442000
b1101010 4
b1101100 A
1)
#444000
0)
#446000
b1101101 A
b1101011 4
1)
#448000
0)
#450000
b1101100 4
b1101110 A
1)
#452000
0)
#454000
b1101111 A
b10 7
b0 4
1)
#456000
0)
#458000
b1 4
b1110000 A
1)
#460000
0)
#462000
b1110001 A
b10 4
1)
#464000
0)
#466000
b11 4
b1110010 A
1)
#468000
0)
#470000
b1110011 A
b100 4
1)
#472000
0)
#474000
b101 4
b1110100 A
1)
#476000
0)
#478000
b1110101 A
b110 4
1)
#480000
0)
#482000
b111 4
b1110110 A
1)
#484000
0)
#486000
b1110111 A
b1000 4
1)
#488000
0)
#490000
b1001 4
b1111000 A
1)
#492000
0)
#494000
b1111001 A
b1010 4
1)
#496000
0)
#498000
b1011 4
b1111010 A
1)
#500000
0)
#502000
b1111011 A
b1100 4
1)
#504000
0)
#506000
b1101 4
b1111100 A
1)
#508000
0)
#510000
b1111101 A
b1110 4
1)
#512000
0)
#514000
b1111 4
b1111110 A
1)
#516000
0)
#518000
b1111111 A
b10000 4
1)
#520000
0)
#522000
b10001 4
b10000000 A
1)
#524000
0)
#526000
b10000001 A
b10010 4
1)
#528000
0)
#530000
b10011 4
b10000010 A
1)
#532000
0)
#534000
b10000011 A
b10100 4
1)
#536000
0)
#538000
b10101 4
b10000100 A
1)
#540000
0)
#542000
b10000101 A
b10110 4
1)
#544000
0)
#546000
b10111 4
b10000110 A
1)
#548000
0)
#550000
b10000111 A
b11000 4
1)
#552000
0)
#554000
b11001 4
b10001000 A
1)
#556000
0)
#558000
b10001001 A
b11010 4
1)
#560000
0)
#562000
b11011 4
b10001010 A
1)
#564000
0)
#566000
b10001011 A
b11100 4
1)
#568000
0)
#570000
b11101 4
b10001100 A
1)
#572000
0)
#574000
b10001101 A
b11110 4
1)
#576000
0)
#578000
b11111 4
b10001110 A
1)
#580000
0)
#582000
b10001111 A
b100000 4
1)
#584000
0)
#586000
b100001 4
b10010000 A
1)
#588000
0)
#590000
b10010001 A
b100010 4
1)
#592000
0)
#594000
b100011 4
b10010010 A
1)
#596000
0)
#598000
b10010011 A
b100100 4
1)
#600000
0)
#602000
b100101 4
b10010100 A
1)
#604000
0)
#606000
b10010101 A
b100110 4
1)
#608000
0)
#610000
b100111 4
b10010110 A
1)
#612000
0)
#614000
b10010111 A
b101000 4
1)
#616000
0)
#618000
b101001 4
b10011000 A
1)
#620000
0)
#622000
b10011001 A
b101010 4
1)
#624000
0)
#626000
b101011 4
b10011010 A
1)
#628000
0)
#630000
b10011011 A
b101100 4
1)
#632000
0)
#634000
b101101 4
b10011100 A
1)
#636000
0)
#638000
b10011101 A
b101110 4
1)
#640000
0)
#642000
b101111 4
b10011110 A
1)
#644000
0)
#646000
b10011111 A
b110000 4
1)
#648000
0)
#650000
b110001 4
b10100000 A
1)
#652000
0)
#654000
b10100001 A
b110010 4
1)
#656000
0)
#658000
b110011 4
b10100010 A
1)
#660000
0)
#662000
b10100011 A
b110100 4
1)
#664000
0)
#666000
b110101 4
b10100100 A
1)
#668000
0)
#670000
b10100101 A
b110110 4
1)
#672000
0)
#674000
b110111 4
b10100110 A
1)
#676000
0)
#678000
b10100111 A
b111000 4
1)
#680000
0)
#682000
b111001 4
b10101000 A
1)
#684000
0)
#686000
b10101001 A
b111010 4
1)
#688000
0)
#690000
b111011 4
b10101010 A
1)
#692000
0)
#694000
b10101011 A
b111100 4
1)
#696000
0)
#698000
b111101 4
b10101100 A
1)
#700000
0)
#702000
b10101101 A
b111110 4
1)
#704000
0)
#706000
b111111 4
b10101110 A
1)
#708000
0)
#710000
b10101111 A
b1000000 4
1)
#712000
0)
#714000
b1000001 4
b10110000 A
1)
#716000
0)
#718000
b10110001 A
b1000010 4
1)
#720000
0)
#722000
b1000011 4
b10110010 A
1)
#724000
0)
#726000
b10110011 A
b1000100 4
1)
#728000
0)
#730000
b1000101 4
b10110100 A
1)
#732000
0)
#734000
b10110101 A
b1000110 4
1)
#736000
0)
#738000
b1000111 4
b10110110 A
1)
#740000
0)
#742000
b10110111 A
b1001000 4
1)
#744000
0)
#746000
b1001001 4
b10111000 A
1)
#748000
0)
#750000
b10111001 A
b1001010 4
1)
#752000
0)
#754000
b1001011 4
b10111010 A
1)
#756000
0)
